Workbook

Sheet Intro
A1: Watershed Area of Suitable Habitat (WASH) Systems Model
A3: Developed by:
A4: Ayman H. Alafifi
A5: Dept. of Civil & Env. Engineering and Utah Water Research Lab Utah State University ayman.alafifi@gmail.com
A7: Version 1.0
A8: Updated: | B8: March 9,2016 | C8: Today: | D8: =NOW() -> 45960.944
A9: Copyright and licenses: | C9: Click here
A11: Introduction
A12: WASH is a system optimization model that maximized water allocation to environmental needs while maintaining human and other beneficial uses. WASH receommends allocation of water to improve habitat quality by incorporating habitat quality indexes as objectives to maximize in a systems optimization model. WASH measures physically-available suitable habitat in three main components of most watersheds, namely riverine, floodplain and wetland habitats. WASH also highlights promising restoration and conservation sites. In addition, WASH considers, quantifies, and measures multiple sources of uncertainty in management decisions and proposes and rank alternatives for managers to restore and protect natural habitat. WASH formulation is generic and adaptable to other regulated river systems and can accomodate multiple priority species of concern. The code below desrcibes the WASH optimization model and includes the objecttive function, decision variables and constraints in addition to all the parameters that are required to run the model. The model reads all the parameters as input data from Excel and writes the results to an Excel file for fuether processing.
A25: Citation:
A28: Code on GitHub:
A29: https://github.com/ayman510/WASH
A31: Instructions:
A32: This workbook provides the input data for the WASH model. The model reads this input data into a GDX file and then load the GDX content to the model as parameters. All values of this input data is for the case of the Lower Bear River in Utah.
A33: The full network for which the data here are dervied can be found here: | F33: Lower Bear River Network
A34: To change any input value:
A35: 1. Use table (1) below for find the input parameter that you want to edit
A36: 2. Click on the hyperlink to go directly to the parameter's sheet
A37: 3. Do NOT change the index cells unless you want to change the domain of the input value
A38: 4. Edit the values of the parameters and then SAVE THE WORKBOOK
A39: 5. Run the GAMS model to see changes in the model results
A42: Table (1) Input data and parameters for the WASH model
A43: Type | B43: Name | C43: Description
A44: Set | B44: s | C44: sub-indicators. Here s1=riverine habitat s2=floodplain connectivity and s3=impounded wetlands
A45: Set | B45: j | C45: river netowrk nodes which lists all nodes in the network
A46: Set | B46: dem | C46: demand sites which are a subset of the model nodes (j)
A47: Set | B47: v | C47: reservoirs which are a subset of the model nodes (j)
A48: Set | B48: y | C48: The type(s) of priorty fish species that the model uses as indicator species
A49: Set | B49: n | C49: The type(s) of prioty vegetation species that the model uses as indicator species
A50: Set | B50: t | C50: timesteps in months (t1 =January - t12=December)
A51: Set | B51: RA_par_indx | C51: indexes to read the parameters for the reservoir volume elevation curves
A52: Set | B52: sf_par_indx | C52: indexes to read the parameters for stage-flow relationships
A53: Set | B53: wf_par_indx | C53: indexes to read the parameters for width-flow relationships
A54: Set | B54: wsi_par_indx | C54: indexes to read the parameters for wetlands suitability index relationships
... A95: Scalar | B95: b | C95: Total management budget to implement restoration actions [$]

Sheet Copyright & License
A1: Copyright (c) 2016, Ayman H. Alafifi and David E. Rosenberg
A2: All rights reserved.
A3: Redistribution and use in source and binary forms, with or without modification, are permitted provided that the following conditions are met: 1. Redistributions of source code must retain the above copyright notice, this list of conditions and the following disclaimer. 2. Redistributions in binary form must reproduce the above copyright notice, this list of conditions and the following disclaimer in the documentation and/or other materials provided with the distribution. 3. Neither the name of the copyright holder nor the names of its contributors may be used to endorse or promote products derived from this software without specific prior written permission. THIS SOFTWARE IS PROVIDED BY THE COPYRIGHT HOLDERS AND CONTRIBUTORS "AS IS" AND ANY EXPRESS OR IMPLIED WARRANTIES, INCLUDING, BUT NOT LIMITED TO, THE IMPLIED WARRANTIES OF MERCHANTABILITY AND FITNESS FOR A PARTICULAR PURPOSE ARE DISCLAIMED. IN NO EVENT SHALL THE COPYRIGHT HOLDER OR CONTRIBUTORS BE LIABLE FOR ANY DIRECT, INDIRECT, INCIDENTAL, SPECIAL, EXEMPLARY, OR CONSEQUENTIAL DAMAGES (INCLUDING, BUT NOT LIMITED TO, PROCUREMENT OF SUBSTITUTE GOODS OR SERVICES; LOSS OF USE, DATA, OR PROFITS; OR BUSINESS INTERRUPTION) HOWEVER CAUSED AND ON ANY THEORY OF LIABILITY, WHETHER IN CONTRACT, STRICT LIABILITY, OR TORT (INCLUDING NEGLIGENCE OR OTHERWISE) ARISING IN ANY WAY OUT OF THE USE OF THIS SOFTWARE, EVEN IF ADVISED OF THE POSSIBILITY OF SUCH DAMAGE.

Sheet BearRiverNetwork
D2: The Lower Bear River Network | P2: The Lower Bear River Map

Sheet SubInd
A1: riverine
A2: floodplain
A3: wetlands

Sheet FishSpp
A1: trout

Sheet VegSpp
A1: cottonwood

Sheet Month
A1: t1
A2: t2
A3: t3
A4: t4
A5: t5
A6: t6
A7: t7
A8: t8
A9: t9
A10: t10
A11: t11
A12: t12

Sheet Nodes
A1: j1
A2: j2
A3: j3
A4: j4
A5: j5
A6: j6
A7: j7
A8: j8
A9: j9
A10: j12
A11: j13
A12: j14
... A43: j45

Sheet NodesNotDemand
A1: j1
A2: j2
A3: j4
A4: j5
A5: j6
A6: j7
A7: j9
A8: j12
A9: j14
A10: j17
A11: j18
A12: j19
... A31: j45

Sheet NodeNotHeadwater
A1: j1
A2: j3
A3: j4
A4: j5
A5: j8
A6: j9
A7: j12
A8: j13
A9: j14
A10: j15
A11: j16
A12: j17
... A33: j45

Sheet MassBalanceNodes
A1: j4
A2: j5
A3: j6
A4: j9
A5: j12
A6: j14
A7: j18
A8: j19
A9: j20
A10: j21
A11: j22
A12: j23
... A25: j45

Sheet Reservoirs
A1: j1
A2: j7
A3: j17
A4: j29
A5: j33

Sheet Wetlands
A1: j23

Sheet Demand
A1: j3
A2: j39
A3: j8
A4: j13
A5: j15
A6: j16
A7: j27
A8: j28
A9: j38
A10: j41
A11: j42
A12: j44

Sheet R_indx
A1: RA_par1
A2: RA_par2
A3: RA_par3

Sheet sf_indx
A1: sf_par1
A2: sf_par2

Sheet wf_indx
A1: wf_par1
A2: wf_par2

Sheet wsi_indx
A1: wsi_par1
A2: wsi_par2

Sheet Connect
B1: j1 | C1: j2 | D1: j3 | E1: j4 | F1: j5 | G1: j6 | H1: j7 | I1: j8 | J1: j9 | K1: j12 | L1: j13 | M1: j14 | N1: j15 | O1: j16 | P1: j17 | Q1: j18 | R1: j19 | S1: j20 | T1: j21 | U1: j22 | V1: j23 | W1: j24 | X1: j25 | Y1: j26 | Z1: j27 | AA1: j28 | AB1: j29 | AC1: j30 | AD1: j31 | AE1: j32 | AF1: j33 | AG1: j34 | AH1: j35 | AI1: j36 | AJ1: j37 | AK1: j38 | AL1: j39 | AM1: j40 | AN1: j41 | AO1: j42 | AP1: j43 | AQ1: j44 | AR1: j45
A2: j1 | E2: 1
A3: j2 | D3: 1
A4: j3 | Q4: 1
A5: j4 | D5: 1 | F5: 1 | AL5: 1
A6: j5 | Q6: 1
A7: j6 | F7: 1
A8: j7 | I8: 1 | J8: 1 | O8: 1
A9: j8 | J9: 1
A10: j9 | K10: 1
A11: j12 | L11: 1 | M11: 1 | N11: 1
A12: j13 | M12: 1
A13: j14 | P13: 1
A14: j15 | M14: 1
A15: j16
A16: j17 | O16: 1 | S16: 1
A17: j18 | H17: 1
A18: j19 | S18: 1
A19: j20 | T19: 1
A20: j21 | V20: 1
A21: j22 | S21: 1
A22: j23
A23: j24 | H23: 1
A24: j25 | W24: 1
A25: j26 | X25: 1
A26: j27 | X26: 1
A27: j28 | W27: 1
A28: j29 | W28: 1 | Z28: 1 | AA28: 1 | AQ28: 1
A29: j30 | X29: 1 | Z29: 1
A30: j31 | AC30: 1
A31: j32 | AB31: 1
A32: j33 | AK32: 1 | AP32: 1
A33: j34 | AF33: 1
A34: j35 | AM34: 1
A35: j36 | H35: 1
A36: j37 | B36: 1
A37: j38 | AC37: 1
A38: j39 | Q38: 1
A39: j40 | AE39: 1 | AR39: 1
A40: j41 | AB40: 1
A41: j42 | AB41: 1
A42: j43 | AN42: 1 | AR42: 1
A43: j44 | W43: 1
A44: j45 | AE44: 1 | AO44: 1

Sheet EnvSite
B1: j1 | C1: j2 | D1: j3 | E1: j4 | F1: j5 | G1: j6 | H1: j7 | I1: j8 | J1: j9 | K1: j10 | L1: j11 | M1: j12 | N1: j13 | O1: j14 | P1: j15 | Q1: j16 | R1: j17 | S1: j18 | T1: j19 | U1: j20 | V1: j21 | W1: j22 | X1: j23 | Y1: j24 | Z1: j25 | AA1: j26 | AB1: j27 | AC1: j28 | AD1: j29 | AE1: j30 | AF1: j31 | AG1: j32 | AH1: j33 | AI1: j34 | AJ1: j35 | AK1: j36 | AL1: j37 | AM1: j38 | AN1: j39 | AO1: j40 | AP1: j41 | AQ1: j42 | AR1: j43 | AS1: j44 | AT1: j45
A2: j1 | E2: 1
A3: j2
A4: j3
A5: j4 | F5: 1
A6: j5 | S6: 1
A7: j6 | F7: 1
A8: j7 | J8: 1
A9: j8
A10: j9 | M10: 1
A11: j10
A12: j11
A13: j12 | O13: 1
A14: j13
A15: j14 | R15: 1
A16: j15
A17: j16
A18: j17 | U18: 1
A19: j18 | H19: 1
A20: j19 | U20: 1
A21: j20 | V21: 1
A22: j21 | X22: 1
A23: j22
A24: j23
A25: j24 | H25: 1
A26: j25 | Y26: 1
A27: j26
A28: j27
A29: j28
A30: j29 | Y30: 1
A31: j30 | Z31: 1
A32: j31 | AE32: 1
A33: j32 | AD33: 1
A34: j33 | AR34: 1
A35: j34 | AH35: 1
A36: j35 | AO36: 1
A37: j36
A38: j37 | B38: 1
A39: j38
A40: j39
A41: j40 | AG41: 1
A42: j41
A43: j42
A44: j43 | AT44: 1
A45: j44
A46: j45 | AG46: 1

Sheet Diversions
B1: j1 | C1: j2 | D1: j3 | E1: j4 | F1: j5 | G1: j6 | H1: j7 | I1: j8 | J1: j9 | K1: j12 | L1: j13 | M1: j14 | N1: j15 | O1: j16 | P1: j17 | Q1: j18 | R1: j19 | S1: j20 | T1: j21 | U1: j22 | V1: j23 | W1: j24 | X1: j25 | Y1: j26 | Z1: j27 | AA1: j28 | AB1: j29 | AC1: j30 | AD1: j31 | AE1: j32 | AF1: j33 | AG1: j34 | AH1: j35 | AI1: j36 | AJ1: j37 | AK1: j38 | AL1: j39 | AM1: j40 | AN1: j41 | AO1: j42 | AP1: j43 | AQ1: j44 | AR1: j45
A2: j1
A3: j2 | D3: 1
A4: j3
A5: j4 | D5: 1 | AL5: 1
A6: j5
A7: j6
A8: j7 | I8: 1 | O8: 1
A9: j8
A10: j9
A11: j12 | L11: 1 | N11: 1
A12: j13
A13: j14
A14: j15
A15: j16
A16: j17 | O16: 1
A17: j18
A18: j19
A19: j20
A20: j21
A21: j22
A22: j23
A23: j24
A24: j25
A25: j26
A26: j27
A27: j28
A28: j29 | Z28: 1 | AA28: 1 | AQ28: 1
A29: j30 | Z29: 1
A30: j31
A31: j32
A32: j33 | AK32: 1
A33: j34
A34: j35
A35: j36
A36: j37
A37: j38
A38: j39
A39: j40
A40: j41
A41: j42
A42: j43 | AN42: 1
A43: j44
A44: j45 | AO44: 1

Sheet ReturnFlow
B1: j1 | C1: j2 | D1: j3 | E1: j4 | F1: j5 | G1: j6 | H1: j7 | I1: j8 | J1: j9 | K1: j12 | L1: j13 | M1: j14 | N1: j15 | O1: j16 | P1: j17 | Q1: j18 | R1: j19 | S1: j20 | T1: j21 | U1: j22 | V1: j23 | W1: j24 | X1: j25 | Y1: j26 | Z1: j27 | AA1: j28 | AB1: j29 | AC1: j30 | AD1: j31 | AE1: j32 | AF1: j33 | AG1: j34 | AH1: j35 | AI1: j36 | AJ1: j37 | AK1: j38 | AL1: j39 | AM1: j40 | AN1: j41 | AO1: j42 | AP1: j43 | AQ1: j44 | AR1: j45
A2: j1
A3: j2
A4: j3 | Q4: 1
A5: j4
A6: j5
A7: j6
A8: j7
A9: j8 | J9: 1
A10: j9
A11: j12
A12: j13 | M12: 1
A13: j14
A14: j15 | M14: 1
A15: j16
A16: j17
A17: j18
A18: j19
A19: j20
A20: j21
A21: j22
A22: j23
A23: j24
A24: j25
A25: j26
A26: j27 | X26: 1
A27: j28 | W27: 1
A28: j29
A29: j30
A30: j31
A31: j32
A32: j33
A33: j34
A34: j35
A35: j36
A36: j37
A37: j38 | AC37: 1
A38: j39 | Q38: 1
A39: j40
A40: j41 | AB40: 1
A41: j42 | AB41: 1
A42: j43
A43: j44 | W43: 1
A44: j45

Sheet WetlandsSites
B1: j1 | C1: j2 | D1: j3 | E1: j4 | F1: j5 | G1: j6 | H1: j7 | I1: j8 | J1: j9 | K1: j10 | L1: j11 | M1: j12 | N1: j13 | O1: j14 | P1: j15 | Q1: j16 | R1: j17 | S1: j18 | T1: j19 | U1: j20 | V1: j21 | W1: j22 | X1: j23 | Y1: j24 | Z1: j25 | AA1: j26 | AB1: j27 | AC1: j28 | AD1: j29 | AE1: j30 | AF1: j31 | AG1: j32 | AH1: j33 | AI1: j34 | AJ1: j35 | AK1: j36 | AL1: j37 | AM1: j38 | AN1: j39 | AO1: j40 | AP1: j41 | AQ1: j42 | AR1: j43 | AS1: j44 | AT1: j45
A2: j1
A3: j2
A4: j3
A5: j4
A6: j5
A7: j6
A8: j7
A9: j8
A10: j9
A11: j10
A12: j11
A13: j12
... A21: j20
A22: j21 | X22: 1
A23: j22
A24: j23
A25: j24
A26: j25
A27: j26
A28: j27
A29: j28
A30: j29
A31: j30
A32: j31
A33: j32
A34: j33
... A46: j45

Sheet LinktoReservoir
B1: j1 | C1: j2 | D1: j3 | E1: j4 | F1: j5 | G1: j6 | H1: j7 | I1: j8 | J1: j9 | K1: j12 | L1: j13 | M1: j14 | N1: j15 | O1: j16 | P1: j17 | Q1: j18 | R1: j19 | S1: j20 | T1: j21 | U1: j22 | V1: j23 | W1: j24 | X1: j25 | Y1: j26 | Z1: j27 | AA1: j28 | AB1: j29 | AC1: j30 | AD1: j31 | AE1: j32 | AF1: j33 | AG1: j34 | AH1: j35 | AI1: j36 | AJ1: j37 | AK1: j38 | AL1: j39 | AM1: j40 | AN1: j41 | AO1: j42 | AP1: j43 | AQ1: j44 | AR1: j45
A2: j1
A3: j2
A4: j3
A5: j4
A6: j5
A7: j6
A8: j7
A9: j8
A10: j9
A11: j12
A12: j13
A13: j14 | P13: 1
A14: j15
A15: j16
A16: j17
A17: j18 | H17: 1
A18: j19
A19: j20
A20: j21
A21: j22
A22: j23
A23: j24 | H23: 1
A24: j25
A25: j26
A26: j27
A27: j28
A28: j29
A29: j30
A30: j31
A31: j32 | AB31: 1
A32: j33
A33: j34 | AF33: 1
A34: j35
A35: j36 | H35: 1
A36: j37 | B36: 1
A37: j38
A38: j39
A39: j40
A40: j41 | AB40: 1
A41: j42 | AB41: 1
A42: j43
A43: j44
A44: j45

Sheet LinkOutReservoir
B1: j1 | C1: j2 | D1: j3 | E1: j4 | F1: j5 | G1: j6 | H1: j7 | I1: j8 | J1: j9 | K1: j12 | L1: j13 | M1: j14 | N1: j15 | O1: j16 | P1: j17 | Q1: j18 | R1: j19 | S1: j20 | T1: j21 | U1: j22 | V1: j23 | W1: j24 | X1: j25 | Y1: j26 | Z1: j27 | AA1: j28 | AB1: j29 | AC1: j30 | AD1: j31 | AE1: j32 | AF1: j33 | AG1: j34 | AH1: j35 | AI1: j36 | AJ1: j37 | AK1: j38 | AL1: j39 | AM1: j40 | AN1: j41 | AO1: j42 | AP1: j43 | AQ1: j44 | AR1: j45
A2: j1 | E2: 1
A3: j2
A4: j3
A5: j4
A6: j5
A7: j6
A8: j7 | I8: 1 | J8: 1 | O8: 1
A9: j8
A10: j9
A11: j12
A12: j13
A13: j14
A14: j15
A15: j16
A16: j17 | O16: 1 | S16: 1
A17: j18
A18: j19
A19: j20
A20: j21
A21: j22
A22: j23
A23: j24
A24: j25
A25: j26
A26: j27
A27: j28
A28: j29 | W28: 1 | Z28: 1 | AA28: 1 | AQ28: 1
A29: j30
A30: j31
A31: j32
A32: j33 | AK32: 1 | AP32: 1
A33: j34
A34: j35
A35: j36
A36: j37
A37: j38
A38: j39
A39: j40
A40: j41
A41: j42
A42: j43
A43: j44
A44: j45

Sheet rsiIndex
A1: rsi_par1
A2: rsi_par2
A3: rsi_par3
A4: rsi_par4
A5: Func_typ

Sheet rsiEQ
D1: Func_typ | E1: rsi_par1 | F1: rsi_par2 | G1: rsi_par3 | H1: rsi_par4 | N1: Trout | W1: Base case | AC1: With Sucker
A2: j37 | B2: j1 | C2: t1 | D2: 2 | E2: 0 | F2: 0 | G2: 0 | H2: 1 | N2: Months | O2: Depth (m) | P2: Location | Q2: rsi_par1 | R2: rsi_par2 | S2: rsi_par3 | T2: rsi_par4 | W2: 0.027072261 | X2: 0.99326974 | Y2: 0.42271431 | Z2: 0.050595078 | AC2: 0.027072261 | AD2: 0.99326974 | AE2: 0.42271431 | AF2: 0.050595078
A3: j37 | B3: j1 | C3: t2 | D3: 2 | E3: 0 | F3: 0 | G3: 0 | H3: 1 | M3: Adul/Juv | N3: Sep-Mar | O3: 0.75 – 0.30 | Q3: 0 | R3: 1 | S3: 0.42240891 | T3: 0.04896029 | W3: 0.027072261 | X3: 0.99326974 | Y3: 0.42271431 | Z3: 0.050595078 | AC3: 0.027072261 | AD3: 0.99326974 | AE3: 0.42271431 | AF3: 0.050595078
A4: j37 | B4: j1 | C4: t3 | D4: 2 | E4: 0 | F4: 0 | G4: 0 | H4: 3 | M4: Fry | N4: Apr-Aug | O4: 0.45 – 0.20 | Q4: 0 | R4: 1 | S4: 0.2888249 | T4: 0.01979619 | W4: 0.027072261 | X4: 0.99326974 | Y4: 0.42271431 | Z4: 0.050595078 | AC4: 0.027072261 | AD4: 0.99326974 | AE4: 0.42271431 | AF4: 0.050595078
A5: j37 | B5: j1 | C5: t4 | D5: 2 | E5: 0 | F5: 0 | G5: 0 | H5: 3 | W5: 0.029313504 | X5: 0.98886831 | Y5: 0.24676178 | Z5: 0.024946824 | AC5: 0.029313504 | AD5: 0.98886831 | AE5: 0.24676178 | AF5: 0.024946824
A6: j37 | B6: j1 | C6: t5 | D6: 2 | E6: 0 | F6: 0 | G6: 0 | H6: 3 | W6: 0.029313504 | X6: 0.98886831 | Y6: 0.24676178 | Z6: 0.024946824 | AC6: 0.029313504 | AD6: 0.98886831 | AE6: 0.24676178 | AF6: 0.024946824
A7: j37 | B7: j1 | C7: t6 | D7: 2 | E7: 0 | F7: 0 | G7: 0 | H7: 3 | W7: 0.029313504 | X7: 0.98886831 | Y7: 0.24676178 | Z7: 0.024946824 | AC7: 0.029313504 | AD7: 0.98886831 | AE7: 0.24676178 | AF7: 0.024946824
A8: j37 | B8: j1 | C8: t7 | D8: 2 | E8: 0 | F8: 0 | G8: 0 | H8: 3 | N8: Sucker | W8: 0.029313504 | X8: 0.98886831 | Y8: 0.24676178 | Z8: 0.024946824 | AC8: 0.029313504 | AD8: 0.98886831 | AE8: 0.24676178 | AF8: 0.024946824
A9: j37 | B9: j1 | C9: t8 | D9: 2 | E9: 0 | F9: 0 | G9: 0 | H9: 3 | N9: Months | O9: Depth (m) | Q9: rsi_par1 | R9: rsi_par2 | S9: rsi_par3 | T9: rsi_par4 | W9: 0.029313504 | X9: 0.98886831 | Y9: 0.24676178 | Z9: 0.024946824 | AC9: 0.029313504 | AD9: 0.98886831 | AE9: 0.24676178 | AF9: 0.024946824
A10: j37 | B10: j1 | C10: t9 | D10: 2 | E10: 0 | F10: 0 | G10: 0 | H10: 1 | M10: Adul/Juv | N10: Sep-Mar | O10: 1 | Q10: 0 | R10: 1 | S10: 0.48147111 | T10: 0.10105984 | W10: 0.027072261 | X10: 0.99326974 | Y10: 0.42271431 | Z10: 0.050595078 | AC10: 0.027072261 | AD10: 0.99326974 | AE10: 0.42271431 | AF10: 0.050595078
A11: j37 | B11: j1 | C11: t10 | D11: 2 | E11: 0 | F11: 0 | G11: 0 | H11: 1 | M11: Fy | N11: Apr-Aug | O11: 0.3 | Q11: 0 | R11: 1 | S11: 0.1677217 | T11: 0.031354217 | W11: 0.027072261 | X11: 0.99326974 | Y11: 0.42271431 | Z11: 0.050595078 | AC11: 0.027072261 | AD11: 0.99326974 | AE11: 0.42271431 | AF11: 0.050595078
A12: j37 | B12: j1 | C12: t11 | D12: 2 | E12: 0 | F12: 0 | G12: 0 | H12: 1 | W12: 0.027072261 | X12: 0.99326974 | Y12: 0.42271431 | Z12: 0.050595078 | AC12: 0.027072261 | AD12: 0.99326974 | AE12: 0.42271431 | AF12: 0.050595078
A13: j37 | B13: j1 | C13: t12 | D13: 2 | E13: 0 | F13: 0 | G13: 0 | H13: 1 | W13: 0.027072261 | X13: 0.99326974 | Y13: 0.42271431 | Z13: 0.050595078 | AC13: 0.027072261 | AD13: 0.99326974 | AE13: 0.42271431 | AF13: 0.050595078
A14: j1 | B14: j4 | C14: t1 | D14: 2 | E14: 0 | F14: 0 | G14: 0 | H14: 1 | W14: 0.027072261 | X14: 0.99326974 | Y14: 0.42271431 | Z14: 0.050595078 | AC14: 0.027072261 | AD14: 0.99326974 | AE14: 0.42271431 | AF14: 0.050595078
A15: j1 | B15: j4 | C15: t2 | D15: 2 | E15: 0 | F15: 0 | G15: 0 | H15: 1 | W15: 0.027072261 | X15: 0.99326974 | Y15: 0.42271431 | Z15: 0.050595078 | AC15: 0.027072261 | AD15: 0.99326974 | AE15: 0.42271431 | AF15: 0.050595078
A16: j1 | B16: j4 | C16: t3 | D16: 2 | E16: 0 | F16: 0 | G16: 0 | H16: 3 | W16: 0.027072261 | X16: 0.99326974 | Y16: 0.42271431 | Z16: 0.050595078 | AC16: 0.027072261 | AD16: 0.99326974 | AE16: 0.42271431 | AF16: 0.050595078
A17: j1 | B17: j4 | C17: t4 | D17: 2 | E17: 0 | F17: 0 | G17: 0 | H17: 3 | O17: t1 | P17: 0 | Q17: 1 | R17: 0.42240891 | S17: 0.04896029 | W17: 0.029313504 | X17: 0.98886831 | Y17: 0.24676178 | Z17: 0.024946824 | AC17: 0.029313504 | AD17: 0.98886831 | AE17: 0.24676178 | AF17: 0.024946824
A18: j1 | B18: j4 | C18: t5 | D18: 2 | E18: 0 | F18: 0 | G18: 0 | H18: 3 | O18: t2 | P18: 0 | Q18: 1 | R18: 0.42240891 | S18: 0.04896029 | W18: 0.029313504 | X18: 0.98886831 | Y18: 0.24676178 | Z18: 0.024946824 | AC18: 0.029313504 | AD18: 0.98886831 | AE18: 0.24676178 | AF18: 0.024946824
A19: j1 | B19: j4 | C19: t6 | D19: 2 | E19: 0 | F19: 0 | G19: 0 | H19: 3 | O19: t3 | P19: 0 | Q19: 1 | R19: 0.42240891 | S19: 0.04896029 | W19: 0.029313504 | X19: 0.98886831 | Y19: 0.24676178 | Z19: 0.024946824 | AC19: 0.029313504 | AD19: 0.98886831 | AE19: 0.24676178 | AF19: 0.024946824
A20: j1 | B20: j4 | C20: t7 | D20: 2 | E20: 0 | F20: 0 | G20: 0 | H20: 3 | O20: t4 | P20: 0 | Q20: 1 | R20: 0.2888249 | S20: 0.01979619 | W20: 0.029313504 | X20: 0.98886831 | Y20: 0.24676178 | Z20: 0.024946824 | AC20: 0.029313504 | AD20: 0.98886831 | AE20: 0.24676178 | AF20: 0.024946824
A21: j1 | B21: j4 | C21: t8 | D21: 2 | E21: 0 | F21: 0 | G21: 0 | H21: 3 | O21: t5 | P21: 0 | Q21: 1 | R21: 0.2888249 | S21: 0.01979619 | W21: 0.029313504 | X21: 0.98886831 | Y21: 0.24676178 | Z21: 0.024946824 | AC21: 0.029313504 | AD21: 0.98886831 | AE21: 0.24676178 | AF21: 0.024946824
A22: j1 | B22: j4 | C22: t9 | D22: 2 | E22: 0 | F22: 0 | G22: 0 | H22: 1 | O22: t6 | P22: 0 | Q22: 1 | R22: 0.2888249 | S22: 0.01979619 | W22: 0.027072261 | X22: 0.99326974 | Y22: 0.42271431 | Z22: 0.050595078 | AC22: 0.027072261 | AD22: 0.99326974 | AE22: 0.42271431 | AF22: 0.050595078
A23: j1 | B23: j4 | C23: t10 | D23: 2 | E23: 0 | F23: 0 | G23: 0 | H23: 1 | O23: t7 | P23: 0 | Q23: 1 | R23: 0.2888249 | S23: 0.01979619 | W23: 0.027072261 | X23: 0.99326974 | Y23: 0.42271431 | Z23: 0.050595078 | AC23: 0.027072261 | AD23: 0.99326974 | AE23: 0.42271431 | AF23: 0.050595078
A24: j1 | B24: j4 | C24: t11 | D24: 2 | E24: 0 | F24: 0 | G24: 0 | H24: 1 | O24: t8 | P24: 0 | Q24: 1 | R24: 0.2888249 | S24: 0.01979619 | W24: 0.027072261 | X24: 0.99326974 | Y24: 0.42271431 | Z24: 0.050595078 | AC24: 0.027072261 | AD24: 0.99326974 | AE24: 0.42271431 | AF24: 0.050595078
A25: j1 | B25: j4 | C25: t12 | D25: 2 | E25: 0 | F25: 0 | G25: 0 | H25: 1 | O25: t9 | P25: 0 | Q25: 1 | R25: 0.42240891 | S25: 0.04896029 | W25: 0.027072261 | X25: 0.99326974 | Y25: 0.42271431 | Z25: 0.050595078 | AC25: 0.027072261 | AD25: 0.99326974 | AE25: 0.42271431 | AF25: 0.050595078
A26: j6 | B26: j5 | C26: t1 | D26: 2 | E26: 0 | F26: 0 | G26: 0 | H26: 1 | O26: t10 | P26: 0 | Q26: 1 | R26: 0.42240891 | S26: 0.04896029 | W26: 0.027072261 | X26: 0.99326974 | Y26: 0.42271431 | Z26: 0.050595078 | AC26: 0.027072261 | AD26: 0.99326974 | AE26: 0.42271431 | AF26: 0.050595078
A27: j6 | B27: j5 | C27: t2 | D27: 2 | E27: 0 | F27: 0 | G27: 0 | H27: 1 | O27: t11 | P27: 0 | Q27: 1 | R27: 0.42240891 | S27: 0.04896029 | W27: 0.027072261 | X27: 0.99326974 | Y27: 0.42271431 | Z27: 0.050595078 | AC27: 0.027072261 | AD27: 0.99326974 | AE27: 0.42271431 | AF27: 0.050595078
A28: j6 | B28: j5 | C28: t3 | D28: 2 | E28: 0 | F28: 0 | G28: 0 | H28: 3 | O28: t12 | P28: 0 | Q28: 1 | R28: 0.42240891 | S28: 0.04896029 | W28: 0.027072261 | X28: 0.99326974 | Y28: 0.42271431 | Z28: 0.050595078 | AC28: 0.027072261 | AD28: 0.99326974 | AE28: 0.42271431 | AF28: 0.050595078
A29: j6 | B29: j5 | C29: t4 | D29: 2 | E29: 0 | F29: 0 | G29: 0 | H29: 3 | W29: 0.029313504 | X29: 0.98886831 | Y29: 0.24676178 | Z29: 0.024946824 | AC29: 0.029313504 | AD29: 0.98886831 | AE29: 0.24676178 | AF29: 0.024946824
A30: j6 | B30: j5 | C30: t5 | D30: 2 | E30: 0 | F30: 0 | G30: 0 | H30: 3 | W30: 0.029313504 | X30: 0.98886831 | Y30: 0.24676178 | Z30: 0.024946824 | AC30: 0.029313504 | AD30: 0.98886831 | AE30: 0.24676178 | AF30: 0.024946824
A31: j6 | B31: j5 | C31: t6 | D31: 2 | E31: 0 | F31: 0 | G31: 0 | H31: 3 | W31: 0.029313504 | X31: 0.98886831 | Y31: 0.24676178 | Z31: 0.024946824 | AC31: 0.029313504 | AD31: 0.98886831 | AE31: 0.24676178 | AF31: 0.024946824
A32: j6 | B32: j5 | C32: t7 | D32: 2 | E32: 0 | F32: 0 | G32: 0 | H32: 3 | W32: 0.029313504 | X32: 0.98886831 | Y32: 0.24676178 | Z32: 0.024946824 | AC32: 0.029313504 | AD32: 0.98886831 | AE32: 0.24676178 | AF32: 0.024946824
A33: j6 | B33: j5 | C33: t8 | D33: 2 | E33: 0 | F33: 0 | G33: 0 | H33: 3 | W33: 0.029313504 | X33: 0.98886831 | Y33: 0.24676178 | Z33: 0.024946824 | AC33: 0.029313504 | AD33: 0.98886831 | AE33: 0.24676178 | AF33: 0.024946824
A34: j6 | B34: j5 | C34: t9 | D34: 2 | E34: 0 | F34: 0 | G34: 0 | H34: 1 | W34: 0.027072261 | X34: 0.99326974 | Y34: 0.42271431 | Z34: 0.050595078 | AC34: 0.027072261 | AD34: 0.99326974 | AE34: 0.42271431 | AF34: 0.050595078
A35: j6 | B35: j5 | C35: t10 | D35: 2 | E35: 0 | F35: 0 | G35: 0 | H35: 1 | W35: 0.027072261 | X35: 0.99326974 | Y35: 0.42271431 | Z35: 0.050595078 | AC35: 0.027072261 | AD35: 0.99326974 | AE35: 0.42271431 | AF35: 0.050595078
A36: j6 | B36: j5 | C36: t11 | D36: 2 | E36: 0 | F36: 0 | G36: 0 | H36: 1 | W36: 0.027072261 | X36: 0.99326974 | Y36: 0.42271431 | Z36: 0.050595078 | AC36: 0.027072261 | AD36: 0.99326974 | AE36: 0.42271431 | AF36: 0.050595078
A37: j6 | B37: j5 | C37: t12 | D37: 2 | E37: 0 | F37: 0 | G37: 0 | H37: 1 | W37: 0.027072261 | X37: 0.99326974 | Y37: 0.42271431 | Z37: 0.050595078 | AC37: 0.027072261 | AD37: 0.99326974 | AE37: 0.42271431 | AF37: 0.050595078
A38: j5 | B38: j18 | C38: t1 | D38: 2 | E38: 0 | F38: 0 | G38: 0 | H38: 1 | W38: 0.027072261 | X38: 0.99326974 | Y38: 0.42271431 | Z38: 0.050595078 | AC38: 0.027072261 | AD38: 0.99326974 | AE38: 0.42271431 | AF38: 0.050595078
A39: j5 | B39: j18 | C39: t2 | D39: 2 | E39: 0 | F39: 0 | G39: 0 | H39: 1 | W39: 0.027072261 | X39: 0.99326974 | Y39: 0.42271431 | Z39: 0.050595078 | AC39: 0.027072261 | AD39: 0.99326974 | AE39: 0.42271431 | AF39: 0.050595078
A40: j5 | B40: j18 | C40: t3 | D40: 2 | E40: 0 | F40: 0 | G40: 0 | H40: 3 | W40: 0.027072261 | X40: 0.99326974 | Y40: 0.42271431 | Z40: 0.050595078 | AC40: 0.027072261 | AD40: 0.99326974 | AE40: 0.42271431 | AF40: 0.050595078
... A229: j30 | B229: j25 | C229: t12 | D229: 1 | E229: 0 | F229: 1 | G229: 0.42240891 | H229: 0.04896029 | W229: 0.027072261 | X229: 0.99326974 | Y229: 0.42271431 | Z229: 0.050595078 | AC229: 0.0011877608 | AD229: 1.0039966 | AE229: 0.48147111 | AF229: 0.10105984
A230: j32 | B230: j29 | C230: t1 | D230: 1 | E230: 0 | F230: 1 | G230: 0.42240891 | H230: 0.04896029
A231: j32 | B231: j29 | C231: t2 | D231: 1 | E231: 0 | F231: 1 | G231: 0.42240891 | H231: 0.04896029
A232: j32 | B232: j29 | C232: t3 | D232: 1 | E232: 0 | F232: 1 | G232: 0.42240891 | H232: 0.04896029
A233: j32 | B233: j29 | C233: t4 | D233: 1 | E233: 0 | F233: 1 | G233: 0.14862101 | H233: 0.04447113
A234: j32 | B234: j29 | C234: t5 | D234: 1 | E234: 0 | F234: 1 | G234: 0.14862101 | H234: 0.04447113
A235: j32 | B235: j29 | C235: t6 | D235: 1 | E235: 0 | F235: 1 | G235: 0.14862101 | H235: 0.04447113
A236: j32 | B236: j29 | C236: t7 | D236: 1 | E236: 0 | F236: 1 | G236: 0.14862101 | H236: 0.04447113
A237: j32 | B237: j29 | C237: t8 | D237: 1 | E237: 0 | F237: 1 | G237: 0.14862101 | H237: 0.04447113
A238: j32 | B238: j29 | C238: t9 | D238: 1 | E238: 0 | F238: 1 | G238: 0.42240891 | H238: 0.04896029
A239: j32 | B239: j29 | C239: t10 | D239: 1 | E239: 0 | F239: 1 | G239: 0.42240891 | H239: 0.04896029
A240: j32 | B240: j29 | C240: t11 | D240: 1 | E240: 0 | F240: 1 | G240: 0.42240891 | H240: 0.04896029
A241: j32 | B241: j29 | C241: t12 | D241: 1 | E241: 0 | F241: 1 | G241: 0.42240891 | H241: 0.04896029
... A313: j45 | B313: j32 | C313: t12 | D313: 1 | E313: 0 | F313: 1 | G313: 0.42240891 | H313: 0.04896029

Sheet RSI_data
A1: Site | B1: Elevation (ft) | C1: Max Water Temperature recorded in (Co) | D1: Preferred Depth for adult BCT (m) | I1: Preferred Depth for fry BCT (m)
D2: [Sep – Mar] | E2: rsi_par1 | F2: rsi_par2 | G2: rsi_par3 | H2: rsi_par4 | I2: [ Apr – Aug ] | J2: rsi_par1 | K2: rsi_par2 | L2: rsi_par3 | M2: rsi_par4
A3: Bear River at Stateline | B3: 4436 | C3: 26.3 | D3: 0.75 – 0.30 | E3: 0 | F3: 1 | G3: 0.42240891 | H3: 0.04896029 | I3: 0.45 – 0.20 | J3: 0 | K3: 1 | L3: 0.2888249 | M3: 0.01979619
F4: 1 | K4: 1
A5: Bear River at Cutler | B5: 4422 | C5: 26.7 | D5: 0.75 – 0.30 | E5: 0 | F5: 1 | G5: 0.42240891 | H5: 0.04896029 | I5: 0.45 – 0.25 | J5: 0 | K5: 1 | L5: 0.2606764 | M5: 0.0418884
E6: 0 | F6: 1 | K6: 1
A7: Bear- Cub Confluence | B7: 4423 | C7: 26.3 | D7: 0.75 – 0.30 | E7: 0 | F7: 1 | G7: 0.42240891 | H7: 0.04896029 | I7: 0.45 – 0.25 | J7: 0 | K7: 1 | L7: 0.2606764 | M7: 0.0418884
E8: 0 | F8: 1 | K8: 1
A9: Bear River below Cutler at UP L Bridge Station #4901980 | B9: 4245 | C9: 25.9 | D9: 0.75 – 0.30 | E9: 0 | F9: 1 | G9: 0.42240891 | H9: 0.04896029 | I9: 0.45 – 0.25 | J9: 0 | K9: 1 | L9: 0.2606764 | M9: 0.0418884
E10: 0 | F10: 1 | K10: 1
A11: Little Bear at Paradise | B11: 4816 | C11: 20.5 | D11: 0.75 – 0.30 | E11: 0 | F11: 1 | G11: 0.42240891 | H11: 0.04896029 | I11: 0.45 – 0.10 | J11: 0 | K11: 1 | L11: 0.14862101 | M11: 0.04447113
E12: 0 | F12: 1 | K12: 1
A13: Little Bear at Mendon | B13: 4414 | C13: 21.4 | D13: 0.75 – 0.30 | E13: 0 | F13: 1 | G13: 0.42240891 | H13: 0.04896029 | I13: 0.45 – 0.10 | J13: 0 | K13: 1 | L13: 0.14862101 | M13: 0.04447113
E14: 0 | F14: 1 | K14: 1
A15: Little Bear near Wellsville | B15: 4493 | C15: 22.2 | D15: 0.75 – 0.30 | E15: 0 | F15: 1 | G15: 0.42240891 | H15: 0.04896029 | I15: 0.45 – 0.10 | J15: 0 | K15: 1 | L15: 0.14862101 | M15: 0.04447113
E16: 0 | F16: 1 | K16: 1

Sheet h
A1: j37 | B1: j1 | C1: t1 | D1: 1
A2: j37 | B2: j1 | C2: t2 | D2: 1
A3: j37 | B3: j1 | C3: t3 | D3: 3
A4: j37 | B4: j1 | C4: t4 | D4: 3
A5: j37 | B5: j1 | C5: t5 | D5: 3
A6: j37 | B6: j1 | C6: t6 | D6: 3
A7: j37 | B7: j1 | C7: t7 | D7: 3 | P7: Brown Trout
A8: j37 | B8: j1 | C8: t8 | D8: 3 | P8: Months | Q8: Depth (m) | R8: h
A9: j37 | B9: j1 | C9: t9 | D9: 1 | O9: Adult | P9: Sep - Feb | Q9: 0.8 | R9: 1
A10: j37 | B10: j1 | C10: t10 | D10: 1 | O10: Fry | P10: Mar-Aug | Q10: 0.5 | R10: 3
A11: j37 | B11: j1 | C11: t11 | D11: 1
A12: j37 | B12: j1 | C12: t12 | D12: 1
A13: j1 | B13: j4 | C13: t1 | D13: 1
A14: j1 | B14: j4 | C14: t2 | D14: 1
A15: j1 | B15: j4 | C15: t3 | D15: 3
A16: j1 | B16: j4 | C16: t4 | D16: 3
A17: j1 | B17: j4 | C17: t5 | D17: 3
A18: j1 | B18: j4 | C18: t6 | D18: 3
A19: j1 | B19: j4 | C19: t7 | D19: 3
A20: j1 | B20: j4 | C20: t8 | D20: 3
A21: j1 | B21: j4 | C21: t9 | D21: 1
A22: j1 | B22: j4 | C22: t10 | D22: 1
... A312: j45 | B312: j32 | C312: t12 | D312: 1

Sheet fciIndex
A1: fci_par1
A2: fci_par2
A3: fci_par3
A4: fci_par4

Sheet fciEQ
D1: fci_par1 | E1: fci_par2 | F1: fci_par3 | G1: fci_par4
A2: j4 | B2: j5 | C2: t1 | D2: 0.001 | E2: 0.001 | F2: 0.001 | G2: 0.001
A3: j4 | B3: j5 | C3: t2 | D3: 0.001 | E3: 0.001 | F3: 0.001 | G3: 0.001
A4: j4 | B4: j5 | C4: t3 | D4: 0.001 | E4: 0.001 | F4: 0.001 | G4: 0.001
A5: j4 | B5: j5 | C5: t4 | D5: 0.014870277 | E5: 1.0113511 | F5: 140.16933 | G5: 14.751512
A6: j4 | B6: j5 | C6: t5 | D6: 0.014870277 | E6: 1.0113511 | F6: 140.16933 | G6: 14.751512
A7: j4 | B7: j5 | C7: t6 | D7: 0.014870277 | E7: 1.0113511 | F7: 140.16933 | G7: 14.751512
A8: j4 | B8: j5 | C8: t7 | D8: 0.014870277 | E8: 1.0113511 | F8: 140.16933 | G8: 14.751512
A9: j4 | B9: j5 | C9: t8 | D9: 0.014870277 | E9: 1.0113511 | F9: 140.16933 | G9: 14.751512
A10: j4 | B10: j5 | C10: t9 | D10: 0.001 | E10: 0.001 | F10: 0.001 | G10: 0.001
A11: j4 | B11: j5 | C11: t10 | D11: 0.001 | E11: 0.001 | F11: 0.001 | G11: 0.001
A12: j4 | B12: j5 | C12: t11 | D12: 0.001 | E12: 0.001 | F12: 0.001 | G12: 0.001
A13: j4 | B13: j5 | C13: t12 | D13: 0.001 | E13: 0.001 | F13: 0.001 | G13: 0.001
... A313: j45 | B313: j32 | C313: t12 | D313: 0.001 | E313: 0.001 | F313: 0.001 | G313: 0.001

Sheet wp
D1: wsi_par1 | E1: wsi_par2
A2: j21 | B2: j23 | C2: t1 | D2: 0.0003 | E2: 0.3373
A3: j21 | B3: j23 | C3: t2 | D3: 2e-05 | E3: 0.4121
A4: j21 | B4: j23 | C4: t3 | D4: 8e-06 | E4: 0.3051
A5: j21 | B5: j23 | C5: t4 | D5: 2e-05 | E5: 0.1373
A6: j21 | B6: j23 | C6: t5 | D6: 3e-06 | E6: 0.1211
A7: j21 | B7: j23 | C7: t6 | D7: 7e-06 | E7: 0.1167
A8: j21 | B8: j23 | C8: t7 | D8: 2e-05 | E8: 0.1396
A9: j21 | B9: j23 | C9: t8 | D9: 3e-05 | E9: 0.1343
A10: j21 | B10: j23 | C10: t9 | D10: 0.0001 | E10: 0.1656
A11: j21 | B11: j23 | C11: t10 | D11: 6e-05 | E11: 0.185
A12: j21 | B12: j23 | C12: t11 | D12: 0.0001 | E12: 0.3932
A13: j21 | B13: j23 | C13: t12 | D13: 0.0001 | E13: 0.401

Sheet Length
A1: j4 | B1: j5 | C1: 14090
A2: j6 | B2: j5 | C2: 470
A3: j5 | B3: j18 | C3: 11513
A4: j21 | B4: j23 | C4: 33740
A5: j37 | B5: j1 | C5: 21736.476
A6: j1 | B6: j4 | C6: 55344.138
A7: j18 | B7: j7 | C7: 13304.681
A8: j7 | B8: j9 | C8: 8267.8962
A9: j12 | B9: j14 | C9: 14391.808
A10: j14 | B10: j17 | C10: 12605.18
A11: j17 | B11: j20 | C11: 56557.259
A12: j19 | B12: j20 | C12: 127172.76
... A26: j45 | B26: j32 | C26: 9264.09

Sheet aw
A1: j21 | B1: j23 | C1: t1 | D1: =118400000/1000000 -> 118.4 | I1: acres | J1: =D1*247.11 -> 29257.824 | L1: 299.46616
A2: j21 | B2: j23 | C2: t2 | D2: =118400000/1000000 -> 118.4 | L2: 299.46616
A3: j21 | B3: j23 | C3: t3 | D3: =118400000/1000000 -> 118.4 | L3: 299.46616
A4: j21 | B4: j23 | C4: t4 | D4: =118400000/1000000 -> 118.4 | L4: 299.46616
A5: j21 | B5: j23 | C5: t5 | D5: =118400000/1000000 -> 118.4 | L5: 299.46616
A6: j21 | B6: j23 | C6: t6 | D6: =118400000/1000000 -> 118.4 | L6: 299.46616
A7: j21 | B7: j23 | C7: t7 | D7: =118400000/1000000 -> 118.4 | L7: 299.46616
A8: j21 | B8: j23 | C8: t8 | D8: =118400000/1000000 -> 118.4 | L8: 299.46616
A9: j21 | B9: j23 | C9: t9 | D9: =118400000/1000000 -> 118.4 | L9: 299.46616
A10: j21 | B10: j23 | C10: t10 | D10: =118400000/1000000 -> 118.4 | L10: 299.46616
A11: j21 | B11: j23 | C11: t11 | D11: =118400000/1000000 -> 118.4 | L11: 299.46616
A12: j21 | B12: j23 | C12: t12 | D12: =118400000/1000000 -> 118.4 | L12: 299.46616
J20: =0.4*J1 -> 11703.13

Sheet lss
C1: t1 | D1: t2 | E1: t3 | F1: t4 | G1: t5 | H1: t6 | I1: t7 | J1: t8 | K1: t9 | L1: t10 | M1: t11 | N1: t12
A2: j37 | B2: j1 | C2: 0 | D2: 0 | E2: 0 | F2: 0 | G2: 0 | H2: 0 | I2: 0 | J2: 0 | K2: 0 | L2: 0 | M2: 0 | N2: 0
A3: j1 | B3: j4 | C3: 0 | D3: 0 | E3: 0 | F3: 0 | G3: 0 | H3: 0 | I3: 0 | J3: 0 | K3: 0 | L3: 0 | M3: 0 | N3: 0
A4: j4 | B4: j5 | C4: 0 | D4: 0 | E4: 0 | F4: 0 | G4: 0 | H4: 0 | I4: 0 | J4: 0 | K4: 0 | L4: 0 | M4: 0 | N4: 0
A5: j6 | B5: j5 | C5: 0 | D5: 0 | E5: 0 | F5: 0 | G5: 0 | H5: 0 | I5: 0 | J5: 0 | K5: 0 | L5: 0 | M5: 0 | N5: 0
A6: j5 | B6: j18 | C6: 0 | D6: 0 | E6: 0 | F6: 0 | G6: 0 | H6: 0 | I6: 0 | J6: 0 | K6: 0 | L6: 0 | M6: 0 | N6: 0
A7: j2 | B7: j3 | C7: 0 | D7: 0 | E7: 0 | F7: 0 | G7: 0 | H7: 0 | I7: 0 | J7: 0 | K7: 0 | L7: 0 | M7: 0 | N7: 0
A8: j4 | B8: j3 | C8: 0 | D8: 0 | E8: 0 | F8: 0 | G8: 0 | H8: 0 | I8: 0 | J8: 0 | K8: 0 | L8: 0 | M8: 0 | N8: 0
A9: j3 | B9: j18 | C9: 0 | D9: 0 | E9: 0 | F9: 0 | G9: 0 | H9: 0 | I9: 0 | J9: 0 | K9: 0 | L9: 0 | M9: 0 | N9: 0
A10: j18 | B10: j7 | C10: 0 | D10: 0 | E10: 0 | F10: 0 | G10: 0 | H10: 0 | I10: 0 | J10: 0 | K10: 0 | L10: 0 | M10: 0 | N10: 0
A11: j34 | B11: j33 | C11: 0 | D11: 0 | E11: 0 | F11: 0 | G11: 0 | H11: 0 | I11: 0 | J11: 0 | K11: 0 | L11: 0 | M11: 0 | N11: 0
A12: j35 | B12: j32 | C12: 0 | D12: 0 | E12: 0 | F12: 0 | G12: 0 | H12: 0 | I12: 0 | J12: 0 | K12: 0 | L12: 0 | M12: 0 | N12: 0
A13: j33 | B13: j32 | C13: 0 | D13: 0 | E13: 0 | F13: 0 | G13: 0 | H13: 0 | I13: 0 | J13: 0 | K13: 0 | L13: 0 | M13: 0 | N13: 0
... A54: j45 | B54: j32 | C54: 0 | D54: 0 | E54: 0 | F54: 0 | G54: 0 | H54: 0 | I54: 0 | J54: 0 | K54: 0 | L54: 0 | M54: 0 | N54: 0

Sheet LinkName
A1: j37 | B1: j1 | C1: 1 | D1: ="L"&C1 -> L1
A2: j1 | B2: j4 | C2: 2 | D2: ="L"&C2 -> L2
A3: j4 | B3: j5 | C3: 3 | D3: ="L"&C3 -> L3
A4: j6 | B4: j5 | C4: 4 | D4: ="L"&C4 -> L4
A5: j5 | B5: j18 | C5: 5 | D5: ="L"&C5 -> L5
A6: j18 | B6: j7 | C6: 7 | D6: ="L"&C6 -> L7
A7: j7 | B7: j9 | C7: 8 | D7: ="L"&C7 -> L8
A8: j9 | B8: j12 | C8: 9 | D8: ="L"&C8 -> L9
A9: j12 | B9: j14 | C9: 11 | D9: ="L"&C9 -> L11
A10: j14 | B10: j17 | C10: 12 | D10: ="L"&C10 -> L12
A11: j17 | B11: j20 | C11: 13 | D11: ="L"&C11 -> L13
A12: j19 | B12: j20 | C12: 14 | D12: ="L"&C12 -> L14
... A26: j45 | B26: j32 | C26: 30 | D26: ="L"&C26 -> L30

Sheet evap
B1: t1 | C1: t2 | D1: t3 | E1: t4 | F1: t5 | G1: t6 | H1: t7 | I1: t8 | J1: t9 | K1: t10 | L1: t11 | M1: t12
A2: j1 | B2: 0 | C2: 0 | D2: 0 | E2: 0.03048 | F2: 0.12192 | G2: 0.1524 | H2: 0.18288 | I2: 0.1524 | J2: 0.09144 | K2: 0.09144 | L2: 0 | M2: 0
A3: j7 | B3: 0 | C3: 0 | D3: 0 | E3: 0.03048 | F3: 0.12192 | G3: 0.1524 | H3: 0.18288 | I3: 0.1524 | J3: 0.09144 | K3: 0.09144 | L3: 0 | M3: 0
A4: j17 | B4: 0 | C4: 0 | D4: 0 | E4: 0.03048 | F4: 0.12192 | G4: 0.1524 | H4: 0.18288 | I4: 0.1524 | J4: 0.09144 | K4: 0.09144 | L4: 0 | M4: 0
A5: j29 | B5: 0 | C5: 0 | D5: 0 | E5: 0.03048 | F5: 0.12192 | G5: 0.1524 | H5: 0.18288 | I5: 0.1524 | J5: 0.09144 | K5: 0.09144 | L5: 0 | M5: 0
A6: j33 | B6: 0 | C6: 0 | D6: 0 | E6: 0.03048 | F6: 0.12192 | G6: 0.1524 | H6: 0.18288 | I6: 0.1524 | J6: 0.09144 | K6: 0.09144 | L6: 0 | M6: 0

Sheet linkEvap
C1: t1 | D1: t2 | E1: t3 | F1: t4 | G1: t5 | H1: t6 | I1: t7 | J1: t8 | K1: t9 | L1: t10 | M1: t11 | N1: t12
A2: j37 | B2: j1 | C2: 0 | D2: 0 | E2: 0 | F2: 0 | G2: 0 | H2: 0 | I2: 0 | J2: 0 | K2: 0 | L2: 0 | M2: 0 | N2: 0
A3: j1 | B3: j4 | C3: 0 | D3: 0 | E3: 0 | F3: 0 | G3: 0 | H3: 0 | I3: 0 | J3: 0 | K3: 0 | L3: 0 | M3: 0 | N3: 0
A4: j4 | B4: j5 | C4: 0 | D4: 0 | E4: 0 | F4: 0 | G4: 0 | H4: 0 | I4: 0 | J4: 0 | K4: 0 | L4: 0 | M4: 0 | N4: 0
A5: j6 | B5: j5 | C5: 0 | D5: 0 | E5: 0 | F5: 0 | G5: 0 | H5: 0 | I5: 0 | J5: 0 | K5: 0 | L5: 0 | M5: 0 | N5: 0
A6: j5 | B6: j18 | C6: 0 | D6: 0 | E6: 0 | F6: 0 | G6: 0 | H6: 0 | I6: 0 | J6: 0 | K6: 0 | L6: 0 | M6: 0 | N6: 0
A7: j2 | B7: j3 | C7: 0 | D7: 0 | E7: 0 | F7: 0 | G7: 0 | H7: 0 | I7: 0 | J7: 0 | K7: 0 | L7: 0 | M7: 0 | N7: 0
A8: j4 | B8: j3 | C8: 0 | D8: 0 | E8: 0 | F8: 0 | G8: 0 | H8: 0 | I8: 0 | J8: 0 | K8: 0 | L8: 0 | M8: 0 | N8: 0
A9: j3 | B9: j18 | C9: 0 | D9: 0 | E9: 0 | F9: 0 | G9: 0 | H9: 0 | I9: 0 | J9: 0 | K9: 0 | L9: 0 | M9: 0 | N9: 0
A10: j18 | B10: j7 | C10: 0 | D10: 0 | E10: 0 | F10: 0 | G10: 0 | H10: 0 | I10: 0 | J10: 0 | K10: 0 | L10: 0 | M10: 0 | N10: 0
A11: j34 | B11: j33 | C11: 0 | D11: 0 | E11: 0 | F11: 0 | G11: 0 | H11: 0 | I11: 0 | J11: 0 | K11: 0 | L11: 0 | M11: 0 | N11: 0
A12: j35 | B12: j32 | C12: 0 | D12: 0 | E12: 0 | F12: 0 | G12: 0 | H12: 0 | I12: 0 | J12: 0 | K12: 0 | L12: 0 | M12: 0 | N12: 0
A13: j33 | B13: j32 | C13: 0 | D13: 0 | E13: 0 | F13: 0 | G13: 0 | H13: 0 | I13: 0 | J13: 0 | K13: 0 | L13: 0 | M13: 0 | N13: 0
... A55: j45 | B55: j32 | C55: 0 | D55: 0 | E55: 0 | F55: 0 | G55: 0 | H55: 0 | I55: 0 | J55: 0 | K55: 0 | L55: 0 | M55: 0 | N55: 0

Sheet evap_WEAP
B1: t1 | C1: t2 | D1: t3 | E1: t4 | F1: t5 | G1: t6 | H1: t7 | I1: t8 | J1: t9 | K1: t10 | L1: t11 | M1: t12
A2: j1 | B2: 0 | C2: 0 | D2: 0 | E2: 0.03048 | F2: 0.12192 | G2: 0.1524 | H2: 0.18288 | I2: 0.1524 | J2: 0.09144 | K2: 0.09144 | L2: 0 | M2: 0
A3: j7 | B3: 0 | C3: 0 | D3: 0 | E3: 0.03048 | F3: 0.12192 | G3: 0.1524 | H3: 0.18288 | I3: 0.1524 | J3: 0.09144 | K3: 0.09144 | L3: 0 | M3: 0
A4: j17 | B4: 0 | C4: 0 | D4: 0 | E4: 0.03048 | F4: 0.12192 | G4: 0.1524 | H4: 0.18288 | I4: 0.1524 | J4: 0.09144 | K4: 0.09144 | L4: 0 | M4: 0
A5: j29 | B5: 0 | C5: 0 | D5: 0 | E5: 0.03048 | F5: 0.12192 | G5: 0.1524 | H5: 0.18288 | I5: 0.1524 | J5: 0.09144 | K5: 0.09144 | L5: 0 | M5: 0
A6: j33 | B6: 0 | C6: 0 | D6: 0 | E6: 0.03048 | F6: 0.12192 | G6: 0.1524 | H6: 0.18288 | I6: 0.1524 | J6: 0.09144 | K6: 0.09144 | L6: 0 | M6: 0

Sheet ResElevVol
B1: RA_par1 | C1: RA_par2 | D1: RA_par3
A2: j1 | B2: 0.5802 | C2: 8.8779 | D2: 0.04744
A3: j7 | B3: 0.1718 | C3: 0.0521 | D3: 3.0042
A4: j17 | B4: 0.1718 | C4: 0.0521 | D4: 3.0042
A5: j29 | B5: -0.0004 | C5: 0.0694 | D5: 0.4076
A6: j33 | B6: 0.001 | C6: 0.0295 | D6: 0.0897
A17: j33 | B17: 0.001 | C17: 0.0295 | D17: 0.0897

Sheet EvaporationCurve
B1: STOR (m3) | C1: elevation (m) | D1: area (m) | E1: At+Ab | I1: Old elevation at STOR=0
A2: 0 | B2: 0 | C2: 1399.032 | D2: 0 | E2: =(B3-B2/C3-C2)*2 -> 317907.22 | I2: 1399.032
A3: 1 | B3: 160352.64 | C3: 1402.08 | D3: =E2-D2 -> 317907.22 | E3: =(B4-B3/C4-C3)*2 -> 1598027
A4: 2 | B4: 800529.72 | C4: 1405.128 | D4: =E3-D3 -> 1280119.8 | E4: =(B5-B4/C5-C4)*2 -> 4286102.7
A5: 3 | B5: 2145024.9 | C5: 1408.176 | D5: =E4-D4 -> 3005982.8 | E5: =(B6-B5/C6-C5)*2 -> 8519970.3
A6: 4 | B6: 4262913.3 | C6: 1411.224 | D6: =E5-D5 -> 5513987.5 | E6: =(B7-B6/C7-C6)*2 -> 14637513
A7: 5 | B7: 7323181.8 | C7: 1414.272 | D7: =E6-D6 -> 9123525.2 | E7: =(B8-B7/C8-C7)*2 -> 22771714
A8: 6 | B8: 11392438 | C8: 1417.32 | D8: =E7-D7 -> 13648189 | E8: =(B9-B8/C9-C8)*2 -> 32559847
A9: 7 | B9: 16289361 | C9: 1420.368 | D9: =E8-D8 -> 18911657 | E9: =(B10-B9/C10-C9)*2 -> 43691335
A10: 8 | B10: 21858532 | C10: 1423.416 | D10: =E9-D9 -> 24779678 | E10: =(B11-B10/C11-C10)*2 -> 46059204
A11: 9 | B11: 23046375 | C11: 1424.0256 | D11: =E10-D10 -> 21279525 | E11: =(B12-B11/C12-C11)*2 -> 55718219
A12: 10 | B12: 27876690 | C12: 1426.464 | D12: =E11-D11 -> 34438694 | E12: =(B13-B12/C13-C12)*2 -> 69279826
A13: 11 | B13: 34660840 | C13: 1429.512 | D13: =E12-D12 -> 34841132 | E13: =(B14-B13/C14-C13)*2 -> 84072213
A14: 12 | B14: 42061731 | C14: 1432.56 | D14: =E13-D13 -> 49231082 | E14: =(B15-B14/C15-C14)*2 -> 1.0034396e+08
... A18: 16 | B18: 79559580 | C18: 1444.752 | D18: =E17-D17 -> 88431282 | E18: =(B19-B18/C19-C18)*2 -> 1.8219582e+08
A19: 17 | B19: 91154309 | C19: 1447.8 | D19: =E18-D18 -> 93764542 | E19: =(B19/C19)*2 -> 125921.13
A25: j30 | B25: MillCreek | I25: WEAP Data
B26: STOR (m3) | C26: elevation (m) | D26: area (m) | E26: At+Ab | F26: Month | G26: evap(m) | I26: STOR (AF) | J26: elevation (ft) | L26: Month | M26: evap(ft)
B27: =I27*1233.48/1000000 -> 0 | C27: =J27*0.3048 -> 1690.4208 | D27: 0 | E27: =(B28-B27)/(C28-C27)*2*1000000 -> 19078.009 | F27: t1 | G27: =M27*0.3048 -> 0 | I27: 0 | J27: 5546 | L27: t1 | M27: 0
B28: =I28*1233.48/1000000 -> 0.04070484 | C28: =J28*0.3048 -> 1694.688 | D28: =(E27-D27)/1000000 -> 0.019078009 | E28: =(B29-B28)/(C29-C28)*2*1000000 -> 142044.45 | F28: t2 | G28: =M28*0.3048 -> 0 | I28: 33 | J28: 5560 | L28: t2 | M28: 0
B29: =I29*1233.48/1000000 -> 0.47365632 | C29: =J29*0.3048 -> 1700.784 | D29: =(E28-D28)/1000000 -> 0.14204443 | E29: =(B30-B29)/(C30-C29)*2*1000000 -> 297848.19 | F29: t3 | G29: =M29*0.3048 -> 0 | I29: 384 | J29: 5580 | L29: t3 | M29: 0
B30: =I30*1233.48/1000000 -> 1.3814976 | C30: =J30*0.3048 -> 1706.88 | D30: =(E29-D29)/1000000 -> 0.29784805 | E30: =(B31-B30)/(C31-C30)*2*1000000 -> 475909.61 | F30: t4 | G30: =M30*0.3048 -> 0.03048 | I30: 1120 | J30: 5600 | L30: t4 | M30: 0.1
B31: =I31*1233.48/1000000 -> 2.8320701 | C31: =J31*0.3048 -> 1712.976 | D31: =(E30-D30)/1000000 -> 0.47590931 | E31: =(B32-B31)/(C32-C31)*2*1000000 -> 698486.38 | F31: t5 | G31: =M31*0.3048 -> 0.12192 | I31: 2296 | J31: 5620 | L31: t5 | M31: 0.4
B32: =I32*1233.48/1000000 -> 4.9610566 | C32: =J32*0.3048 -> 1719.072 | D32: =(E31-D31)/1000000 -> 0.6984859 | E32: =(B33-B32)/(C33-C32)*2*1000000 -> 985812.76 | F32: t6 | G32: =M32*0.3048 -> 0.1524 | I32: 4022 | J32: 5640 | L32: t6 | M32: 0.5
B33: =I33*1233.48/1000000 -> 7.9658138 | C33: =J33*0.3048 -> 1725.168 | D33: =(E32-D32)/1000000 -> 0.98581206 | E33: =(B34-B33)/(C34-C33)*2*1000000 -> 1573415.4 | F33: t7 | G33: =M33*0.3048 -> 0.18288 | I33: 6458 | J33: 5660 | L33: t7 | M33: 0.6
B34: =I34*1233.48/1000000 -> 12.761584 | C34: =J34*0.3048 -> 1731.264 | D34: =(E33-D33)/1000000 -> 1.5734144 | E34: =(B35-B34)/(C35-C34)*2*1000000 -> 2167088.4 | F34: t8 | G34: =M34*0.3048 -> 0.1524 | I34: 10346 | J34: 5680 | L34: t8 | M34: 0.5
B35: =I35*1233.48/1000000 -> 19.366869 | C35: =J35*0.3048 -> 1737.36 | D35: =(E34-D34)/1000000 -> 2.1670868 | E35: =(B36-B35)/(C36-C35)*2*1000000 -> 2838865.6 | F35: t9 | G35: =M35*0.3048 -> 0.09144 | I35: 15701 | J35: 5700 | L35: t9 | M35: 0.3
B36: =I36*1233.48/1000000 -> 28.019732 | C36: =J36*0.3048 -> 1743.456 | D36: =(E35-D35)/1000000 -> 2.8388634 | E36: =(B37-B36)/(C37-C36)*2*1000000 -> 3569726.7 | F36: t10 | G36: =M36*0.3048 -> 0.09144 | I36: 22716 | J36: 5720 | L36: t10 | M36: 0.3
B37: =I37*1233.48/1000000 -> 38.900259 | C37: =J37*0.3048 -> 1749.552 | D37: =(E36-D36)/1000000 -> 3.5697239 | E37: =(B38-B37)/(C38-C37)*2*1000000 -> 4366146.9 | F37: t11 | G37: =M37*0.3048 -> 0 | I37: 31537 | J37: 5740 | L37: t11 | M37: 0
B38: =I38*1233.48/1000000 -> 52.208274 | C38: =J38*0.3048 -> 1755.648 | D38: =(E37-D37)/1000000 -> 4.3661433 | E38: =(B39-B38)/(C39-C38)*2*1000000 -> 5181991.9 | F38: t12 | G38: =M38*0.3048 -> 0 | I38: 42326 | J38: 5760 | L38: t12 | M38: 0
B39: =I39*1233.48/1000000 -> 68.002986 | C39: =J39*0.3048 -> 1761.744 | D39: =(E38-D38)/1000000 -> 5.1819876 | E39: =(B40-B39)/(C40-C39)*2*1000000 -> 6052064.8 | I39: 55131 | J39: 5780
B40: =I40*1233.48/1000000 -> 86.449679 | C40: =J40*0.3048 -> 1767.84 | D40: =(E39-D39)/1000000 -> 6.0520596 | E40: =(B41-B40)/(C41-C40)*2*1000000 -> 97802.606 | I40: 70086 | J40: 5800
A45: j7 | B45: Cutler | I45: WEAP Data
B46: STOR (m3) | C46: elevation (m) | D46: area (m) | E46: At+Ab | F46: Month | G46: evap(m) | I46: STOR (AF) | J46: elevation (ft) | L46: Month | M46: evap(ft)
B47: =I47*1233.48/1000000 -> 0 | C47: =J47*0.3048 -> 1284.1224 | D47: 0 | E47: =(B48-B47)/(C48-C47)*2*1000000 -> 3570750.3 | F47: t1 | G47: =M47*0.3048 -> 0 | I47: 0 | J47: 4213 | L47: t1 | M47: 0
B48: =I48*1233.48/1000000 -> 9.2511 | C48: =J48*0.3048 -> 1289.304 | D48: =(E47-D47)/1000000 -> 3.5707503 | E48: =(B49-B48)/(C49-C48)*2*1000000 -> 11128839 | F48: t2 | G48: =M48*0.3048 -> 0 | I48: 7500 | J48: 4230 | L48: t2 | M48: 0
B49: =I49*1233.48/1000000 -> 26.21145 | C49: =J49*0.3048 -> 1292.352 | D49: =(E48-D48)/1000000 -> 11.128835 | E49: =(B50-B49)/(C50-C49)*2*1000000 -> 17199114 | F49: t3 | G49: =M49*0.3048 -> 0 | I49: 21250 | J49: 4240 | L49: t3 | M49: 0
B50: =I50*1233.48/1000000 -> 52.4229 | C50: =J50*0.3048 -> 1295.4 | D50: =(E49-D49)/1000000 -> 17.199103 | E50: =(B51-B50)/(C51-C50)*2*1000000 -> 22257677 | F50: t4 | G50: =M50*0.3048 -> 0.03048 | I50: 42500 | J50: 4250 | L50: t4 | M50: 0.1
B51: =I51*1233.48/1000000 -> 86.3436 | C51: =J51*0.3048 -> 1298.448 | D51: =(E50-D50)/1000000 -> 22.25766 | E51: =(B52-B51)/(C52-C51)*2*1000000 -> 25292815 | F51: t5 | G51: =M51*0.3048 -> 0.12192 | I51: 70000 | J51: 4260 | L51: t5 | M51: 0.4
B52: =I52*1233.48/1000000 -> 117.1806 | C52: =J52*0.3048 -> 1300.8864 | D52: =(E51-D51)/1000000 -> 25.292793 | E52: =(B53-B52)/(C53-C52)*2*1000000 -> 28906074 | F52: t6 | G52: =M52*0.3048 -> 0.1524 | I52: 95000 | J52: 4268 | L52: t6 | M52: 0.5
B53: =I53*1233.48/1000000 -> 148.0176 | C53: =J53*0.3048 -> 1303.02 | D53: =(E52-D52)/1000000 -> 28.906049 | E53: =(B54-B53)/(C54-C53)*2*1000000 -> 227191.6 | F53: t7 | G53: =M53*0.3048 -> 0.18288 | I53: 120000 | J53: 4275 | L53: t7 | M53: 0.6
F54: t8 | G54: =M54*0.3048 -> 0.1524 | L54: t8 | M54: 0.5
F55: t9 | G55: =M55*0.3048 -> 0.09144 | L55: t9 | M55: 0.3
F56: t10 | G56: =M56*0.3048 -> 0.09144 | L56: t10 | M56: 0.3
F57: t11 | G57: =M57*0.3048 -> 0 | L57: t11 | M57: 0
F58: t12 | G58: =M58*0.3048 -> 0 | L58: t12 | M58: 0
A62: j1 | B62: Onida | I62: WEAP Data
B63: STOR (m3) | C63: elevation (m) | D63: area (m) | E63: At+Ab | F63: Month | G63: evap(m) | I63: STOR (AF) | J63: elevation (ft) | L63: Month | M63: evap(ft)
B64: =(I64*1233.48)/1000000 -> 0 | C64: =J64*0.3048 -> 13621.817 | D64: 0 | E64: =(B65-B64)/(C65-C64)*2*1000000 -> -985.17919 | F64: t1 | G64: =M64*0.3048 -> 0 | I64: 0 | J64: 44691 | L64: t1 | M64: 0
B65: =(I65*1233.48)/1000000 -> 5.9996467 | C65: =J65*0.3048 -> 1442.0088 | D65: =(E64-D64)/1000000 -> -0.00098517919 | E65: =(B66-B65)/(C66-C65)*2*1000000 -> 2258790 | F65: t2 | G65: =M65*0.3048 -> 0 | I65: 4864 | J65: 4731 | L65: t2 | M65: 0
B66: =(I66*1233.48)/1000000 -> 14.605637 | C66: =J66*0.3048 -> 1449.6288 | D66: =(E65-D65)/1000000 -> 2.25879 | E66: =(B67-B66)/(C67-C66)*2*1000000 -> 3050030.2 | F66: t3 | G66: =M66*0.3048 -> 0 | I66: 11841 | J66: 4756 | L66: t3 | M66: 0
B67: =(I67*1233.48)/1000000 -> 26.226252 | C67: =J67*0.3048 -> 1457.2488 | D67: =(E66-D66)/1000000 -> 3.0500279 | E67: =(B68-B67)/(C68-C67)*2*1000000 -> 3739613.5 | F67: t4 | G67: =M67*0.3048 -> 0.03048 | I67: 21262 | J67: 4781 | L67: t4 | M67: 0.1
B68: =(I68*1233.48)/1000000 -> 40.474179 | C68: =J68*0.3048 -> 1464.8688 | D68: =(E67-D67)/1000000 -> 3.7396105 | E68: =(B69-B68)/(C69-C68)*2*1000000 -> 4421750.6 | F68: t5 | G68: =M68*0.3048 -> 0.12192 | I68: 32813 | J68: 4806 | L68: t5 | M68: 0.4
B69: =(I69*1233.48)/1000000 -> 57.321049 | C69: =J69*0.3048 -> 1472.4888 | D69: =(E68-D68)/1000000 -> 4.4217469 | E69: =(B70-B69)/(C70-C69)*2*1000000 -> 5518932.7 | F69: t6 | G69: =M69*0.3048 -> 0.1524 | I69: 46471 | J69: 4831 | L69: t6 | M69: 0.5
B70: =(I70*1233.48)/1000000 -> 78.348183 | C70: =J70*0.3048 -> 1480.1088 | D70: =(E69-D69)/1000000 -> 5.5189283 | E70: =(B71-B70)/(C71-C70)*2*1000000 -> 8608136.4 | F70: t7 | G70: =M70*0.3048 -> 0.18288 | I70: 63518 | J70: 4856 | L70: t7 | M70: 0.6
B71: =(I71*1233.48)/1000000 -> 111.14518 | C71: =J71*0.3048 -> 1487.7288 | D71: =(E70-D70)/1000000 -> 8.6081309 | E71: =(B72-B71)/(C72-C71)*2*1000000 -> 9929028.4 | F71: t8 | G71: =M71*0.3048 -> 0.1524 | I71: 90107 | J71: 4881 | L71: t8 | M71: 0.5
B72: =(I72*1233.48)/1000000 -> 148.97478 | C72: =J72*0.3048 -> 1495.3488 | D72: =(E71-D71)/1000000 -> 9.9290198 | E72: =(B73-B72)/(C73-C72)*2*1000000 -> 199250.88 | F72: t9 | G72: =M72*0.3048 -> 0.09144 | I72: 120776 | J72: 4906 | L72: t9 | M72: 0.3
F73: t10 | G73: =M73*0.3048 -> 0.09144 | L73: t10 | M73: 0.3
F74: t11 | G74: =M74*0.3048 -> 0 | L74: t11 | M74: 0
F75: t12 | G75: =M75*0.3048 -> 0 | L75: t12 | M75: 0
A80: j17 | B80: Mainstem | I80: WEAP Data
B81: STOR (Mm3) | C81: elevation (m) | D81: area (Mm2) | E81: At+Ab | F81: Month | G81: evap(m) | I81: STOR (AF) | J81: elevation (ft) | L81: Month | M81: evap(ft)
B82: =I82*1233.48/1000000 -> 0 | C82: =J82*0.3048 -> 1284.1224 | D82: 0 | E82: =(B83-B82)/(C83-C82)*2*1000000 -> 3570750.3 | F82: t1 | G82: =M82*0.3048 -> 0 | I82: 0 | J82: 4213 | L82: t1 | M82: 0
B83: =I83*1233.48/1000000 -> 9.2511 | C83: =J83*0.3048 -> 1289.304 | D83: =(E82-D82)/1000000 -> 3.5707503 | E83: =(B84-B83)/(C84-C83)*2*1000000 -> 11128839 | F83: t2 | G83: =M83*0.3048 -> 0 | I83: 7500 | J83: 4230 | L83: t2 | M83: 0
B84: =I84*1233.48/1000000 -> 26.21145 | C84: =J84*0.3048 -> 1292.352 | D84: =(E83-D83)/1000000 -> 11.128835 | E84: =(B85-B84)/(C85-C84)*2*1000000 -> 17199114 | F84: t3 | G84: =M84*0.3048 -> 0 | I84: 21250 | J84: 4240 | L84: t3 | M84: 0
B85: =I85*1233.48/1000000 -> 52.4229 | C85: =J85*0.3048 -> 1295.4 | D85: =(E84-D84)/1000000 -> 17.199103 | E85: =(B86-B85)/(C86-C85)*2*1000000 -> 22257677 | F85: t4 | G85: =M85*0.3048 -> 0.03048 | I85: 42500 | J85: 4250 | L85: t4 | M85: 0.1
B86: =I86*1233.48/1000000 -> 86.3436 | C86: =J86*0.3048 -> 1298.448 | D86: =(E85-D85)/1000000 -> 22.25766 | E86: =(B87-B86)/(C87-C86)*2*1000000 -> 25292815 | F86: t5 | G86: =M86*0.3048 -> 0.12192 | I86: 70000 | J86: 4260 | L86: t5 | M86: 0.4
B87: =I87*1233.48/1000000 -> 117.1806 | C87: =J87*0.3048 -> 1300.8864 | D87: =(E86-D86)/1000000 -> 25.292793 | E87: =(B88-B87)/(C88-C87)*2*1000000 -> 28906074 | F87: t6 | G87: =M87*0.3048 -> 0.1524 | I87: 95000 | J87: 4268 | L87: t6 | M87: 0.5
B88: =I88*1233.48/1000000 -> 148.0176 | C88: =J88*0.3048 -> 1303.02 | D88: =(E87-D87)/1000000 -> 28.906049 | E88: =(B89-B88)/(C89-C88)*2*1000000 -> 227191.6 | F88: t7 | G88: =M88*0.3048 -> 0.18288 | I88: 120000 | J88: 4275 | L88: t7 | M88: 0.6
F89: t8 | G89: =M89*0.3048 -> 0.1524 | L89: t8 | M89: 0.5
F90: t9 | G90: =M90*0.3048 -> 0.09144 | L90: t9 | M90: 0.3
F91: t10 | G91: =M91*0.3048 -> 0.09144 | L91: t10 | M91: 0.3
F92: t11 | G92: =M92*0.3048 -> 0 | L92: t11 | M92: 0
F93: t12 | G93: =M93*0.3048 -> 0 | L93: t12 | M93: 0
A96: j29 | B96: Hyrum | I96: WEAP Data | O96: Adel
B97: STOR (Mm3) | C97: elevation (m) | D97: area (Mm2) | E97: At+Ab | F97: Month | G97: evap(m) | H97: Area - Adel | I97: STOR (AF) | J97: elevation (ft) | L97: Month | M97: evap(ft) | O97: Elevation (ft) | P97: Area (Acre) | Q97: Storage (Acre-Feet)
B98: =Q98*0.00123348185532 -> 0 | C98: =J98*0.3048 -> 1399.032 | D98: 0 | E98: =(B99-B98)/(C99-C98)*2*1000000 -> 105218.27 | F98: t1 | G98: =M98*0.3048 -> 0 | H98: =P98*0.0040468564224 -> 0.0040468564 | I98: 0 | J98: 4590 | L98: t1 | M98: 0 | O98: 4590 | P98: 1 | Q98: 0
B99: =Q99*0.00123348185532 -> 0.16035264 | C99: =J99*0.3048 -> 1402.08 | D99: =(E98-D98)/1000000 -> 0.10521827 | E99: =(B100-B99)/(C100-C99)*2*1000000 -> 420063.7 | F99: t2 | G99: =M99*0.3048 -> 0 | H99: =P99*0.0040468564224 -> 0.10521827 | I99: 130 | J99: 4600 | L99: t2 | M99: 0 | O99: 4600 | P99: 26 | Q99: 130
B100: =Q100*0.00123348185532 -> 0.80052972 | C100: =J100*0.3048 -> 1405.128 | D100: =(E99-D99)/1000000 -> 0.4200636 | E100: =(B101-B100)/(C101-C100)*2*1000000 -> 882214.71 | F100: t3 | G100: =M100*0.3048 -> 0 | H100: =P100*0.0040468564224 -> 0.30756109 | I100: 649 | J100: 4610 | L100: t3 | M100: 0 | O100: 4610 | P100: 76 | Q100: 649
B101: =Q101*0.00123348185532 -> 2.1450249 | C101: =J101*0.3048 -> 1408.176 | D101: =(E100-D100)/1000000 -> 0.88221429 | E101: =(B102-B101)/(C102-C101)*2*1000000 -> 1389690.5 | F101: t4 | G101: =M101*0.3048 -> 0.03048 | H101: =P101*0.0040468564224 -> 0.57465361 | I101: 1739 | J101: 4620 | L101: t4 | M101: 0.1 | O101: 4620 | P101: 142 | Q101: 1739
B102: =Q102*0.00123348185532 -> 4.2629133 | C102: =J102*0.3048 -> 1411.224 | D102: =(E101-D101)/1000000 -> 1.3896896 | E102: =(B103-B102)/(C103-C102)*2*1000000 -> 2008050.2 | F102: t5 | G102: =M102*0.3048 -> 0.12192 | H102: =P102*0.0040468564224 -> 0.82960557 | I102: 3456 | J102: 4630 | L102: t5 | M102: 0.4 | O102: 4630 | P102: 205 | Q102: 3456
B103: =Q103*0.00123348185532 -> 7.3231818 | C103: =J103*0.3048 -> 1414.272 | D103: =(E102-D102)/1000000 -> 2.0080488 | E103: =(B104-B103)/(C104-C103)*2*1000000 -> 2670115.9 | F103: t6 | G103: =M103*0.3048 -> 0.1524 | H103: =P103*0.0040468564224 -> 1.1776352 | I103: 5937 | J103: 4640 | L103: t6 | M103: 0.5 | O103: 4640 | P103: 291 | Q103: 5937
B104: =Q104*0.00123348185532 -> 11.392438 | C104: =J104*0.3048 -> 1417.32 | D104: =(E103-D103)/1000000 -> 2.6701139 | E104: =(B105-B104)/(C105-C104)*2*1000000 -> 3213204 | F104: t7 | G104: =M104*0.3048 -> 0.18288 | H104: =P104*0.0040468564224 -> 1.4851963 | I104: 9236 | J104: 4650 | L104: t7 | M104: 0.6 | O104: 4650 | P104: 367 | Q104: 9236
B105: =Q105*0.00123348185532 -> 16.289361 | C105: =J105*0.3048 -> 1420.368 | D105: =(E104-D104)/1000000 -> 3.2132014 | E105: =(B106-B105)/(C106-C105)*2*1000000 -> 3654311.4 | F105: t8 | G105: =M105*0.3048 -> 0.1524 | H105: =P105*0.0040468564224 -> 1.7280077 | I105: 13206 | J105: 4660 | L105: t8 | M105: 0.5 | O105: 4660 | P105: 427 | Q105: 13206
B106: =Q106*0.00123348185532 -> 21.858532 | C106: =J106*0.3048 -> 1423.416 | D106: =(E105-D105)/1000000 -> 3.6543082 | E106: =(B107-B106)/(C107-C106)*2*1000000 -> 3897122.8 | F106: t9 | G106: =M106*0.3048 -> 0.09144 | H106: =P106*0.0040468564224 -> 1.9141631 | I106: 17721 | J106: 4670 | L106: t9 | M106: 0.3 | O106: 4670 | P106: 473 | Q106: 17721
B107: =Q107*0.00123348185532 -> 23.046375 | C107: =J107*0.3048 -> 1424.0256 | D107: =(E106-D106)/1000000 -> 3.8971191 | E107: =(B108-B107)/(C108-C107)*2*1000000 -> 3961872.5 | F107: t10 | G107: =M107*0.3048 -> 0.09144 | H107: =P107*0.0040468564224 -> 1.9384442 | I107: 18684 | J107: 4672 | L107: t10 | M107: 0.3 | O107: 4672 | P107: 479 | Q107: 18684
B108: =Q108*0.00123348185532 -> 27.87669 | C108: =J108*0.3048 -> 1426.464 | D108: =(E107-D107)/1000000 -> 3.9618686 | E108: =(B109-B108)/(C109-C108)*2*1000000 -> 4451542.1 | F108: t11 | G108: =M108*0.3048 -> 0 | H108: =P108*0.0040468564224 -> 2.0881779 | I108: 22600 | J108: 4680 | L108: t11 | M108: 0 | O108: 4680 | P108: 516 | Q108: 22600
B109: =Q109*0.00123348185532 -> 34.66084 | C109: =J109*0.3048 -> 1429.512 | D109: =(E108-D108)/1000000 -> 4.4515382 | E109: =(B110-B109)/(C110-C109)*2*1000000 -> 4856227.8 | F109: t12 | G109: =M109*0.3048 -> 0 | H109: =P109*0.0040468564224 -> 2.3148019 | I109: 28100 | J109: 4690 | L109: t12 | M109: 0 | O109: 4690 | P109: 572 | Q109: 28100
B110: =Q110*0.00123348185532 -> 42.061731 | C110: =J110*0.3048 -> 1432.56 | D110: =(E109-D109)/1000000 -> 4.8562233 | E110: =(B111-B110)/(C111-C110)*2*1000000 -> 5341850.6 | H110: =P110*0.0040468564224 -> 2.5454727 | I110: 34100 | J110: 4700 | O110: 4700 | P110: 629 | Q110: 34100
B111: =Q111*0.00123348185532 -> 50.202712 | C111: =J111*0.3048 -> 1435.608 | D111: =(E110-D110)/1000000 -> 5.3418457 | E111: =(B112-B111)/(C112-C111)*2*1000000 -> 5827473.3 | H111: =P111*0.0040468564224 -> 2.8004246 | I111: 40700 | J111: 4710 | O111: 4710 | P111: 692 | Q111: 40700
B112: =Q112*0.00123348185532 -> 59.083781 | C112: =J112*0.3048 -> 1438.656 | D112: =(E111-D111)/1000000 -> 5.827468 | E112: =(B113-B112)/(C113-C112)*2*1000000 -> 6394033.2 | H112: =P112*0.0040468564224 -> 3.0634703 | I112: 47900 | J112: 4720 | O112: 4720 | P112: 757 | Q112: 47900
B113: =Q113*0.00123348185532 -> 68.828288 | C113: =J113*0.3048 -> 1441.704 | D113: =(E112-D112)/1000000 -> 6.3940274 | E113: =(B114-B113)/(C114-C113)*2*1000000 -> 7041530.3 | H113: =P113*0.0040468564224 -> 3.3427034 | I113: 55800 | J113: 4730 | O113: 4730 | P113: 826 | Q113: 55800
B114: =Q114*0.00123348185532 -> 79.55958 | C114: =J114*0.3048 -> 1444.752 | D114: =(E113-D113)/1000000 -> 7.0415239 | E114: =(B115-B114)/(C115-C114)*2*1000000 -> 7608090.2 | H114: =P114*0.0040468564224 -> 3.6421708 | I114: 64500 | J114: 4740 | O114: 4740 | P114: 900 | Q114: 64500
B115: =Q115*0.00123348185532 -> 91.154309 | C115: =J115*0.3048 -> 1447.8 | D115: =(E114-D114)/1000000 -> 7.6080831 | E115: =(B116-B115)/(C116-C115)*2*1000000 -> 125921.13 | H115: =P115*0.0040468564224 -> 3.9497319 | I115: 73900 | J115: 4750 | O115: 4750 | P115: 976 | Q115: 73900
A120: j33 | B120: Porcupine | I120: WEAP Data
B121: STOR (Mm3) | C121: elevation (m) | D121: area (Mm2) | E121: At+Ab | F121: Month | G121: evap(m) | I121: STOR (AF) | J121: elevation (ft) | K121: Area Acres | L121: Month | M121: evap(ft)
B122: =I122*1233.48/1000000 -> 0 | C122: =J122*0.3048 -> 1597.152 | D122: =K122*4046.856/1000000 -> 0 | E122: =(B123-B122)/(C123-C122)*2*1000000 -> 101171.26 | F122: t1 | G122: =M122*0.3048 -> 0 | I122: 0 | J122: 5240 | K122: 0 | L122: t1 | M122: 0
B123: =I123*1233.48/1000000 -> 0.30837 | C123: =J123*0.3048 -> 1603.248 | D123: =K123*4046.856/1000000 -> 0.1011714 | E123: =(B124-B123)/(C124-C123)*2*1000000 -> 256300.52 | F123: t2 | G123: =M123*0.3048 -> 0 | I123: 250 | J123: 5260 | K123: 25 | L123: t2 | M123: 0
B124: =I124*1233.48/1000000 -> 1.480176 | C124: =J124*0.3048 -> 1612.392 | D124: =K124*4046.856/1000000 -> 0.15378053 | E124: =(B125-B124)/(C125-C124)*2*1000000 -> 566559.06 | F124: t3 | G124: =M124*0.3048 -> 0 | I124: 1200 | J124: 5290 | K124: 38 | L124: t3 | M124: 0
B125: =I125*1233.48/1000000 -> 3.207048 | C125: =J125*0.3048 -> 1618.488 | D125: =K125*4046.856/1000000 -> 0.28327992 | E125: =(B126-B125)/(C126-C125)*2*1000000 -> 822859.58 | F125: t4 | G125: =M125*0.3048 -> 0.03048 | I125: 2600 | J125: 5310 | K125: 70 | L125: t4 | M125: 0.1
...

Sheet Cons
B1: t1 | C1: t2 | D1: t3 | E1: t4 | F1: t5 | G1: t6 | H1: t7 | I1: t8 | J1: t9 | K1: t10 | L1: t11 | M1: t12 | R1: Value in WEAP
A2: j3 | B2: 0.27 | C2: 0.27 | D2: 0.27 | E2: 0.73 | F2: 0.73 | G2: 0.73 | H2: 0.73 | I2: 0.73 | J2: 0.73 | K2: 0.73 | L2: 0.27 | M2: 0.27 | R2: Y | S2: j3 | T2: Cache M&I
A3: j8 | B3: 1 | C3: 1 | D3: 1 | E3: 1 | F3: 1 | G3: 1 | H3: 1 | I3: 1 | J3: 1 | K3: 1 | L3: 1 | M3: 1 | R3: N | S3: j8 | T3: BRCC
A4: j13 | B4: 0.27 | C4: 0.27 | D4: 0.27 | E4: 0.73 | F4: 0.73 | G4: 0.73 | H4: 0.73 | I4: 0.73 | J4: 0.73 | K4: 0.73 | L4: 0.27 | M4: 0.27 | R4: N | S4: j13 | T4: Box Elder M&I
A5: j16 | B5: 1 | C5: 1 | D5: 1 | E5: 1 | F5: 1 | G5: 1 | H5: 1 | I5: 1 | J5: 1 | K5: 1 | L5: 1 | M5: 1 | R5: N | S5: j16 | T5: Wasatch Front
A6: j15 | B6: 1 | C6: 1 | D6: 1 | E6: 1 | F6: 1 | G6: 1 | H6: 1 | I6: 1 | J6: 1 | K6: 1 | L6: 1 | M6: 1 | R6: N | S6: j15 | T6: Box Elder Ag
A7: j28 | B7: 1 | C7: 1 | D7: 1 | E7: 1 | F7: 1 | G7: 1 | H7: 1 | I7: 1 | J7: 1 | K7: 1 | L7: 1 | M7: 1 | R7: N | S7: j28 | T7: South Cache M&I
A8: j27 | B8: 0.27 | C8: 0.27 | D8: 0.27 | E8: 0.73 | F8: 0.73 | G8: 0.73 | H8: 0.73 | I8: 0.73 | J8: 0.73 | K8: 0.73 | L8: 0.27 | M8: 0.27 | R8: N | S8: j27 | T8: South Cache New
A9: j39 | B9: 1 | C9: 1 | D9: 1 | E9: 1 | F9: 1 | G9: 1 | H9: 1 | I9: 1 | J9: 1 | K9: 1 | L9: 1 | M9: 1 | R9: Y | S9: j39 | T9: Cache Ag
A10: j38 | B10: 1 | C10: 1 | D10: 1 | E10: 1 | F10: 1 | G10: 1 | H10: 1 | I10: 1 | J10: 1 | K10: 1 | L10: 1 | M10: 1
A11: j41 | B11: 0.27 | C11: 0.27 | D11: 0.27 | E11: 0.73 | F11: 0.73 | G11: 0.73 | H11: 0.73 | I11: 0.73 | J11: 0.73 | K11: 0.73 | L11: 0.27 | M11: 0.27
A12: j42 | B12: 0.27 | C12: 0.27 | D12: 0.27 | E12: 0.73 | F12: 0.73 | G12: 0.73 | H12: 0.73 | I12: 0.73 | J12: 0.73 | K12: 0.73 | L12: 0.27 | M12: 0.27
A13: j44 | B13: 0.27 | C13: 0.27 | D13: 0.27 | E13: 0.73 | F13: 0.73 | G13: 0.73 | H13: 0.73 | I13: 0.73 | J13: 0.73 | K13: 0.73 | L13: 0.27 | M13: 0.27

Sheet inactive
A1: j1 | B1: 0
A2: j7 | B2: 0
A3: j17 | B3: 0
A4: j29 | B4: 4.2 | F4: 4.2
A5: j33 | B5: =2000*1233.48/1000000 -> 2.46696 | F5: =2000*1233.48/1000000 -> 2.46696

Sheet capacity
A1: j1 | B1: 0
A2: j7 | B2: 0
A3: j17 | B3: 0
A4: j29 | B4: =23046340/1000000 -> 23.04634 | G4: =23046340/1000000 -> 23.04634
A5: j33 | B5: =13000*1233.48/1000000 -> 16.03524 | G5: =13000*1233.48/1000000 -> 16.03524

Sheet InStor
A1: j1 | B1: 0 | G1: WEAP
A2: j7 | B2: 0
A3: j17 | B3: 0
A4: j29 | B4: 5 | F4: 5 | H4: 12.796141
A5: j33 | B5: 3 | F5: 3 | H5: 3

Sheet demandReq
B1: t1 | C1: t2 | D1: t3 | E1: t4 | F1: t5 | G1: t6 | H1: t7 | I1: t8 | J1: t9 | K1: t10 | L1: t11 | M1: t12
A2: j3 | B2: 2.376916 | C2: 2.376916 | D2: 2.376916 | E2: 8.8748886 | F2: 8.8748886 | G2: 8.8748886 | H2: 8.8748886 | I2: 8.8748886 | J2: 8.8748886 | K2: 8.8748886 | L2: 2.376916 | M2: 2.376916
A3: j8 | B3: 1.575154 | C3: 0.97074876 | D3: 0.36757704 | E3: 3.1379731 | F3: 42.490919 | G3: 56.682106 | H3: 59.722265 | I3: 56.020529 | J3: 43.834179 | K3: 20.588015 | L3: 5.6444045 | M3: 1.9254623
A4: j13 | B4: 0 | C4: 0 | D4: 0 | E4: 0 | F4: 0 | G4: 0 | H4: 0 | I4: 0 | J4: 0 | K4: 0 | L4: 0 | M4: 0
A5: j16 | B5: 0 | C5: 0 | D5: 0 | E5: 0 | F5: 0 | G5: 0 | H5: 0 | I5: 0 | J5: 0 | K5: 0 | L5: 0 | M5: 0
A6: j15 | B6: 0 | C6: 0 | D6: 0 | E6: 0 | F6: 0 | G6: 0 | H6: 0 | I6: 0 | J6: 0 | K6: 0 | L6: 0 | M6: 0
A7: j28 | B7: =B25*0.0744661151309 -> 0 | C7: =C25*0.0744661151309 -> 0 | D7: =D25*0.0744661151309 -> 0 | E7: =E25*0.0744661151309 -> 0 | F7: =F25*0.0744661151309 -> 1.6015534 | G7: =G25*0.0744661151309 -> 2.1768928 | H7: =H25*0.0744661151309 -> 2.0624712 | I7: =I25*0.0744661151309 -> 1.8378718 | ... M7: =M25*0.0744661151309 -> 0
A8: j27 | B8: =B26*0.0744661151309 -> 0 | C8: =C26*0.0744661151309 -> 0 | D8: =D26*0.0744661151309 -> 0 | E8: =E26*0.0744661151309 -> 0 | F8: =F26*0.0744661151309 -> 0 | G8: =G26*0.0744661151309 -> 0 | H8: =H26*0.0744661151309 -> 0 | I8: =I26*0.0744661151309 -> 0 | ... M8: =M26*0.0744661151309 -> 0
A9: j39 | B9: =B27*0.0744661151309 -> 0 | C9: =C27*0.0744661151309 -> 0 | D9: =D27*0.0744661151309 -> 0 | E9: =E27*0.0744661151309 -> 0 | F9: =F27*0.0744661151309 -> 0 | G9: =G27*0.0744661151309 -> 0 | H9: =H27*0.0744661151309 -> 0 | I9: =I27*0.0744661151309 -> 0 | ... M9: =M27*0.0744661151309 -> 0
A10: j38 | B10: =B28*0.0744661151309 -> 0 | C10: =C28*0.0744661151309 -> 0 | D10: =D28*0.0744661151309 -> 0 | E10: =E28*0.0744661151309 -> 0 | F10: =F28*0.0744661151309 -> 2.8759877 | G10: =G28*0.0744661151309 -> 2.4447226 | H10: =H28*0.0744661151309 -> 1.9548556 | I10: =I28*0.0744661151309 -> 1.7756565 | ... M10: =M28*0.0744661151309 -> 0
A11: j41 | B11: =B29*0.0744661151309 -> 0 | C11: =C29*0.0744661151309 -> 0 | D11: =D29*0.0744661151309 -> 0 | E11: =E29*0.0744661151309 -> 0 | F11: =F29*0.0744661151309 -> 0.89566779 | G11: =G29*0.0744661151309 -> 1.7569039 | H11: =H29*0.0744661151309*0.5 -> 1.2348163 | I11: =I29*0.0744661151309*0.3 -> 0.72345032 | J11: 0 | K11: =K29*0.0744661151309 -> 0 | L11: =L29*0.0744661151309 -> 0 | M11: =M29*0.0744661151309 -> 0
A12: j42 | B12: =B30*0.0744661151309 -> 0 | C12: =C30*0.0744661151309 -> 0 | D12: =D30*0.0744661151309 -> 0 | E12: =E30*0.0744661151309 -> 0 | F12: =F30*0.0744661151309 -> 2.8759877 | G12: =G30*0.0744661151309 -> 2.4447226 | H12: =H30*0.0744661151309 -> 1.9548556 | I12: =I30*0.0744661151309 -> 1.7756565 | ... M12: =M30*0.0744661151309 -> 0
A13: j44 | B13: =B31*0.0744661151309 -> 0 | C13: =C31*0.0744661151309 -> 0 | D13: =D31*0.0744661151309 -> 0 | E13: =E31*0.0744661151309 -> 0 | F13: =F31*0.0744661151309 -> 2.4287711 | G13: =G31*0.0744661151309 -> 4.3567642 | H13: =H31*0.0744661151309 -> 4.2909297 | I13: =I31*0.0744661151309 -> 3.0648812 | ... M13: =M31*0.0744661151309 -> 0
A24: cfs
A25: j28 | B25: 0 | C25: 0 | D25: 0 | E25: 0 | F25: 21.507143 | G25: 29.233333 | H25: 27.696774 | I25: 24.680645 | J25: 13.956667 | K25: 0 | L25: 0 | M25: 0
A26: j27 | B26: 0 | C26: 0 | D26: 0 | E26: 0 | F26: 0 | G26: 0 | H26: 0 | I26: 0 | J26: 0 | K26: 0 | L26: 0 | M26: 0
A27: j39 | B27: 0 | C27: 0 | D27: 0 | E27: 0 | F27: 0 | G27: 0 | H27: 0 | I27: 0 | J27: 0 | K27: 0 | L27: 0 | M27: 0
A28: j38 | F28: 38.621429 | G28: 32.83 | H28: 26.251613 | I28: 23.845161 | J28: 13.023333
A29: j41 | F29: 12.027857 | G29: 23.593333 | H29: 33.164516 | I29: 32.383871 | J29: 13.22
A30: j42 | F30: 38.621429 | G30: 32.83 | H30: 26.251613 | I30: 23.845161 | J30: 13.023333
A31: j44 | F31: 32.615789 | G31: 58.506667 | H31: 57.622581 | I31: 41.158065 | J31: 0
A45: j28 | E45: Old | F45: 3.7716555 | G45: 4.2016264 | H45: 4.4244883 | I45: 4.1871576 | J45: 1.9542391

Sheet Instream
C1: t1 | D1: t2 | E1: t3 | F1: t4 | G1: t5 | H1: t6 | I1: t7 | J1: t8 | K1: t9 | L1: t10 | M1: t11 | N1: t12
A2: j37 | B2: j1 | C2: 0 | D2: 0 | E2: 0 | F2: 0 | G2: 0 | H2: 0 | I2: 0 | J2: 0 | K2: 0 | L2: 0 | M2: 0 | N2: 0
A3: j1 | B3: j4 | C3: 0 | D3: 0 | E3: 0 | F3: 0 | G3: 0 | H3: 0 | I3: 0 | J3: 0 | K3: 0 | L3: 0 | M3: 0 | N3: 0
A4: j4 | B4: j5 | C4: 0 | D4: 0 | E4: 0 | F4: 0 | G4: 0 | H4: 0 | I4: 0 | J4: 0 | K4: 0 | L4: 0 | M4: 0 | N4: 0
A5: j6 | B5: j5 | C5: 0 | D5: 0 | E5: 0 | F5: 0 | G5: 0 | H5: 0 | I5: 0 | J5: 0 | K5: 0 | L5: 0 | M5: 0 | N5: 0
A6: j5 | B6: j18 | C6: 0 | D6: 0 | E6: 0 | F6: 0 | G6: 0 | H6: 0 | I6: 0 | J6: 0 | K6: 0 | L6: 0 | M6: 0 | N6: 0
A7: j18 | B7: j7 | C7: 0 | D7: 0 | E7: 0 | F7: 0 | G7: 0 | H7: 0 | I7: 0 | J7: 0 | K7: 0 | L7: 0 | M7: 0 | N7: 0
A8: j7 | B8: j9 | C8: 0 | D8: 0 | E8: 0 | F8: 0 | G8: 0 | H8: 0 | I8: 0 | J8: 0 | K8: 0 | L8: 0 | M8: 0 | N8: 0
A9: j9 | B9: j12 | C9: 0 | D9: 0 | E9: 0 | F9: 0 | G9: 0 | H9: 0 | I9: 0 | J9: 0 | K9: 0 | L9: 0 | M9: 0 | N9: 0
A10: j12 | B10: j14 | C10: 0 | D10: 0 | E10: 0 | F10: 0 | G10: 0 | H10: 0 | I10: 0 | J10: 0 | K10: 0 | L10: 0 | M10: 0 | N10: 0
A11: j14 | B11: j17 | C11: 0 | D11: 0 | E11: 0 | F11: 0 | G11: 0 | H11: 0 | I11: 0 | J11: 0 | K11: 0 | L11: 0 | M11: 0 | N11: 0
A12: j17 | B12: j20 | C12: 0 | D12: 0 | E12: 0 | F12: 0 | G12: 0 | H12: 0 | I12: 0 | J12: 0 | K12: 0 | L12: 0 | M12: 0 | N12: 0
A13: j19 | B13: j20 | C13: 0 | D13: 0 | E13: 0 | F13: 0 | G13: 0 | H13: 0 | I13: 0 | J13: 0 | K13: 0 | L13: 0 | M13: 0 | N13: 0
... A27: j45 | B27: j32 | C27: 0 | D27: 0 | E27: 0 | F27: 0 | G27: 0 | H27: 0 | I27: 0 | J27: 0 | K27: 0 | L27: 0 | M27: 0 | N27: 0

Sheet divCap
A1: j4 | B1: j39 | C1: 100000
A2: j7 | B2: j16 | C2: 100000
A3: j7 | B3: j8 | C3: 100000
A4: j17 | B4: j16 | C4: 100000
A5: j29 | B5: j44 | C5: 100000
A6: j29 | B6: j28 | C6: 100000
A7: j12 | B7: j13 | C7: 100000
A8: j12 | B8: j15 | C8: 100000
A9: j30 | B9: j27 | C9: 100000
A10: j4 | B10: j3 | C10: 100000
A11: j45 | B11: j42 | C11: 100000
A12: j43 | B12: j41 | C12: 100000
A13: j33 | B13: j38 | C13: 100000

Sheet StageFlow
C1: sf_par1 | D1: sf_par2 | K1: Old | L1: Old
A2: j4 | B2: j5 | C2: 0.0117 | D2: 0.9086 | K2: 0.0117 | L2: 0.9086
A3: j6 | B3: j5 | C3: 0.0222 | D3: 1.5952 | K3: 0.0222 | L3: 1.5952
A4: j5 | B4: j18 | C4: 0.0142 | D4: 1.181 | K4: 0.0142 | L4: 1.181
A5: j21 | B5: j23 | C5: 0.0121 | D5: 0.6608 | K5: 0.0121 | L5: 0.6608
A6: j37 | B6: j1 | C6: 0.0083 | D6: 0.7054 | K6: 0.0083 | L6: 0.7054
A7: j1 | B7: j4 | C7: 0.0083 | D7: 0.7054 | K7: 0.0083 | L7: 0.7054
A8: j18 | B8: j7 | C8: 0.0121 | D8: 0.3608 | K8: 0.0121 | L8: 0.3608
A9: j7 | B9: j9 | C9: 0.0121 | D9: 0.3608 | K9: 0.0121 | L9: 0.3608
A10: j12 | B10: j14 | C10: 0.0121 | D10: 0.3608 | K10: 0.0121 | L10: 0.3608
A11: j14 | B11: j17 | C11: 0.0121 | D11: 0.3608 | K11: 0.0121 | L11: 0.3608
A12: j17 | B12: j20 | C12: 0.0121 | D12: 0.3608 | K12: 0.0121 | L12: 0.3608
A13: j19 | B13: j20 | C13: 0.0256 | D13: 0.2982 | K13: 0.0256 | L13: 0.2982
... A27: j45 | B27: j32 | C27: 0.0505 | D27: 0.357 | K27: 0.0217 | L27: 1.0789

Sheet WidthFlow
C1: wf_par1 | D1: wf_par2 | L1: Old values
A2: j4 | B2: j5 | C2: 0.0822 | D2: 32.695 | L2: 24.762 | M2: 0.1031
A3: j6 | B3: j5 | C3: 0.2618 | D3: 9.0059 | L3: 8.8047 | M3: 0.1246
A4: j5 | B4: j18 | C4: 0.1234 | D4: 29.276 | L4: 18.932 | M4: 0.1618
A5: j21 | B5: j23 | C5: 0.1618 | D5: 18.932 | L5: 18.932 | M5: 0.1618
A6: j37 | B6: j1 | C6: 0.1031 | D6: 24.762 | L6: 24.762 | M6: 0.1031
A7: j1 | B7: j4 | C7: 0.1031 | D7: 24.762 | L7: 24.762 | M7: 0.1031
A8: j18 | B8: j7 | C8: 0.1618 | D8: 18.932 | L8: 18.932 | M8: 0.1618
A9: j7 | B9: j9 | C9: 0.1618 | D9: 28.221 | L9: 18.932 | M9: 0.1618
A10: j12 | B10: j14 | C10: 0.1618 | D10: 28.221 | L10: 18.932 | M10: 0.1618
A11: j14 | B11: j17 | C11: 0.1618 | D11: 28.221 | L11: 18.932 | M11: 0.1618
A12: j17 | B12: j20 | C12: 0.1618 | D12: 28.221 | L12: 18.932 | M12: 0.1618
A13: j19 | B13: j20 | C13: 0.1618 | D13: 28.221 | L13: 18.932 | M13: 0.1618
... A27: j45 | B27: j32 | C27: 0.1618 | D27: 15.32 | L27: 18.932 | M27: 0.1618

Sheet Revegetate
D1: cottonwood
A2: j4 | B2: j5 | C2: t1 | D2: 0
A3: j4 | B3: j5 | C3: t2 | D3: 0
A4: j4 | B4: j5 | C4: t3 | D4: 0.05
A5: j4 | B5: j5 | C5: t4 | D5: 0.1
A6: j4 | B6: j5 | C6: t5 | D6: 0.5
A7: j4 | B7: j5 | C7: t6 | D7: 0.5
A8: j4 | B8: j5 | C8: t7 | D8: 0.5
A9: j4 | B9: j5 | C9: t8 | D9: 0.04
A10: j4 | B10: j5 | C10: t9 | D10: 0.02
A11: j4 | B11: j5 | C11: t10 | D11: 0
A12: j4 | B12: j5 | C12: t11 | D12: 0
A13: j4 | B13: j5 | C13: t12 | D13: 0
... A241: j1 | B241: j4 | C241: t12 | D241: 0

Sheet NaturalGrowth
D1: cottonwood
A2: j4 | B2: j5 | C2: t1 | D2: 0
A3: j4 | B3: j5 | C3: t2 | D3: 0
A4: j4 | B4: j5 | C4: t3 | D4: 0
A5: j4 | B5: j5 | C5: t4 | D5: 0
A6: j4 | B6: j5 | C6: t5 | D6: 0
A7: j4 | B7: j5 | C7: t6 | D7: 0
A8: j4 | B8: j5 | C8: t7 | D8: 0
A9: j4 | B9: j5 | C9: t8 | D9: 0
A10: j4 | B10: j5 | C10: t9 | D10: 0
A11: j4 | B11: j5 | C11: t10 | D11: 0
A12: j4 | B12: j5 | C12: t11 | D12: 0
A13: j4 | B13: j5 | C13: t12 | D13: 0
... A325: j45 | B325: j32 | C325: t12 | D325: 0

Sheet Cmax
A1: j4 | B1: j5 | C1: =L1/1000000 -> 8.6592 | L1: 8659200
A2: j6 | B2: j5 | C2: =L2/1000000 -> 0.470914 | L2: 470914
A3: j5 | B3: j18 | C3: =L3/1000000 -> 11.079797 | L3: 11079797
A4: j18 | B4: j7 | C4: =L4/1000000 -> 1.049697 | L4: 1049697
A5: j7 | B5: j9 | C5: =L5/1000000 -> 0.683126 | L5: 683126
A6: j9 | B6: j12 | C6: =L6/1000000 -> 4.456809 | L6: 4456809
A7: j12 | B7: j14 | C7: =L7/1000000 -> 1.000458 | L7: 1000458
A8: j14 | B8: j17 | C8: =L8/1000000 -> 1.541125 | L8: 1541125
A9: j17 | B9: j20 | C9: =L9/1000000 -> 5.909368 | L9: 5909368
A10: j19 | B10: j20 | C10: =L10/1000000 -> 0.740186 | L10: 740186
A11: j20 | B11: j21 | C11: =L11/1000000 -> 2.224502 | L11: 2224502
A12: j31 | B12: j30 | C12: =L12/1000000 -> 0.477768 | L12: 477768
... A27: j26 | B27: j25 | C27: =L27/1000000 -> 0.883165 | L27: 883165

Sheet MaxVegCover
D1: cottonwood | M1: Floodplain (m2)
A2: j4 | B2: j5 | C2: t1 | D2: =M2/1000000 -> 8.6592 | M2: 8659200
A3: j4 | B3: j5 | C3: t2 | D3: =M3/1000000 -> 8.6592 | M3: 8659200
A4: j4 | B4: j5 | C4: t3 | D4: =M4/1000000 -> 8.6592 | M4: 8659200
A5: j4 | B5: j5 | C5: t4 | D5: =M5/1000000 -> 8.6592 | M5: 8659200
A6: j4 | B6: j5 | C6: t5 | D6: =M6/1000000 -> 8.6592 | M6: 8659200
A7: j4 | B7: j5 | C7: t6 | D7: =M7/1000000 -> 8.6592 | M7: 8659200
A8: j4 | B8: j5 | C8: t7 | D8: =M8/1000000 -> 8.6592 | M8: 8659200
A9: j4 | B9: j5 | C9: t8 | D9: =M9/1000000 -> 8.6592 | M9: 8659200
A10: j4 | B10: j5 | C10: t9 | D10: =M10/1000000 -> 8.6592 | M10: 8659200
A11: j4 | B11: j5 | C11: t10 | D11: =M11/1000000 -> 8.6592 | M11: 8659200
A12: j4 | B12: j5 | C12: t11 | D12: =M12/1000000 -> 8.6592 | M12: 8659200
A13: j4 | B13: j5 | C13: t12 | D13: =M13/1000000 -> 8.6592 | M13: 8659200
... A325: j26 | B325: j25 | C325: t12 | D325: =M325/1000000 -> 0.883165 | M325: 883165

Sheet SimLinks
A1: j1 | B1: j4 | C1: 1
A2: j6 | B2: j5 | C2: 1
A3: j31 | B3: j30 | C3: 1
A4: j34 | B4: j33 | C4: 1
A5: j19 | B5: j20 | C5: 1
A6: j20 | B6: j21 | C6: 1
A7: j21 | B7: j23 | C7: 1
A8: j32 | B8: j29 | C8: 1
A9: j7 | B9: j9 | C9: 1
A10: j22 | B10: j20 | C10: 1

Sheet Connect_Sim
B1: j1 | C1: j2 | D1: j3 | E1: j4 | F1: j5 | G1: j6 | H1: j7 | I1: j8 | J1: j9 | K1: j12 | L1: j13 | M1: j14 | N1: j15 | O1: j16 | P1: j17 | Q1: j18 | R1: j19 | S1: j20 | T1: j21 | U1: j22 | V1: j23 | W1: j24 | X1: j25 | Y1: j26 | Z1: j27 | AA1: j28 | AB1: j29 | AC1: j30 | AD1: j31 | AE1: j32 | AF1: j33 | AG1: j34 | AH1: j35 | AI1: j36 | AJ1: j37 | AK1: j38 | AL1: j39
A2: j1 | E2: 1
A3: j2 | D3: 1
A4: j3 | Q4: 1
A5: j4 | D5: 1 | F5: 1 | AL5: 1
A6: j5 | Q6: 1
A7: j6
A8: j7 | I8: 1 | J8: 1 | O8: 1
A9: j8 | J9: 1
A10: j9 | K10: 1
A11: j12 | L11: 1 | M11: 1 | N11: 1
A12: j13 | M12: 1
A13: j14
A14: j15 | M14: 1
A15: j16
A16: j17 | O16: 1 | S16: 1
A17: j18 | H17: 1
A18: j19
A19: j20 | T19: 1
A20: j21 | V20: 1
A21: j22 | S21: 1
A22: j23
A23: j24 | H23: 1
A24: j25 | W24: 1
A25: j26
A26: j27 | X26: 1
A27: j28 | W27: 1
A28: j29 | W28: 1 | AA28: 1
A29: j30 | X29: 1 | Z29: 1
A30: j31
A31: j32 | AB31: 1
A32: j33 | AE32: 1 | AK32: 1
A33: j34
A34: j35 | AE34: 1
A35: j36 | H35: 1
A36: j37
A37: j38 | AA37: 1 | AC37: 1
A38: j39 | Q38: 1

Sheet Qmax
C1: t1 | D1: t2 | E1: t3 | F1: t4 | G1: t5 | H1: t6 | I1: t7 | J1: t8 | K1: t9 | L1: t10 | M1: t11 | N1: t12
A2: j37 | B2: j1 | C2: =HeadFlow!B36+capacity!$B$1 -> 21.266482 | D2: =HeadFlow!C36+capacity!$B$1 -> 26.588725 | E2: =HeadFlow!D36+capacity!$B$1 -> 29.659233 | F2: =HeadFlow!E36+capacity!$B$1 -> 27.043714 | G2: =HeadFlow!F36+capacity!$B$1 -> 18.032911 | H2: =HeadFlow!G36+capacity!$B$1 -> 67.227595 | I2: =HeadFlow!H36+capacity!$B$1 -> 76.370406 | J2: =HeadFlow!I36+capacity!$B$1 -> 66.766579 | ... N2: =HeadFlow!M36+capacity!$B$1 -> 21.981016
A3: j1 | B3: j4 | C3: =$C$2 -> 21.266482 | D3: =$D$2 -> 26.588725 | E3: =$E$2 -> 29.659233 | F3: =$F$2 -> 27.043714 | G3: =$G$2 -> 18.032911 | H3: =$H$2 -> 67.227595 | I3: =$I$2 -> 76.370406 | J3: =$J$2 -> 66.766579 | K3: =$K$2 -> 31.87429 | L3: =$L$2 -> 16.034636 | M3: =$M$2 -> 21.262041 | N3: =$N$2 -> 21.981016
A4: j4 | B4: j5 | C4: =$C$2 -> 21.266482 | D4: =$D$2 -> 26.588725 | E4: =$E$2 -> 29.659233 | F4: =$F$2 -> 27.043714 | G4: =$G$2 -> 18.032911 | H4: =$H$2 -> 67.227595 | I4: =$I$2 -> 76.370406 | J4: =$J$2 -> 66.766579 | K4: =$K$2 -> 31.87429 | L4: =$L$2 -> 16.034636 | M4: =$M$2 -> 21.262041 | N4: =$N$2 -> 21.981016
A5: j6 | B5: j5 | C5: =HeadFlow!B7 -> 1.2510288 | D5: =HeadFlow!C7 -> 1.377621 | E5: =HeadFlow!D7 -> 2.3233392 | F5: =HeadFlow!E7 -> 6.0466392 | G5: =HeadFlow!F7 -> 27.098177 | H5: =HeadFlow!G7 -> 31.126788 | I5: =HeadFlow!H7 -> 8.3476386 | J5: =HeadFlow!I7 -> 4.0807368 | ... N5: =HeadFlow!M7 -> 1.2808152
A6: j5 | B6: j18 | C6: =C$2+C$5 -> 22.51751 | D6: =D$2+D$5 -> 27.966346 | E6: =E$2+E$5 -> 31.982572 | F6: =F$2+F$5 -> 33.090353 | G6: =G$2+G$5 -> 45.131088 | H6: =H$2+H$5 -> 98.354383 | I6: =I$2+I$5 -> 84.718044 | J6: =J$2+J$5 -> 70.847316 | ... N6: =N$2+N$5 -> 23.261831
A7: j2 | B7: j3 | C7: =C2 -> 21.266482 | D7: =D2 -> 26.588725 | E7: =E2 -> 29.659233 | F7: =F2 -> 27.043714 | G7: =G2 -> 18.032911 | H7: =H2 -> 67.227595 | I7: =I2 -> 76.370406 | J7: =J2 -> 66.766579 | ... N7: =N2 -> 21.981016
A8: j4 | B8: j3 | C8: =C2 -> 21.266482 | D8: =D2 -> 26.588725 | E8: =E2 -> 29.659233 | F8: =F2 -> 27.043714 | G8: =G2 -> 18.032911 | H8: =H2 -> 67.227595 | I8: =I2 -> 76.370406 | J8: =J2 -> 66.766579 | ... N8: =N2 -> 21.981016
A9: j3 | B9: j18 | C9: =C7 -> 21.266482 | D9: =D7 -> 26.588725 | E9: =E7 -> 29.659233 | F9: =F7 -> 27.043714 | G9: =G7 -> 18.032911 | H9: =H7 -> 67.227595 | I9: =I7 -> 76.370406 | J9: =J7 -> 66.766579 | ... N9: =N7 -> 21.981016
A10: j18 | B10: j7 | C10: =C6 -> 22.51751 | D10: =D6 -> 27.966346 | E10: =E6 -> 31.982572 | F10: =F6 -> 33.090353 | G10: =G6 -> 45.131088 | H10: =H6 -> 98.354383 | I10: =I6 -> 84.718044 | J10: =J6 -> 70.847316 | ... N10: =N6 -> 23.261831
A11: j34 | B11: j33 | C11: =HeadFlow!B33+capacity!$B$5+capacity!$B$4 -> 39.442198 | D11: =HeadFlow!C33+capacity!$B$5+capacity!$B$4 -> 39.794239 | E11: =HeadFlow!D33+capacity!$B$5+capacity!$B$4 -> 41.073421 | F11: =HeadFlow!E33+capacity!$B$5+capacity!$B$4 -> 46.164544 | G11: =HeadFlow!F33+capacity!$B$5+capacity!$B$4 -> 41.505092 | H11: =HeadFlow!G33+capacity!$B$5+capacity!$B$4 -> 40.035243 | I11: =HeadFlow!H33+capacity!$B$5+capacity!$B$4 -> 39.490151 | J11: =HeadFlow!I33+capacity!$B$5+capacity!$B$4 -> 39.399863 | ... N11: =HeadFlow!M33+capacity!$B$5+capacity!$B$4 -> 39.14414
A12: j35 | B12: j40 | C12: =HeadFlow!B34+capacity!$B$5+capacity!$B$4 -> 40.416065 | D12: =HeadFlow!C34+capacity!$B$5+capacity!$B$4 -> 40.499226 | E12: =HeadFlow!D34+capacity!$B$5+capacity!$B$4 -> 42.913655 | F12: =HeadFlow!E34+capacity!$B$5+capacity!$B$4 -> 45.240754 | G12: =HeadFlow!F34+capacity!$B$5+capacity!$B$4 -> 48.055052 | H12: =HeadFlow!G34+capacity!$B$5+capacity!$B$4 -> 44.270303 | I12: =HeadFlow!H34+capacity!$B$5+capacity!$B$4 -> 41.036436 | J12: =HeadFlow!I34+capacity!$B$5+capacity!$B$4 -> 40.857237 | ... N12: =HeadFlow!M34+capacity!$B$5+capacity!$B$4 -> 40.251498
A13: j33 | B13: j43 | C13: =C$11 -> 39.442198 | D13: =D$12 -> 40.499226 | E13: =E$12 -> 42.913655 | F13: =F$12 -> 45.240754 | G13: =G$12 -> 48.055052 | H13: =H$12 -> 44.270303 | I13: =I$12 -> 41.036436 | J13: =J$12 -> 40.857237 | K13: =K$12 -> 40.714269 | ... N13: =N$12 -> 40.251498
A14: j32 | B14: j29 | C14: =HeadFlow!B33+capacity!$B$5+capacity!$B$4+HeadFlow!B34 -> 40.776683 | D14: =HeadFlow!C33+capacity!$B$5+capacity!$B$4+HeadFlow!C34 -> 41.211885 | E14: =HeadFlow!D33+capacity!$B$5+capacity!$B$4+HeadFlow!D34 -> 44.905496 | F14: =HeadFlow!E33+capacity!$B$5+capacity!$B$4+HeadFlow!E34 -> 52.323717 | G14: =HeadFlow!F33+capacity!$B$5+capacity!$B$4+HeadFlow!F34 -> 50.478563 | H14: =HeadFlow!G33+capacity!$B$5+capacity!$B$4+HeadFlow!G34 -> 45.223966 | I14: =HeadFlow!H33+capacity!$B$5+capacity!$B$4+HeadFlow!H34 -> 41.445006 | J14: =HeadFlow!I33+capacity!$B$5+capacity!$B$4+HeadFlow!I34 -> 41.175519 | ... N14: =HeadFlow!M33+capacity!$B$5+capacity!$B$4+HeadFlow!M34 -> 40.314058
A15: j29 | B15: j28 | C15: =C$14 -> 40.776683 | D15: =D$14 -> 41.211885 | E15: =E$14 -> 44.905496 | F15: =F$14 -> 52.323717 | G15: =G$14 -> 50.478563 | H15: =H$14 -> 45.223966 | I15: =I$14 -> 41.445006 | J15: =J$14 -> 41.175519 | ... N15: =N$14 -> 40.314058
A16: j29 | B16: j24 | C16: =C$14 -> 40.776683 | D16: =D$14 -> 41.211885 | E16: =E$14 -> 44.905496 | F16: =F$14 -> 52.323717 | G16: =G$14 -> 50.478563 | H16: =H$14 -> 45.223966 | I16: =I$14 -> 41.445006 | J16: =J$14 -> 41.175519 | ... N16: =N$14 -> 40.314058
A17: j28 | B17: j24 | C17: =C$14 -> 40.776683 | D17: =D$14 -> 41.211885 | E17: =E$14 -> 44.905496 | F17: =F$14 -> 52.323717 | G17: =G$14 -> 50.478563 | H17: =H$14 -> 45.223966 | I17: =I$14 -> 41.445006 | J17: =J$14 -> 41.175519 | ... N17: =N$14 -> 40.314058
A18: j24 | B18: j7 | C18: =C$24+C$23+capacity!$B$2+C16 -> 82.387312 | D18: =D$24+D$23+capacity!$B$2+D16 -> 83.85993 | E18: =E$24+E$23+capacity!$B$2+E16 -> 90.531717 | F18: =F$24+F$23+capacity!$B$2+F16 -> 100.63001 | G18: =G$24+G$23+capacity!$B$2+G16 -> 100.38777 | H18: =H$24+H$23+capacity!$B$2+H16 -> 91.389707 | I18: =I$24+I$23+capacity!$B$2+I16 -> 85.087797 | J18: =J$24+J$23+capacity!$B$2+J16 -> 84.560512 | ... N18: =N$24+N$23+capacity!$B$2+N16 -> 83.07672
A19: j31 | B19: j30 | C19: =HeadFlow!B30 -> 2.1684303 | D19: =HeadFlow!C30 -> 2.1488195 | E19: =HeadFlow!D30 -> 2.7125664 | F19: =HeadFlow!E30 -> 3.0655383 | G19: =HeadFlow!F30 -> 1.8541562 | H19: =HeadFlow!G30 -> 1.8954377 | I19: =HeadFlow!H30 -> 2.6063551 | J19: =HeadFlow!I30 -> 2.5277563 | ... N19: =HeadFlow!M30 -> 2.5111646
A20: j30 | B20: j27 | C20: =C19+C11 -> 41.610629 | D20: =D19+D12 -> 42.648045 | E20: =E19+E12 -> 45.626221 | F20: =F19+F12 -> 48.306292 | G20: =G19+G12 -> 49.909208 | H20: =H19+H12 -> 46.165741 | I20: =I19+I12 -> 43.642791 | J20: =J19+J12 -> 43.384993 | K20: =K19+K12 -> 43.491975 | ... N20: =N19+N12 -> 42.762662
A21: j27 | B21: j25 | C21: =C20 -> 41.610629 | D21: =D20 -> 42.648045 | E21: =E20 -> 45.626221 | F21: =F20 -> 48.306292 | G21: =G20 -> 49.909208 | H21: =H20 -> 46.165741 | I21: =I20 -> 43.642791 | J21: =J20 -> 43.384993 | ... N21: =N20 -> 42.762662
A22: j30 | B22: j25 | C22: =C20 -> 41.610629 | D22: =D20 -> 42.648045 | E22: =E20 -> 45.626221 | F22: =F20 -> 48.306292 | G22: =G20 -> 49.909208 | H22: =H20 -> 46.165741 | I22: =I20 -> 43.642791 | J22: =J20 -> 43.384993 | ... N22: =N20 -> 42.762662
A23: j26 | B23: j25 | C23: =HeadFlow!B25 -> 0 | D23: =HeadFlow!C25 -> 0 | E23: =HeadFlow!D25 -> 0 | F23: =HeadFlow!E25 -> 0 | G23: =HeadFlow!F25 -> 0 | H23: =HeadFlow!G25 -> 0 | I23: =HeadFlow!H25 -> 0 | J23: =HeadFlow!I25 -> 0 | ... N23: =HeadFlow!M25 -> 0
A24: j25 | B24: j24 | C24: =C$20+C$23 -> 41.610629 | D24: =D$20+D$23 -> 42.648045 | E24: =E$20+E$23 -> 45.626221 | F24: =F$20+F$23 -> 48.306292 | G24: =G$20+G$23 -> 49.909208 | H24: =H$20+H$23 -> 46.165741 | I24: =I$20+I$23 -> 43.642791 | J24: =J$20+J$23 -> 43.384993 | ... N24: =N$20+N$23 -> 42.762662
A25: j7 | B25: j8 | C25: =C18+C10+C44 -> 157.49408 | D25: =D18+D10+D44 -> 153.55028 | E25: =E18+E10+E44 -> 179.36215 | F25: =F18+F10+F44 -> 188.98837 | G25: =G18+G10+G44 -> 173.6835 | H25: =H18+H10+H44 -> 189.74409 | I25: =I18+I10+I44 -> 169.80584 | J25: =J18+J10+J44 -> 155.40783 | ... N25: =N18+N10+N44 -> 134.12621
A26: j7 | B26: j9 | C26: =C$25 -> 157.49408 | D26: =D$25 -> 153.55028 | E26: =E$25 -> 179.36215 | F26: =F$25 -> 188.98837 | G26: =G$25 -> 173.6835 | H26: =H$25 -> 189.74409 | I26: =I$25 -> 169.80584 | J26: =J$25 -> 155.40783 | ... N26: =N$25 -> 134.12621
A27: j8 | B27: j9 | C27: =C$25 -> 157.49408 | D27: =D$25 -> 153.55028 | E27: =E$25 -> 179.36215 | F27: =F$25 -> 188.98837 | G27: =G$25 -> 173.6835 | H27: =H$25 -> 189.74409 | I27: =I$25 -> 169.80584 | J27: =J$25 -> 155.40783 | ... N27: =N$25 -> 134.12621
A28: j9 | B28: j12 | C28: =C$25 -> 157.49408 | D28: =D$25 -> 153.55028 | E28: =E$25 -> 179.36215 | F28: =F$25 -> 188.98837 | G28: =G$25 -> 173.6835 | H28: =H$25 -> 189.74409 | I28: =I$25 -> 169.80584 | J28: =J$25 -> 155.40783 | ... N28: =N$25 -> 134.12621
A29: j12 | B29: j13 | C29: =C$25 -> 157.49408 | D29: =D$25 -> 153.55028 | E29: =E$25 -> 179.36215 | F29: =F$25 -> 188.98837 | G29: =G$25 -> 173.6835 | H29: =H$25 -> 189.74409 | I29: =I$25 -> 169.80584 | J29: =J$25 -> 155.40783 | ... N29: =N$25 -> 134.12621
A30: j13 | B30: j14 | C30: =C$25 -> 157.49408 | D30: =D$25 -> 153.55028 | E30: =E$25 -> 179.36215 | F30: =F$25 -> 188.98837 | G30: =G$25 -> 173.6835 | H30: =H$25 -> 189.74409 | I30: =I$25 -> 169.80584 | J30: =J$25 -> 155.40783 | ... N30: =N$25 -> 134.12621
A31: j12 | B31: j14 | C31: =C$25 -> 157.49408 | D31: =D$25 -> 153.55028 | E31: =E$25 -> 179.36215 | F31: =F$25 -> 188.98837 | G31: =G$25 -> 173.6835 | H31: =H$25 -> 189.74409 | I31: =I$25 -> 169.80584 | J31: =J$25 -> 155.40783 | ... N31: =N$25 -> 134.12621
A32: j15 | B32: j14 | C32: =C$25 -> 157.49408 | D32: =D$25 -> 153.55028 | E32: =E$25 -> 179.36215 | F32: =F$25 -> 188.98837 | G32: =G$25 -> 173.6835 | H32: =H$25 -> 189.74409 | I32: =I$25 -> 169.80584 | J32: =J$25 -> 155.40783 | ... N32: =N$25 -> 134.12621
A33: j14 | B33: j17 | C33: =C$25 -> 157.49408 | D33: =D$25 -> 153.55028 | E33: =E$25 -> 179.36215 | F33: =F$25 -> 188.98837 | G33: =G$25 -> 173.6835 | H33: =H$25 -> 189.74409 | I33: =I$25 -> 169.80584 | J33: =J$25 -> 155.40783 | ... N33: =N$25 -> 134.12621
A34: j17 | B34: j20 | C34: =C$25 -> 157.49408 | D34: =D$25 -> 153.55028 | E34: =E$25 -> 179.36215 | F34: =F$25 -> 188.98837 | G34: =G$25 -> 173.6835 | H34: =H$25 -> 189.74409 | I34: =I$25 -> 169.80584 | J34: =J$25 -> 155.40783 | ... N34: =N$25 -> 134.12621
A35: j19 | B35: j20 | C35: =HeadFlow!B18 -> 6.7317368 | D35: =HeadFlow!C18 -> 3.2839557 | E35: =HeadFlow!D18 -> 13.925164 | F35: =HeadFlow!E18 -> 31.581079 | G35: =HeadFlow!F18 -> 47.032798 | H35: =HeadFlow!G18 -> 37.955379 | I35: =HeadFlow!H18 -> 24.298293 | J35: =HeadFlow!I18 -> 15.436826 | ... N35: =HeadFlow!M18 -> 1.2286909
A36: j22 | B36: j20 | C36: =HeadFlow!B21 -> 9.0319571 | D36: =HeadFlow!C21 -> 6.2126171 | E36: =HeadFlow!D21 -> 5.916466 | F36: =HeadFlow!E21 -> 5.294486 | G36: =HeadFlow!F21 -> 6.8148416 | H36: =HeadFlow!G21 -> 8.697664 | I36: =HeadFlow!H21 -> 6.1230754 | J36: =HeadFlow!I21 -> 4.9483324 | ... N36: =HeadFlow!M21 -> 5.5292852
A37: j20 | B37: j21 | C37: =C$34+C$35+C36 -> 173.25778 | D37: =D$34+D$35+D36 -> 163.04685 | E37: =E$34+E$35+E36 -> 199.20378 | F37: =F$34+F$35+F36 -> 225.86393 | G37: =G$34+G$35+G36 -> 227.53114 | H37: =H$34+H$35+H36 -> 236.39713 | I37: =I$34+I$35+I36 -> 200.22721 | J37: =J$34+J$35+J36 -> 175.79299 | ... N37: =N$34+N$35+N36 -> 140.88418
A38: j21 | B38: j23 | C38: =C37+C36 -> 182.28973 | D38: =D37+D36 -> 169.25947 | E38: =E37+E36 -> 205.12025 | F38: =F37+F36 -> 231.15842 | G38: =G37+G36 -> 234.34598 | H38: =H37+H36 -> 245.0948 | I38: =I37+I36 -> 206.35029 | J38: =J37+J36 -> 180.74132 | ... N38: =N37+N36 -> 146.41347
A39: j7 | B39: j16 | C39: =C10+C18+C44 -> 157.49408 | D39: =D10+D18+D44 -> 153.55028 | E39: =E10+E18+E44 -> 179.36215 | F39: =F10+F18+F44 -> 188.98837 | G39: =G10+G18+G44 -> 173.6835 | H39: =H10+H18+H44 -> 189.74409 | I39: =I10+I18+I44 -> 169.80584 | J39: =J10+J18+J44 -> 155.40783 | ... N39: =N10+N18+N44 -> 134.12621
A40: j33 | B40: j38 | C40: =C11 -> 39.442198 | D40: =D11 -> 39.794239 | E40: =E11 -> 41.073421 | F40: =F11 -> 46.164544 | G40: =G11 -> 41.505092 | H40: =H11 -> 40.035243 | I40: =I11 -> 39.490151 | J40: =J11 -> 39.399863 | ... N40: =N11 -> 39.14414
A41: j38 | B41: j30 | C41: =C40 -> 39.442198 | D41: =D40 -> 39.794239 | E41: =E40 -> 41.073421 | F41: =F40 -> 46.164544 | G41: =G40 -> 41.505092 | H41: =H40 -> 40.035243 | I41: =I40 -> 39.490151 | J41: =J40 -> 39.399863 | ... N41: =N40 -> 39.14414
A42: j4 | B42: j39 | C42: =C2 -> 21.266482 | D42: =D2 -> 26.588725 | E42: =E2 -> 29.659233 | F42: =F2 -> 27.043714 | G42: =G2 -> 18.032911 | H42: =H2 -> 67.227595 | I42: =I2 -> 76.370406 | J42: =J2 -> 66.766579 | ... N42: =N2 -> 21.981016
A43: j39 | B43: j18 | C43: =C42 -> 21.266482 | D43: =D42 -> 26.588725 | E43: =E42 -> 29.659233 | F43: =F42 -> 27.043714 | G43: =G42 -> 18.032911 | H43: =H42 -> 67.227595 | I43: =I42 -> 76.370406 | J43: =J42 -> 66.766579 | ... N43: =N42 -> 21.981016
A44: j36 | B44: j7 | C44: =HeadFlow!B35 -> 52.58926 | D44: =HeadFlow!C35 -> 41.724003 | E44: =HeadFlow!D35 -> 56.84786 | F44: =HeadFlow!E35 -> 55.268006 | G44: =HeadFlow!F35 -> 28.16464 | H44: =HeadFlow!G35 -> 0 | I44: =HeadFlow!H35 -> 0 | J44: =HeadFlow!I35 -> 0 | ... N44: =HeadFlow!M35 -> 27.787655
A45: j40 | B45: j32 | C45: =C12 -> 40.416065 | D45: =D12 -> 40.499226 | E45: =E12 -> 42.913655 | F45: =F12 -> 45.240754 | G45: =G12 -> 48.055052 | H45: =H12 -> 44.270303 | I45: =I12 -> 41.036436 | J45: =J12 -> 40.857237 | ... N45: =N12 -> 40.251498
A46: j17 | B46: j16 | C46: =C33 -> 157.49408 | D46: =D33 -> 153.55028 | E46: =E33 -> 179.36215 | F46: =F33 -> 188.98837 | G46: =G33 -> 173.6835 | H46: =H33 -> 189.74409 | I46: =I33 -> 169.80584 | J46: =J33 -> 155.40783 | ... N46: =N33 -> 134.12621
A47: j43 | B47: j45 | C47: =C11 -> 39.442198 | D47: =D11 -> 39.794239 | E47: =E11 -> 41.073421 | F47: =F11 -> 46.164544 | G47: =G11 -> 41.505092 | H47: =H11 -> 40.035243 | I47: =I11 -> 39.490151 | J47: =J11 -> 39.399863 | ... N47: =N11 -> 39.14414
A48: j40 | B48: j45 | C48: =C12 -> 40.416065 | D48: =D12 -> 40.499226 | E48: =E12 -> 42.913655 | F48: =F12 -> 45.240754 | G48: =G12 -> 48.055052 | H48: =H12 -> 44.270303 | I48: =I12 -> 41.036436 | J48: =J12 -> 40.857237 | ... N48: =N12 -> 40.251498
A49: j43 | B49: j41 | C49: =C11 -> 39.442198 | D49: =D11 -> 39.794239 | E49: =E11 -> 41.073421 | F49: =F11 -> 46.164544 | G49: =G11 -> 41.505092 | H49: =H11 -> 40.035243 | I49: =I11 -> 39.490151 | J49: =J11 -> 39.399863 | ... N49: =N11 -> 39.14414
A50: j41 | B50: j29 | C50: =C11 -> 39.442198 | D50: =D11 -> 39.794239 | E50: =E11 -> 41.073421 | F50: =F11 -> 46.164544 | G50: =G11 -> 41.505092 | H50: =H11 -> 40.035243 | I50: =I11 -> 39.490151 | J50: =J11 -> 39.399863 | ... N50: =N11 -> 39.14414
A51: j42 | B51: j29 | C51: =C11 -> 39.442198 | D51: =D11 -> 39.794239 | E51: =E11 -> 41.073421 | F51: =F11 -> 46.164544 | G51: =G11 -> 41.505092 | H51: =H11 -> 40.035243 | I51: =I11 -> 39.490151 | J51: =J11 -> 39.399863 | ... N51: =N11 -> 39.14414
A52: j29 | B52: j44 | C52: =C14 -> 40.776683 | D52: =D14 -> 41.211885 | E52: =E14 -> 44.905496 | F52: =F14 -> 52.323717 | G52: =G14 -> 50.478563 | H52: =H14 -> 45.223966 | I52: =I14 -> 41.445006 | J52: =J14 -> 41.175519 | ... N52: =N14 -> 40.314058
A53: j44 | B53: j24 | C53: =C12 -> 40.416065 | D53: =D12 -> 40.499226 | E53: =E12 -> 42.913655 | F53: =F12 -> 45.240754 | G53: =G12 -> 48.055052 | H53: =H12 -> 44.270303 | I53: =I12 -> 41.036436 | J53: =J12 -> 40.857237 | ... N53: =N12 -> 40.251498
A54: j12 | B54: j15 | C54: =C28 -> 157.49408 | D54: =D28 -> 153.55028 | E54: =E28 -> 179.36215 | F54: =F28 -> 188.98837 | G54: =G28 -> 173.6835 | H54: =H28 -> 189.74409 | I54: =I28 -> 169.80584 | J54: =J28 -> 155.40783 | ... N54: =N28 -> 134.12621
A55: j29 | B55: j27 | C55: =C15 -> 40.776683 | D55: =D15 -> 41.211885 | E55: =E15 -> 44.905496 | F55: =F15 -> 52.323717 | G55: =G15 -> 50.478563 | H55: =H15 -> 45.223966 | I55: =I15 -> 41.445006 | J55: =J15 -> 41.175519 | ... N55: =N15 -> 40.314058
A56: j45 | B56: j32 | C56: =C47+C48 -> 79.858263 | D56: =D47+D48 -> 80.293465 | E56: =E47+E48 -> 83.987076 | F56: =F47+F48 -> 91.405297 | G56: =G47+G48 -> 89.560143 | H56: =H47+H48 -> 84.305546 | I56: =I47+I48 -> 80.526586 | J56: =J47+J48 -> 80.257099 | ... N56: =N47+N48 -> 79.395638
A57: j45 | B57: j42 | C57: =C56 -> 79.858263 | D57: =D56 -> 80.293465 | E57: =E56 -> 83.987076 | F57: =F56 -> 91.405297 | G57: =G56 -> 89.560143 | H57: =H56 -> 84.305546 | I57: =I56 -> 80.526586 | J57: =J56 -> 80.257099 | ... N57: =N56 -> 79.395638

Sheet Qmin
C1: t1 | D1: t2 | E1: t3 | F1: t4 | G1: t5 | H1: t6 | I1: t7 | J1: t8 | K1: t9 | L1: t10 | M1: t11 | N1: t12
A2: j37 | B2: j1 | C2: 2 | D2: 2 | E2: 2 | F2: 2 | G2: 2 | H2: 2 | I2: 2 | J2: 2 | K2: 2 | L2: 2 | M2: 2 | N2: 2
A3: j1 | B3: j4 | C3: 2 | D3: 2 | E3: 2 | F3: 2 | G3: 2 | H3: 2 | I3: 2 | J3: 2 | K3: 2 | L3: 2 | M3: 2 | N3: 2
A4: j4 | B4: j5 | C4: 2 | D4: 2 | E4: 2 | F4: 2 | G4: 2 | H4: 2 | I4: 2 | J4: 2 | K4: 2 | L4: 2 | M4: 2 | N4: 2
A5: j6 | B5: j5 | C5: 2 | D5: 2 | E5: 2 | F5: 2 | G5: 2 | H5: 2 | I5: 2 | J5: 2 | K5: 2 | L5: 2 | M5: 2 | N5: 2
A6: j5 | B6: j18 | C6: 2 | D6: 2 | E6: 2 | F6: 2 | G6: 2 | H6: 2 | I6: 2 | J6: 2 | K6: 2 | L6: 2 | M6: 2 | N6: 2
A7: j2 | B7: j3 | C7: 2 | D7: 2 | E7: 2 | F7: 2 | G7: 2 | H7: 2 | I7: 2 | J7: 2 | K7: 2 | L7: 2 | M7: 2 | N7: 2
A8: j4 | B8: j3 | C8: 2 | D8: 2 | E8: 2 | F8: 2 | G8: 2 | H8: 2 | I8: 2 | J8: 2 | K8: 2 | L8: 2 | M8: 2 | N8: 2
A9: j3 | B9: j18 | C9: 2 | D9: 2 | E9: 2 | F9: 2 | G9: 2 | H9: 2 | I9: 2 | J9: 2 | K9: 2 | L9: 2 | M9: 2 | N9: 2
A10: j18 | B10: j7 | C10: 2 | D10: 2 | E10: 2 | F10: 2 | G10: 2 | H10: 2 | I10: 2 | J10: 2 | K10: 2 | L10: 2 | M10: 2 | N10: 2
A11: j34 | B11: j33 | C11: 2 | D11: 2 | E11: 2 | F11: 2 | G11: 2 | H11: 2 | I11: 2 | J11: 2 | K11: 2 | L11: 2 | M11: 2 | N11: 2
A12: j35 | B12: j32 | C12: 2 | D12: 2 | E12: 2 | F12: 2 | G12: 2 | H12: 2 | I12: 2 | J12: 2 | K12: 2 | L12: 2 | M12: 2 | N12: 2
A13: j33 | B13: j32 | C13: 2 | D13: 2 | E13: 2 | F13: 2 | G13: 2 | H13: 2 | I13: 2 | J13: 2 | K13: 2 | L13: 2 | M13: 2 | N13: 2
... A44: j39 | B44: j18 | C44: 2 | D44: 2 | E44: 2 | F44: 2 | G44: 2 | H44: 2 | I44: 2 | J44: 2 | K44: 2 | L44: 2 | M44: 2 | N44: 2

Sheet QSim
C1: t1 | D1: t2 | E1: t3 | F1: t4 | G1: t5 | H1: t6 | I1: t7 | J1: t8 | K1: t9 | L1: t10 | M1: t11 | N1: t12
A2: j1 | B2: j4 | C2: =HeadFlow!B36 -> 21.266482 | D2: =HeadFlow!C36 -> 26.588725 | E2: =HeadFlow!D36 -> 29.659233 | F2: =HeadFlow!E36 -> 27.043714 | G2: =HeadFlow!F36 -> 18.032911 | H2: =HeadFlow!G36 -> 67.227595 | I2: =HeadFlow!H36 -> 76.370406 | J2: =HeadFlow!I36 -> 66.766579 | ... N2: =HeadFlow!M36 -> 21.981016 | W2: Stateline
A3: j6 | B3: j5 | C3: =HeadFlow!B7 -> 1.2510288 | D3: =HeadFlow!C7 -> 1.377621 | E3: =HeadFlow!D7 -> 2.3233392 | F3: =HeadFlow!E7 -> 6.0466392 | G3: =HeadFlow!F7 -> 27.098177 | H3: =HeadFlow!G7 -> 31.126788 | I3: =HeadFlow!H7 -> 8.3476386 | J3: =HeadFlow!I7 -> 4.0807368 | ... N3: =HeadFlow!M7 -> 1.2808152 | W3: Cub
A4: j31 | B4: j30 | C4: =HeadFlow!B30 -> 2.1684303 | D4: =HeadFlow!C30 -> 2.1488195 | E4: =HeadFlow!D30 -> 2.7125664 | F4: =HeadFlow!E30 -> 3.0655383 | G4: =HeadFlow!F30 -> 1.8541562 | H4: =HeadFlow!G30 -> 1.8954377 | I4: =HeadFlow!H30 -> 2.6063551 | J4: =HeadFlow!I30 -> 2.5277563 | ... N4: =HeadFlow!M30 -> 2.5111646 | W4: BLKsmith
A5: j34 | B5: j33 | C5: =HeadFlow!B33 -> 0.36061829 | D5: =HeadFlow!C33 -> 0.71265887 | E5: =HeadFlow!D33 -> 1.991841 | F5: =HeadFlow!E33 -> 7.0829635 | G5: =HeadFlow!F33 -> 2.4235117 | H5: =HeadFlow!G33 -> 0.95366271 | I5: =HeadFlow!H33 -> 0.40857075 | J5: =HeadFlow!I33 -> 0.31828259 | ... N5: =HeadFlow!M33 -> 0.062560207 | W5: East Fork
A6: j19 | B6: j20 | C6: =HeadFlow!B18 -> 6.7317368 | D6: =HeadFlow!C18 -> 3.2839557 | E6: =HeadFlow!D18 -> 13.925164 | F6: =HeadFlow!E18 -> 31.581079 | G6: =HeadFlow!F18 -> 47.032798 | H6: =HeadFlow!G18 -> 37.955379 | I6: =HeadFlow!H18 -> 24.298293 | J6: =HeadFlow!I18 -> 15.436826 | ... N6: =HeadFlow!M18 -> 1.2286909 | W6: Malad
A7: j20 | B7: j21 | C7: =RiversHeadFlow!B10*74466.1151309/1000000 -> 97.997408 | D7: =RiversHeadFlow!C10*74466.1151309/1000000 -> 95.912356 | E7: =RiversHeadFlow!D10*74466.1151309/1000000 -> 180.05907 | F7: =RiversHeadFlow!E10*74466.1151309/1000000 -> 288.48173 | G7: =RiversHeadFlow!F10*74466.1151309/1000000 -> 395.564 | H7: =RiversHeadFlow!G10*74466.1151309/1000000 -> 407.25518 | I7: =RiversHeadFlow!H10*74466.1151309/1000000 -> 183.18664 | J7: =RiversHeadFlow!I10*74466.1151309/1000000 -> 101.79518 | ... N7: =RiversHeadFlow!M10*74466.1151309/1000000 -> 129.42211 | W7: Corinne
A8: j21 | B8: j23 | C8: =C7 -> 97.997408 | D8: =D7 -> 95.912356 | E8: =E7 -> 180.05907 | F8: =F7 -> 288.48173 | G8: =G7 -> 395.564 | H8: =H7 -> 407.25518 | I8: =I7 -> 183.18664 | J8: =J7 -> 101.79518 | ... N8: =N7 -> 129.42211 | W8: Conrinne
A9: j32 | B9: j29 | C9: =RiversHeadFlow!B11*74466.1151309/1000000 -> 2.9190717 | D9: =RiversHeadFlow!C11*74466.1151309/1000000 -> 2.5765276 | E9: =RiversHeadFlow!D11*74466.1151309/1000000 -> 6.1657943 | F9: =RiversHeadFlow!E11*74466.1151309/1000000 -> 27.358851 | G9: =RiversHeadFlow!F11*74466.1151309/1000000 -> 36.786261 | H9: =RiversHeadFlow!G11*74466.1151309/1000000 -> 15.109175 | I9: =RiversHeadFlow!H11*74466.1151309/1000000 -> 3.0084311 | J9: =RiversHeadFlow!I11*74466.1151309/1000000 -> 2.4052555 | ... N9: =RiversHeadFlow!M11*74466.1151309/1000000 -> 4.5945593 | W9: Paradise
A10: j7 | B10: j9 | C10: =RiversHeadFlow!B12*74466.1151309/1000000 -> 83.625447 | D10: =RiversHeadFlow!C12*74466.1151309/1000000 -> 76.253302 | E10: =RiversHeadFlow!D12*74466.1151309/1000000 -> 161.88933 | F10: =RiversHeadFlow!E12*74466.1151309/1000000 -> 233.00447 | G10: =RiversHeadFlow!F12*74466.1151309/1000000 -> 387.59613 | H10: =RiversHeadFlow!G12*74466.1151309/1000000 -> 224.5898 | I10: =RiversHeadFlow!H12*74466.1151309/1000000 -> 9.4348568 | J10: =RiversHeadFlow!I12*74466.1151309/1000000 -> 6.9253487 | ... N10: =RiversHeadFlow!M12*74466.1151309/1000000 -> 90.327398 | W10: Cutler
A11: j22 | B11: j20 | C11: =HeadFlow!B21 -> 9.0319571 | D11: =HeadFlow!C21 -> 6.2126171 | E11: =HeadFlow!D21 -> 5.916466 | F11: =HeadFlow!E21 -> 5.294486 | G11: =HeadFlow!F21 -> 6.8148416 | H11: =HeadFlow!G21 -> 8.697664 | I11: =HeadFlow!H21 -> 6.1230754 | J11: =HeadFlow!I21 -> 4.9483324 | ... N11: =HeadFlow!M21 -> 5.5292852 | W11: Malad Gain

Sheet QSimulation_NHD
C1: t1 | D1: t2 | E1: t3 | F1: t4 | G1: t5 | H1: t6 | I1: t7 | J1: t8 | K1: t9 | L1: t10 | M1: t11 | N1: t12
A2: j4 | B2: j5 | C2: 59.571861 | D2: 59.758648 | E2: 71.466127 | F2: 78.49401 | G2: 79.653382 | H2: 70.096154 | I2: 54.426046 | J2: 51.68913 | K2: 53.058024 | L2: 53.315874 | M2: 58.164489 | N2: 58.828337 | U2: L3
A3: j6 | B3: j5 | C3: 1.0624825 | D3: 1.1207895 | E3: 2.8535167 | F3: 9.8581718 | G3: 21.839025 | H3: 22.837864 | I3: 4.5922757 | J3: 1.6142268 | K3: 1.5640863 | L3: 1.7827684 | M3: 1.4868897 | N3: 1.1362785 | U3: L4
A4: j5 | B4: j18 | C4: 72.00362 | D4: 69.97476 | E4: 88.155624 | F4: 99.67395 | G4: 116.77245 | H4: 99.212806 | I4: 62.752775 | J4: 55.943544 | K4: 59.307712 | L4: 58.408521 | M4: 60.809675 | N4: 65.070769 | U4: L5
A5: j18 | B5: j7 | C5: 89.363346 | D5: 85.831499 | E5: 109.6277 | F5: 117.12441 | G5: 139.58801 | H5: 115.6074 | I5: 72.752758 | J5: 64.747387 | K5: 69.408925 | L5: 67.578257 | M5: 70.054512 | N5: 77.680167 | U5: L7
A6: j7 | B6: j9 | C6: 106.12077 | D6: 103.99807 | E6: 161.11043 | F6: 189.75792 | G6: 226.69155 | H6: 166.44959 | I6: 89.952699 | J6: 92.722973 | K6: 98.878163 | L6: 100.7985 | M6: 94.514776 | N6: 104.0592 | U6: L8
A7: j9 | B7: j12 | C7: 66.876975 | D7: 67.440952 | E7: 104.83572 | F7: 125.29952 | G7: 146.2759 | H7: 106.26451 | I7: 52.293308 | J7: 53.56889 | K7: 60.057748 | L7: 64.729105 | M7: 62.321995 | N7: 66.932296 | U7: L9
A8: j12 | B8: j14 | C8: 121.35397 | D8: 135.70407 | E8: 178.50485 | F8: 202.9845 | G8: 204.55306 | H8: 153.37681 | I8: 49.70401 | J8: 37.512827 | K8: 68.8176 | L8: 100.42314 | M8: 122.09609 | N8: 119.46979 | U8: L11
A9: j14 | B9: j17 | C9: 121.35609 | D9: 135.7063 | E9: 178.52223 | F9: 202.99389 | G9: 204.54137 | H9: 153.37823 | I9: 49.486084 | J9: 37.344906 | K9: 68.776532 | L9: 100.43848 | M9: 122.10499 | N9: 119.4715 | U9: L12
A10: j17 | B10: j20 | C10: 121.36075 | D10: 135.71138 | E10: 178.56061 | F10: 203.01773 | G10: 204.51101 | H10: 153.38177 | I10: 48.993657 | J10: 36.956536 | K10: 68.683541 | L10: 100.47249 | M10: 122.12472 | N10: 119.47522 | U10: L13
A11: j19 | B11: j20 | C11: 6.349333 | D11: 7.2364997 | E11: 10.612317 | F11: 16.660342 | G11: 7.0564926 | H11: 3.884895 | I11: 1.7267902 | J11: 1.7693059 | K11: 2.0159873 | L11: 3.3637066 | M11: 4.5442789 | N11: 4.6877728 | U11: L14
A12: j20 | B12: j21 | C12: 140.80187 | D12: 144.853 | E12: 198.3331 | F12: 235.87164 | G12: 261.361 | H12: 207.74726 | I12: 70.033296 | J12: 54.391614 | K12: 85.195317 | L12: 115.01396 | M12: 133.33064 | N12: 131.28197 | U12: L16
A13: j21 | B13: j23 | C13: 140.80187 | D13: 144.85618 | E13: 198.36529 | F13: 235.88155 | G13: 261.2704 | H13: 207.76642 | I13: 69.391696 | J13: 53.890606 | K13: 85.071058 | L13: 115.05231 | M13: 133.34982 | N13: 131.28197 | U13: L17
... A24: j24 | B24: j7 | C24: 13.85484 | D24: 14.534734 | E24: 19.396678 | F24: 56.009935 | G24: 68.853827 | H24: 40.870225 | I24: 14.962574 | J24: 5.2091188 | K24: 23.282147 | L24: 25.711958 | M24: 12.810019 | N24: 11.809744 | U24: L28

Sheet HeadFlow
B1: t1 | C1: t2 | D1: t3 | E1: t4 | F1: t5 | G1: t6 | H1: t7 | I1: t8 | J1: t9 | K1: t10 | L1: t11 | M1: t12
A2: j1 | B2: 0 | C2: 0 | D2: 0 | E2: 0 | F2: 0 | G2: 0 | H2: 0 | I2: 0 | J2: 0 | K2: 0 | L2: 0 | M2: 0
A3: j2 | B3: 0 | C3: 0 | D3: 0 | E3: 0 | F3: 0 | G3: 0 | H3: 0 | I3: 0 | J3: 0 | K3: 0 | L3: 0 | M3: 0
A4: j3 | B4: 0 | C4: 0 | D4: 0 | E4: 0 | F4: 0 | G4: 0 | H4: 0 | I4: 0 | J4: 0 | K4: 0 | L4: 0 | M4: 0
A5: j4 | B5: 0 | C5: 0 | D5: 0 | E5: 0 | F5: 0 | G5: 0 | H5: 0 | I5: 0 | J5: 0 | K5: 0 | L5: 0 | M5: 0
A6: j5 | B6: 0 | C6: 0 | D6: 0 | E6: 0 | F6: 0 | G6: 0 | H6: 0 | I6: 0 | J6: 0 | K6: 0 | L6: 0 | M6: 0
A7: j6 | B7: =RiversHeadFlow!B6*0.074466 -> 1.2510288 | C7: =RiversHeadFlow!C6*0.074466 -> 1.377621 | D7: =RiversHeadFlow!D6*0.074466 -> 2.3233392 | E7: =RiversHeadFlow!E6*0.074466 -> 6.0466392 | F7: =RiversHeadFlow!F6*0.074466 -> 27.098177 | G7: =RiversHeadFlow!G6*0.074466 -> 31.126788 | H7: =RiversHeadFlow!H6*0.074466 -> 8.3476386 | I7: =RiversHeadFlow!I6*0.074466 -> 4.0807368 | ... M7: =RiversHeadFlow!M6*0.074466 -> 1.2808152
A8: j7 | B8: 0 | C8: 0 | D8: 0 | E8: 0 | F8: 0 | G8: 0 | H8: 0 | I8: 0 | J8: 0 | K8: 0 | L8: 0 | M8: 0
A9: j8 | B9: 0 | C9: 0 | D9: 0 | E9: 0 | F9: 0 | G9: 0 | H9: 0 | I9: 0 | J9: 0 | K9: 0 | L9: 0 | M9: 0
A10: j9 | B10: 0 | C10: 0 | D10: 0 | E10: 0 | F10: 0 | G10: 0 | H10: 0 | I10: 0 | J10: 0 | K10: 0 | L10: 0 | M10: 0
A11: j12 | B11: 0 | C11: 0 | D11: 0 | E11: 0 | F11: 0 | G11: 0 | H11: 0 | I11: 0 | J11: 0 | K11: 0 | L11: 0 | M11: 0
A12: j13 | B12: 0 | C12: 0 | D12: 0 | E12: 0 | F12: 0 | G12: 0 | H12: 0 | I12: 0 | J12: 0 | K12: 0 | L12: 0 | M12: 0
A13: j14 | B13: 0 | C13: 0 | D13: 0 | E13: 0 | F13: 0 | G13: 0 | H13: 0 | I13: 0 | J13: 0 | K13: 0 | L13: 0 | M13: 0
A14: j15 | B14: 0 | C14: 0 | D14: 0 | E14: 0 | F14: 0 | G14: 0 | H14: 0 | I14: 0 | J14: 0 | K14: 0 | L14: 0 | M14: 0
A15: j16 | B15: 0 | C15: 0 | D15: 0 | E15: 0 | F15: 0 | G15: 0 | H15: 0 | I15: 0 | J15: 0 | K15: 0 | L15: 0 | M15: 0
A16: j17 | B16: 0 | C16: 0 | D16: 0 | E16: 0 | F16: 0 | G16: 0 | H16: 0 | I16: 0 | J16: 0 | K16: 0 | L16: 0 | M16: 0
A17: j18 | B17: 0 | C17: 0 | D17: 0 | E17: 0 | F17: 0 | G17: 0 | H17: 0 | I17: 0 | J17: 0 | K17: 0 | L17: 0 | M17: 0
A18: j19 | B18: =RiversHeadFlow!B4*74466.1151309/1000000 -> 6.7317368 | C18: =RiversHeadFlow!C4*74466.1151309/1000000 -> 3.2839557 | D18: =RiversHeadFlow!D4*74466.1151309/1000000 -> 13.925164 | E18: =RiversHeadFlow!E4*74466.1151309/1000000 -> 31.581079 | F18: =RiversHeadFlow!F4*74466.1151309/1000000 -> 47.032798 | G18: =RiversHeadFlow!G4*74466.1151309/1000000 -> 37.955379 | H18: =RiversHeadFlow!H4*74466.1151309/1000000 -> 24.298293 | I18: =RiversHeadFlow!I4*74466.1151309/1000000 -> 15.436826 | ... M18: =RiversHeadFlow!M4*74466.1151309/1000000 -> 1.2286909
A19: j20 | B19: 0 | C19: 0 | D19: 0 | E19: 0 | F19: 0 | G19: 0 | H19: 0 | I19: 0 | J19: 0 | K19: 0 | L19: 0 | M19: 0
A20: j21 | B20: 0 | C20: 0 | D20: 0 | E20: 0 | F20: 0 | G20: 0 | H20: 0 | I20: 0 | J20: 0 | K20: 0 | L20: 0 | M20: 0
A21: j22 | B21: =RiversHeadFlow!B9*74466.1151309/1000000 -> 9.0319571 | C21: =RiversHeadFlow!C9*74466.1151309/1000000 -> 6.2126171 | D21: =RiversHeadFlow!D9*74466.1151309/1000000 -> 5.916466 | E21: =RiversHeadFlow!E9*74466.1151309/1000000 -> 5.294486 | F21: =RiversHeadFlow!F9*74466.1151309/1000000 -> 6.8148416 | G21: =RiversHeadFlow!G9*74466.1151309/1000000 -> 8.697664 | H21: =RiversHeadFlow!H9*74466.1151309/1000000 -> 6.1230754 | I21: =RiversHeadFlow!I9*74466.1151309/1000000 -> 4.9483324 | ... M21: =RiversHeadFlow!M9*74466.1151309/1000000 -> 5.5292852
A22: j23 | B22: 0 | C22: 0 | D22: 0 | E22: 0 | F22: 0 | G22: 0 | H22: 0 | I22: 0 | J22: 0 | K22: 0 | L22: 0 | M22: 0
A23: j24 | B23: 0 | C23: 0 | D23: 0 | E23: 0 | F23: 0 | G23: 0 | H23: 0 | I23: 0 | J23: 0 | K23: 0 | L23: 0 | M23: 0
A24: j25 | B24: 0 | C24: 0 | D24: 0 | E24: 0 | F24: 0 | G24: 0 | H24: 0 | I24: 0 | J24: 0 | K24: 0 | L24: 0 | M24: 0
A25: j26 | B25: =RiversHeadFlow!B7*0.074466 -> 0 | C25: =RiversHeadFlow!C7*0.074466 -> 0 | D25: =RiversHeadFlow!D7*0.074466 -> 0 | E25: =RiversHeadFlow!E7*0.074466 -> 0 | F25: =RiversHeadFlow!F7*0.074466 -> 0 | G25: =RiversHeadFlow!G7*0.074466 -> 0 | H25: =RiversHeadFlow!H7*0.074466 -> 0 | I25: =RiversHeadFlow!I7*0.074466 -> 0 | ... M25: =RiversHeadFlow!M7*0.074466 -> 0
A26: j27 | B26: 0 | C26: 0 | D26: 0 | E26: 0 | F26: 0 | G26: 0 | H26: 0 | I26: 0 | J26: 0 | K26: 0 | L26: 0 | M26: 0
A27: j28 | B27: 0 | C27: 0 | D27: 0 | E27: 0 | F27: 0 | G27: 0 | H27: 0 | I27: 0 | J27: 0 | K27: 0 | L27: 0 | M27: 0
A28: j29 | B28: 0 | C28: 0 | D28: 0 | E28: 0 | F28: 0 | G28: 0 | H28: 0 | I28: 0 | J28: 0 | K28: 0 | L28: 0 | M28: 0
A29: j30 | B29: 0 | C29: 0 | D29: 0 | E29: 0 | F29: 0 | G29: 0 | H29: 0 | I29: 0 | J29: 0 | K29: 0 | L29: 0 | M29: 0
A30: j31 | B30: =RiversHeadFlow!B3*74466.1151309/1000000 -> 2.1684303 | C30: =RiversHeadFlow!C3*74466.1151309/1000000 -> 2.1488195 | D30: =RiversHeadFlow!D3*74466.1151309/1000000 -> 2.7125664 | E30: =RiversHeadFlow!E3*74466.1151309/1000000 -> 3.0655383 | F30: =RiversHeadFlow!F3*74466.1151309/1000000 -> 1.8541562 | G30: =RiversHeadFlow!G3*74466.1151309/1000000 -> 1.8954377 | H30: =RiversHeadFlow!H3*74466.1151309/1000000 -> 2.6063551 | I30: =RiversHeadFlow!I3*74466.1151309/1000000 -> 2.5277563 | ... M30: =RiversHeadFlow!M3*74466.1151309/1000000 -> 2.5111646
A31: j32 | B31: 0 | C31: 0 | D31: 0 | E31: 0 | F31: 0 | G31: 0 | H31: 0 | I31: 0 | J31: 0 | K31: 0 | L31: 0 | M31: 0
A32: j33 | B32: 0 | C32: 0 | D32: 0 | E32: 0 | F32: 0 | G32: 0 | H32: 0 | I32: 0 | J32: 0 | K32: 0 | L32: 0 | M32: 0
A33: j34 | B33: =RiversHeadFlow!B5*74466.1151309/1000000 -> 0.36061829 | C33: =RiversHeadFlow!C5*74466.1151309/1000000 -> 0.71265887 | D33: =RiversHeadFlow!D5*74466.1151309/1000000 -> 1.991841 | E33: =RiversHeadFlow!E5*74466.1151309/1000000 -> 7.0829635 | F33: =RiversHeadFlow!F5*74466.1151309/1000000 -> 2.4235117 | G33: =RiversHeadFlow!G5*74466.1151309/1000000 -> 0.95366271 | H33: =RiversHeadFlow!H5*74466.1151309/1000000 -> 0.40857075 | I33: =RiversHeadFlow!I5*74466.1151309/1000000 -> 0.31828259 | ... M33: =RiversHeadFlow!M5*74466.1151309/1000000 -> 0.062560207
A34: j35 | B34: =RiversHeadFlow!B13*74466.1151309/1000000 -> 1.3344851 | C34: =RiversHeadFlow!C13*74466.1151309/1000000 -> 1.4176457 | D34: =RiversHeadFlow!D13*74466.1151309/1000000 -> 3.8320749 | E34: =RiversHeadFlow!E13*74466.1151309/1000000 -> 6.159174 | F34: =RiversHeadFlow!F13*74466.1151309/1000000 -> 8.9734717 | G34: =RiversHeadFlow!G13*74466.1151309/1000000 -> 5.1887234 | H34: =RiversHeadFlow!H13*74466.1151309/1000000 -> 1.9548556 | I34: =RiversHeadFlow!I13*74466.1151309/1000000 -> 1.7756565 | ... M34: =RiversHeadFlow!M13*74466.1151309/1000000 -> 1.1699179
A35: j36 | B35: =IF((RiversHeadFlow!B8*74466.1151309/1000000 - B7 -B25 ) <0,0, (RiversHeadFlow!B8*74466.1151309/1000000 - B7 -B25 ) ) -> 52.58926 | C35: =IF((RiversHeadFlow!C8*74466.1151309/1000000 - C7 -C25 ) <0,0, (RiversHeadFlow!C8*74466.1151309/1000000 - C7 -C25 ) ) -> 41.724003 | D35: =IF((RiversHeadFlow!D8*74466.1151309/1000000 - D7 -D25 ) <0,0, (RiversHeadFlow!D8*74466.1151309/1000000 - D7 -D25 ) ) -> 56.84786 | E35: =IF((RiversHeadFlow!E8*74466.1151309/1000000 - E7 -E25 ) <0,0, (RiversHeadFlow!E8*74466.1151309/1000000 - E7 -E25 ) ) -> 55.268006 | F35: =IF((RiversHeadFlow!F8*74466.1151309/1000000 - F7 -F25 ) <0,0, (RiversHeadFlow!F8*74466.1151309/1000000 - F7 -F25 ) ) -> 28.16464 | G35: =IF((RiversHeadFlow!G8*74466.1151309/1000000 - G7 -G25 ) <0,0, (RiversHeadFlow!G8*74466.1151309/1000000 - G7 -G25 ) ) -> 0 | H35: =IF((RiversHeadFlow!H8*74466.1151309/1000000 - H7 -H25 ) <0,0, (RiversHeadFlow!H8*74466.1151309/1000000 - H7 -H25 ) ) -> 0 | I35: =IF((RiversHeadFlow!I8*74466.1151309/1000000 - I7 -I25 ) <0,0, (RiversHeadFlow!I8*74466.1151309/1000000 - I7 -I25 ) ) -> 0 | ... M35: =IF((RiversHeadFlow!M8*74466.1151309/1000000 - M7 -M25 ) <0,0, (RiversHeadFlow!M8*74466.1151309/1000000 - M7 -M25 ) ) -> 27.787655
A36: j37 | B36: =RiversHeadFlow!B2*74466.1151309/1000000 -> 21.266482 | C36: =RiversHeadFlow!C2*74466.1151309/1000000 -> 26.588725 | D36: =RiversHeadFlow!D2*74466.1151309/1000000 -> 29.659233 | E36: =RiversHeadFlow!E2*74466.1151309/1000000 -> 27.043714 | F36: =RiversHeadFlow!F2*74466.1151309/1000000 -> 18.032911 | G36: =RiversHeadFlow!G2*74466.1151309/1000000 -> 67.227595 | H36: =RiversHeadFlow!H2*74466.1151309/1000000 -> 76.370406 | I36: =RiversHeadFlow!I2*74466.1151309/1000000 -> 66.766579 | ... M36: =RiversHeadFlow!M2*74466.1151309/1000000 -> 21.981016
A37: j38 | B37: 0 | C37: 0 | D37: 0 | E37: 0 | F37: 0 | G37: 0 | H37: 0 | I37: 0 | J37: 0 | K37: 0 | L37: 0 | M37: 0
A38: j39 | B38: 0 | C38: 0 | D38: 0 | E38: 0 | F38: 0 | G38: 0 | H38: 0 | I38: 0 | J38: 0 | K38: 0 | L38: 0 | M38: 0

Sheet HeadFlow_Climate1
B1: t1 | C1: t2 | D1: t3 | E1: t4 | F1: t5 | G1: t6 | H1: t7 | I1: t8 | J1: t9 | K1: t10 | L1: t11 | M1: t12
A2: j1 | B2: =HeadFlow!B2*(1+$T$19/100) -> 0 | C2: =HeadFlow!C2*(1+$T$19/100) -> 0 | D2: =HeadFlow!D2*(1+$T$19/100) -> 0 | E2: =HeadFlow!E2*(1+$T$19/100) -> 0 | F2: =HeadFlow!F2*(1+$T$19/100) -> 0 | G2: =HeadFlow!G2*(1+$T$19/100) -> 0 | H2: =HeadFlow!H2*(1+$T$19/100) -> 0 | I2: =HeadFlow!I2*(1+$T$19/100) -> 0 | ... M2: =HeadFlow!M2*(1+$T$19/100) -> 0 | R2: Annual Temp | T2: +3.5 | U2: C
A3: j2 | B3: 0 | C3: 0 | D3: 0 | E3: 0 | F3: 0 | G3: 0 | H3: 0 | I3: 0 | J3: 0 | K3: 0 | L3: 0 | M3: 0 | R3: Annual Precip | T3: +1.6 | U3: %
A4: j3 | B4: 0 | C4: 0 | D4: 0 | E4: 0 | F4: 0 | G4: 0 | H4: 0 | I4: 0 | J4: 0 | K4: 0 | L4: 0 | M4: 0
A5: j4 | B5: 0 | C5: 0 | D5: 0 | E5: 0 | F5: 0 | G5: 0 | H5: 0 | I5: 0 | J5: 0 | K5: 0 | L5: 0 | M5: 0
A6: j5 | B6: 0 | C6: 0 | D6: 0 | E6: 0 | F6: 0 | G6: 0 | H6: 0 | I6: 0 | J6: 0 | K6: 0 | L6: 0 | M6: 0
A7: j6 | B7: 0 | C7: 0 | D7: 0 | E7: 0 | F7: 0 | G7: 0 | H7: 0 | I7: 0 | J7: 0 | K7: 0 | L7: 0 | M7: 0
A8: j7 | B8: 0 | C8: 0 | D8: 0 | E8: 0 | F8: 0 | G8: 0 | H8: 0 | I8: 0 | J8: 0 | K8: 0 | L8: 0 | M8: 0
A9: j8 | B9: 0 | C9: 0 | D9: 0 | E9: 0 | F9: 0 | G9: 0 | H9: 0 | I9: 0 | J9: 0 | K9: 0 | L9: 0 | M9: 0
A10: j9 | B10: 0 | C10: 0 | D10: 0 | E10: 0 | F10: 0 | G10: 0 | H10: 0 | I10: 0 | J10: 0 | K10: 0 | L10: 0 | M10: 0
A11: j12 | B11: 0 | C11: 0 | D11: 0 | E11: 0 | F11: 0 | G11: 0 | H11: 0 | I11: 0 | J11: 0 | K11: 0 | L11: 0 | M11: 0
A12: j13 | B12: 0 | C12: 0 | D12: 0 | E12: 0 | F12: 0 | G12: 0 | H12: 0 | I12: 0 | J12: 0 | K12: 0 | L12: 0 | M12: 0
A13: j14 | B13: 0 | C13: 0 | D13: 0 | E13: 0 | F13: 0 | G13: 0 | H13: 0 | I13: 0 | J13: 0 | K13: 0 | L13: 0 | M13: 0
A14: j15 | B14: 0 | C14: 0 | D14: 0 | E14: 0 | F14: 0 | G14: 0 | H14: 0 | I14: 0 | J14: 0 | K14: 0 | L14: 0 | M14: 0
A15: j16 | B15: 0 | C15: 0 | D15: 0 | E15: 0 | F15: 0 | G15: 0 | H15: 0 | I15: 0 | J15: 0 | K15: 0 | L15: 0 | M15: 0
A16: j17 | B16: 0 | C16: 0 | D16: 0 | E16: 0 | F16: 0 | G16: 0 | H16: 0 | I16: 0 | J16: 0 | K16: 0 | L16: 0 | M16: 0
A17: j18 | B17: 0 | C17: 0 | D17: 0 | E17: 0 | F17: 0 | G17: 0 | H17: 0 | I17: 0 | J17: 0 | K17: 0 | L17: 0 | M17: 0 | R17: Hydrology | T17: Mar, Apr | U17: May - Oct | V17: Nov-Feb
A18: j19 | B18: =HeadFlow!B18*(1+$V$19/100) -> 10.097605 | C18: =HeadFlow!C18*(1+$V$19/100) -> 4.9259335 | D18: =HeadFlow!D18*(1+$T$19/100) -> 11.390784 | E18: =HeadFlow!E18*(1+$T$19/100) -> 25.833323 | F18: =HeadFlow!F18*(1+$U$19/100) -> 35.274599 | G18: =HeadFlow!G18*(1+$U$19/100) -> 28.466534 | H18: =HeadFlow!H18*(1+$U$19/100) -> 18.22372 | I18: =HeadFlow!I18*(1+$U$19/100) -> 11.577619 | J18: =HeadFlow!J18*(1+$U$19/100) -> 17.011784 | K18: =HeadFlow!K18*(1+$U$19/100) -> 26.104097 | L18: =HeadFlow!L18*(1+$V$19/100) -> 20.329249 | M18: =HeadFlow!M18*(1+$V$19/100) -> 1.8430363 | T18: Runoff | U18: Summer | V18: Winter
A19: j20 | B19: 0 | C19: 0 | D19: 0 | E19: 0 | F19: 0 | G19: 0 | H19: 0 | I19: 0 | J19: 0 | K19: 0 | L19: 0 | M19: 0 | R19: Bear | T19: -18.2 | U19: -25 | V19: 50 | W19: %
A20: j21 | B20: 0 | C20: 0 | D20: 0 | E20: 0 | F20: 0 | G20: 0 | H20: 0 | I20: 0 | J20: 0 | K20: 0 | L20: 0 | M20: 0 | R20: Blacksmith Fork | T20: -4.6 | U20: -10 | V20: 30 | W20: %
A21: j22 | B21: 0 | C21: 0 | D21: 0 | E21: 0 | F21: 0 | G21: 0 | H21: 0 | I21: 0 | J21: 0 | K21: 0 | L21: 0 | M21: 0 | R21: Logan | T21: -6.6 | W21: %
A22: j23 | B22: 0 | C22: 0 | D22: 0 | E22: 0 | F22: 0 | G22: 0 | H22: 0 | I22: 0 | J22: 0 | K22: 0 | L22: 0 | M22: 0
A23: j24 | B23: 0 | C23: 0 | D23: 0 | E23: 0 | F23: 0 | G23: 0 | H23: 0 | I23: 0 | J23: 0 | K23: 0 | L23: 0 | M23: 0
A24: j25 | B24: 0 | C24: 0 | D24: 0 | E24: 0 | F24: 0 | G24: 0 | H24: 0 | I24: 0 | J24: 0 | K24: 0 | L24: 0 | M24: 0
A25: j26 | B25: 0 | C25: 0 | D25: 0 | E25: 0 | F25: 0 | G25: 0 | H25: 0 | I25: 0 | J25: 0 | K25: 0 | L25: 0 | M25: 0
A26: j27 | B26: 0 | C26: 0 | D26: 0 | E26: 0 | F26: 0 | G26: 0 | H26: 0 | I26: 0 | J26: 0 | K26: 0 | L26: 0 | M26: 0
A27: j28 | B27: 0 | C27: 0 | D27: 0 | E27: 0 | F27: 0 | G27: 0 | H27: 0 | I27: 0 | J27: 0 | K27: 0 | L27: 0 | M27: 0
A28: j29 | B28: 0 | C28: 0 | D28: 0 | E28: 0 | F28: 0 | G28: 0 | H28: 0 | I28: 0 | J28: 0 | K28: 0 | L28: 0 | M28: 0
A29: j30 | B29: 0 | C29: 0 | D29: 0 | E29: 0 | F29: 0 | G29: 0 | H29: 0 | I29: 0 | J29: 0 | K29: 0 | L29: 0 | M29: 0
A30: j31 | B30: =HeadFlow!B30*(1+$V$20/100) -> 2.8189593 | C30: =HeadFlow!C30*(1+$V$20/100) -> 2.7934653 | D30: =HeadFlow!D30*(1+$T$20/100) -> 2.5877883 | E30: =HeadFlow!E30*(1+$T$20/100) -> 2.9245235 | F30: =HeadFlow!F30*(1+$U$20/100) -> 1.6687406 | G30: =HeadFlow!G30*(1+$U$20/100) -> 1.705894 | H30: =HeadFlow!H30*(1+$U$20/100) -> 2.3457196 | I30: =HeadFlow!I30*(1+$U$20/100) -> 2.2749807 | J30: =HeadFlow!J30*(1+$U$20/100) -> 2.4999355 | K30: =HeadFlow!K30*(1+$U$20/100) -> 2.4146055 | L30: =HeadFlow!L30*(1+$V$20/100) -> 3.4854229 | M30: =HeadFlow!M30*(1+$V$20/100) -> 3.2645139
A31: j32 | B31: 0 | C31: 0 | D31: 0 | E31: 0 | F31: 0 | G31: 0 | H31: 0 | I31: 0 | J31: 0 | K31: 0 | L31: 0 | M31: 0
A32: j33 | B32: 0 | C32: 0 | D32: 0 | E32: 0 | F32: 0 | G32: 0 | H32: 0 | I32: 0 | J32: 0 | K32: 0 | L32: 0 | M32: 0
A33: j34 | B33: =HeadFlow!B33*(1+$V$20/100) -> 0.46880378 | C33: =HeadFlow!C33*(1+$V$20/100) -> 0.92645653 | D33: =HeadFlow!D33*(1+$T$20/100) -> 1.9002163 | E33: =HeadFlow!E33*(1+$T$20/100) -> 6.7571472 | F33: =HeadFlow!F33*(1+$U$20/100) -> 2.1811606 | G33: =HeadFlow!G33*(1+$U$20/100) -> 0.85829644 | H33: =HeadFlow!H33*(1+$U$20/100) -> 0.36771368 | I33: =HeadFlow!I33*(1+$U$20/100) -> 0.28645433 | J33: =HeadFlow!J33*(1+$U$20/100) -> 0.24841896 | K33: =HeadFlow!K33*(1+$U$20/100) -> 0.21219351 | L33: =HeadFlow!L33*(1+$V$20/100) -> 0.35571622 | M33: =HeadFlow!M33*(1+$V$20/100) -> 0.081328269
A34: j35 | B34: 0 | C34: 0 | D34: 0 | E34: 0 | F34: 0 | G34: 0 | H34: 0 | I34: 0 | J34: 0 | K34: 0 | L34: 0 | M34: 0
A35: j36 | B35: 0 | C35: 0 | D35: 0 | E35: 0 | F35: 0 | G35: 0 | H35: 0 | I35: 0 | J35: 0 | K35: 0 | L35: 0 | M35: 0
A36: j37 | B36: =HeadFlow!B36*(1+HeadFlow_Climate1!$V$19/100) -> 31.899722 | C36: =HeadFlow!C36*(1+HeadFlow_Climate1!$V$19/100) -> 39.883087 | D36: =HeadFlow!D36*(1+HeadFlow_Climate1!$T$19/100) -> 24.261253 | E36: =HeadFlow!E36*(1+HeadFlow_Climate1!$T$19/100) -> 22.121758 | F36: =HeadFlow!F36*(1+HeadFlow_Climate1!$U$19/100) -> 13.524683 | G36: =HeadFlow!G36*(1+HeadFlow_Climate1!$U$19/100) -> 50.420696 | H36: =HeadFlow!H36*(1+HeadFlow_Climate1!$U$19/100) -> 57.277804 | I36: =HeadFlow!I36*(1+HeadFlow_Climate1!$U$19/100) -> 50.074934 | J36: =HeadFlow!J36*(1+HeadFlow_Climate1!$U$19/100) -> 23.905717 | K36: =HeadFlow!K36*(1+HeadFlow_Climate1!$U$19/100) -> 12.025977 | L36: =HeadFlow!L36*(1+HeadFlow_Climate1!$V$19/100) -> 31.893061 | M36: =HeadFlow!M36*(1+HeadFlow_Climate1!$V$19/100) -> 32.971524
A37: j38 | B37: 0 | C37: 0 | D37: 0 | E37: 0 | F37: 0 | G37: 0 | H37: 0 | I37: 0 | J37: 0 | K37: 0 | L37: 0 | M37: 0
A38: j39 | B38: 0 | C38: 0 | D38: 0 | E38: 0 | F38: 0 | G38: 0 | H38: 0 | I38: 0 | J38: 0 | K38: 0 | L38: 0 | M38: 0

Sheet HeadFlow_Climate2
B1: t1 | C1: t2 | D1: t3 | E1: t4 | F1: t5 | G1: t6 | H1: t7 | I1: t8 | J1: t9 | K1: t10 | L1: t11 | M1: t12
A2: j1 | B2: =HeadFlow!B2*(1+$T$19/100) -> 0 | C2: =HeadFlow!C2*(1+$T$19/100) -> 0 | D2: =HeadFlow!D2*(1+$T$19/100) -> 0 | E2: =HeadFlow!E2*(1+$T$19/100) -> 0 | F2: =HeadFlow!F2*(1+$T$19/100) -> 0 | G2: =HeadFlow!G2*(1+$T$19/100) -> 0 | H2: =HeadFlow!H2*(1+$T$19/100) -> 0 | I2: =HeadFlow!I2*(1+$T$19/100) -> 0 | ... M2: =HeadFlow!M2*(1+$T$19/100) -> 0 | R2: Annual Temp | T2: +2.7 | U2: C
A3: j2 | B3: 0 | C3: 0 | D3: 0 | E3: 0 | F3: 0 | G3: 0 | H3: 0 | I3: 0 | J3: 0 | K3: 0 | L3: 0 | M3: 0 | R3: Annual Precip | T3: -3 | U3: %
A4: j3 | B4: 0 | C4: 0 | D4: 0 | E4: 0 | F4: 0 | G4: 0 | H4: 0 | I4: 0 | J4: 0 | K4: 0 | L4: 0 | M4: 0
A5: j4 | B5: 0 | C5: 0 | D5: 0 | E5: 0 | F5: 0 | G5: 0 | H5: 0 | I5: 0 | J5: 0 | K5: 0 | L5: 0 | M5: 0
A6: j5 | B6: 0 | C6: 0 | D6: 0 | E6: 0 | F6: 0 | G6: 0 | H6: 0 | I6: 0 | J6: 0 | K6: 0 | L6: 0 | M6: 0
A7: j6 | B7: 0 | C7: 0 | D7: 0 | E7: 0 | F7: 0 | G7: 0 | H7: 0 | I7: 0 | J7: 0 | K7: 0 | L7: 0 | M7: 0
A8: j7 | B8: 0 | C8: 0 | D8: 0 | E8: 0 | F8: 0 | G8: 0 | H8: 0 | I8: 0 | J8: 0 | K8: 0 | L8: 0 | M8: 0
A9: j8 | B9: 0 | C9: 0 | D9: 0 | E9: 0 | F9: 0 | G9: 0 | H9: 0 | I9: 0 | J9: 0 | K9: 0 | L9: 0 | M9: 0
A10: j9 | B10: 0 | C10: 0 | D10: 0 | E10: 0 | F10: 0 | G10: 0 | H10: 0 | I10: 0 | J10: 0 | K10: 0 | L10: 0 | M10: 0
A11: j12 | B11: 0 | C11: 0 | D11: 0 | E11: 0 | F11: 0 | G11: 0 | H11: 0 | I11: 0 | J11: 0 | K11: 0 | L11: 0 | M11: 0
A12: j13 | B12: 0 | C12: 0 | D12: 0 | E12: 0 | F12: 0 | G12: 0 | H12: 0 | I12: 0 | J12: 0 | K12: 0 | L12: 0 | M12: 0
A13: j14 | B13: 0 | C13: 0 | D13: 0 | E13: 0 | F13: 0 | G13: 0 | H13: 0 | I13: 0 | J13: 0 | K13: 0 | L13: 0 | M13: 0
A14: j15 | B14: 0 | C14: 0 | D14: 0 | E14: 0 | F14: 0 | G14: 0 | H14: 0 | I14: 0 | J14: 0 | K14: 0 | L14: 0 | M14: 0
A15: j16 | B15: 0 | C15: 0 | D15: 0 | E15: 0 | F15: 0 | G15: 0 | H15: 0 | I15: 0 | J15: 0 | K15: 0 | L15: 0 | M15: 0
A16: j17 | B16: 0 | C16: 0 | D16: 0 | E16: 0 | F16: 0 | G16: 0 | H16: 0 | I16: 0 | J16: 0 | K16: 0 | L16: 0 | M16: 0
A17: j18 | B17: 0 | C17: 0 | D17: 0 | E17: 0 | F17: 0 | G17: 0 | H17: 0 | I17: 0 | J17: 0 | K17: 0 | L17: 0 | M17: 0 | R17: Hydrology | T17: Mar, Apr | U17: May - Oct | V17: Nov-Feb
A18: j19 | B18: =HeadFlow!B18*(1+$V$19/100) -> 10.097605 | C18: =HeadFlow!C18*(1+$V$19/100) -> 4.9259335 | D18: =HeadFlow!D18*(1+$T$19/100) -> 12.059192 | E18: =HeadFlow!E18*(1+$T$19/100) -> 27.349215 | F18: =HeadFlow!F18*(1+$U$19/100) -> 23.516399 | G18: =HeadFlow!G18*(1+$U$19/100) -> 18.977689 | H18: =HeadFlow!H18*(1+$U$19/100) -> 12.149147 | I18: =HeadFlow!I18*(1+$U$19/100) -> 7.7184128 | J18: =HeadFlow!J18*(1+$U$19/100) -> 11.341189 | K18: =HeadFlow!K18*(1+$U$19/100) -> 17.402731 | L18: =HeadFlow!L18*(1+$V$19/100) -> 20.329249 | M18: =HeadFlow!M18*(1+$V$19/100) -> 1.8430363 | T18: Runoff | U18: Summer | V18: Winter
A19: j20 | B19: 0 | C19: 0 | D19: 0 | E19: 0 | F19: 0 | G19: 0 | H19: 0 | I19: 0 | J19: 0 | K19: 0 | L19: 0 | M19: 0 | R19: Bear | T19: -13.4 | U19: -50 | V19: 50 | W19: %
A20: j21 | B20: 0 | C20: 0 | D20: 0 | E20: 0 | F20: 0 | G20: 0 | H20: 0 | I20: 0 | J20: 0 | K20: 0 | L20: 0 | M20: 0 | R20: Blacksmith Fork | T20: -7.7 | U20: -15 | V20: 30 | W20: %
A21: j22 | B21: 0 | C21: 0 | D21: 0 | E21: 0 | F21: 0 | G21: 0 | H21: 0 | I21: 0 | J21: 0 | K21: 0 | L21: 0 | M21: 0 | R21: Logan | T21: 4.6 | W21: %
A22: j23 | B22: 0 | C22: 0 | D22: 0 | E22: 0 | F22: 0 | G22: 0 | H22: 0 | I22: 0 | J22: 0 | K22: 0 | L22: 0 | M22: 0
A23: j24 | B23: 0 | C23: 0 | D23: 0 | E23: 0 | F23: 0 | G23: 0 | H23: 0 | I23: 0 | J23: 0 | K23: 0 | L23: 0 | M23: 0
A24: j25 | B24: 0 | C24: 0 | D24: 0 | E24: 0 | F24: 0 | G24: 0 | H24: 0 | I24: 0 | J24: 0 | K24: 0 | L24: 0 | M24: 0
A25: j26 | B25: 0 | C25: 0 | D25: 0 | E25: 0 | F25: 0 | G25: 0 | H25: 0 | I25: 0 | J25: 0 | K25: 0 | L25: 0 | M25: 0
A26: j27 | B26: 0 | C26: 0 | D26: 0 | E26: 0 | F26: 0 | G26: 0 | H26: 0 | I26: 0 | J26: 0 | K26: 0 | L26: 0 | M26: 0
A27: j28 | B27: 0 | C27: 0 | D27: 0 | E27: 0 | F27: 0 | G27: 0 | H27: 0 | I27: 0 | J27: 0 | K27: 0 | L27: 0 | M27: 0
A28: j29 | B28: 0 | C28: 0 | D28: 0 | E28: 0 | F28: 0 | G28: 0 | H28: 0 | I28: 0 | J28: 0 | K28: 0 | L28: 0 | M28: 0
A29: j30 | B29: 0 | C29: 0 | D29: 0 | E29: 0 | F29: 0 | G29: 0 | H29: 0 | I29: 0 | J29: 0 | K29: 0 | L29: 0 | M29: 0
A30: j31 | B30: =HeadFlow!B30*(1+$V$20/100) -> 2.8189593 | C30: =HeadFlow!C30*(1+$V$20/100) -> 2.7934653 | D30: =HeadFlow!D30*(1+$T$20/100) -> 2.5036988 | E30: =HeadFlow!E30*(1+$T$20/100) -> 2.8294918 | F30: =HeadFlow!F30*(1+$U$20/100) -> 1.5760328 | G30: =HeadFlow!G30*(1+$U$20/100) -> 1.6111221 | H30: =HeadFlow!H30*(1+$U$20/100) -> 2.2154018 | I30: =HeadFlow!I30*(1+$U$20/100) -> 2.1485928 | J30: =HeadFlow!J30*(1+$U$20/100) -> 2.3610502 | K30: =HeadFlow!K30*(1+$U$20/100) -> 2.2804608 | L30: =HeadFlow!L30*(1+$V$20/100) -> 3.4854229 | M30: =HeadFlow!M30*(1+$V$20/100) -> 3.2645139
A31: j32 | B31: 0 | C31: 0 | D31: 0 | E31: 0 | F31: 0 | G31: 0 | H31: 0 | I31: 0 | J31: 0 | K31: 0 | L31: 0 | M31: 0
A32: j33 | B32: 0 | C32: 0 | D32: 0 | E32: 0 | F32: 0 | G32: 0 | H32: 0 | I32: 0 | J32: 0 | K32: 0 | L32: 0 | M32: 0
A33: j34 | B33: =HeadFlow!B33*(1+$V$20/100) -> 0.46880378 | C33: =HeadFlow!C33*(1+$V$20/100) -> 0.92645653 | D33: =HeadFlow!D33*(1+$T$20/100) -> 1.8384693 | E33: =HeadFlow!E33*(1+$T$20/100) -> 6.5375753 | F33: =HeadFlow!F33*(1+$U$20/100) -> 2.059985 | G33: =HeadFlow!G33*(1+$U$20/100) -> 0.81061331 | H33: =HeadFlow!H33*(1+$U$20/100) -> 0.34728514 | I33: =HeadFlow!I33*(1+$U$20/100) -> 0.2705402 | J33: =HeadFlow!J33*(1+$U$20/100) -> 0.23461791 | K33: =HeadFlow!K33*(1+$U$20/100) -> 0.20040498 | L33: =HeadFlow!L33*(1+$V$20/100) -> 0.35571622 | M33: =HeadFlow!M33*(1+$V$20/100) -> 0.081328269
A34: j35 | B34: 0 | C34: 0 | D34: 0 | E34: 0 | F34: 0 | G34: 0 | H34: 0 | I34: 0 | J34: 0 | K34: 0 | L34: 0 | M34: 0
A35: j36 | B35: 0 | C35: 0 | D35: 0 | E35: 0 | F35: 0 | G35: 0 | H35: 0 | I35: 0 | J35: 0 | K35: 0 | L35: 0 | M35: 0
A36: j37 | B36: =HeadFlow!B36*(1+HeadFlow_Climate2!$V$19/100) -> 31.899722 | C36: =HeadFlow!C36*(1+HeadFlow_Climate2!$V$19/100) -> 39.883087 | D36: =HeadFlow!D36*(1+HeadFlow_Climate2!$T$19/100) -> 25.684896 | E36: =HeadFlow!E36*(1+HeadFlow_Climate2!$T$19/100) -> 23.419857 | F36: =HeadFlow!F36*(1+HeadFlow_Climate2!$U$19/100) -> 9.0164553 | G36: =HeadFlow!G36*(1+HeadFlow_Climate2!$U$19/100) -> 33.613798 | H36: =HeadFlow!H36*(1+HeadFlow_Climate2!$U$19/100) -> 38.185203 | I36: =HeadFlow!I36*(1+HeadFlow_Climate2!$U$19/100) -> 33.38329 | J36: =HeadFlow!J36*(1+HeadFlow_Climate2!$U$19/100) -> 15.937145 | K36: =HeadFlow!K36*(1+HeadFlow_Climate2!$U$19/100) -> 8.0173182 | L36: =HeadFlow!L36*(1+HeadFlow_Climate2!$V$19/100) -> 31.893061 | M36: =HeadFlow!M36*(1+HeadFlow_Climate2!$V$19/100) -> 32.971524
A37: j38 | B37: 0 | C37: 0 | D37: 0 | E37: 0 | F37: 0 | G37: 0 | H37: 0 | I37: 0 | J37: 0 | K37: 0 | L37: 0 | M37: 0
A38: j39 | B38: 0 | C38: 0 | D38: 0 | E38: 0 | F38: 0 | G38: 0 | H38: 0 | I38: 0 | J38: 0 | K38: 0 | L38: 0 | M38: 0

Sheet RiversHeadFlow
A1: Flow (cfs) | B1: t1 | C1: t2 | D1: t3 | E1: t4 | F1: t5 | G1: t6 | H1: t7 | I1: t8 | J1: t9 | K1: t10 | L1: t11 | M1: t12
A2: Bear | B2: 285.58602 | C2: 357.05804 | D2: 398.29167 | E2: 363.16806 | F2: 242.16263 | G2: 902.79444 | H2: 1025.5726 | I2: 896.60349 | J2: 428.0375 | K2: 215.32796 | L2: 285.52639 | M2: 295.18145
A3: Blacksmithfork | B3: 29.119691 | C3: 28.856339 | D3: 36.426855 | E3: 41.166889 | F3: 24.899328 | G3: 25.453694 | H3: 35.000551 | I3: 33.945054 | J3: 37.301611 | K3: 36.028401 | L3: 36.004222 | M3: 33.722245
A4: Malad | B4: 90.4 | C4: 44.1 | D4: 187 | E4: 424.1 | F4: 631.6 | G4: 509.7 | H4: 326.3 | I4: 207.3 | J4: 304.6 | K4: 467.4 | L4: 182 | M4: 16.5
A5: Little Bear - East Fork | B5: 4.8427166 | C5: 9.5702437 | D5: 26.748287 | E5: 95.116598 | F5: 32.545161 | G5: 12.806667 | H5: 5.4866667 | I5: 4.2741935 | J5: 3.7066667 | K5: 3.1661456 | L5: 3.6745285 | M5: 0.84011643
A6: Cub River | B6: 16.8 | C6: 18.5 | D6: 31.2 | E6: 81.2 | F6: 363.9 | G6: 418 | H6: 112.1 | I6: 54.8 | J6: 36.1 | K6: 28.2 | L6: 23.3 | M6: 17.2
A7: Logan River | B7: 0 | C7: 0 | D7: 0 | E7: 0 | F7: 0 | G7: 0 | H7: 0 | I7: 0 | J7: 0 | K7: 0 | L7: 0 | M7: 0
A8: SouthCache Gain To Cutler | B8: 723.01728 | C8: 578.80854 | D8: 794.6057 | E8: 823.38987 | F8: 742.12032 | G8: 247.97269 | H8: 0 | I8: 0 | J8: 234.17365 | K8: 185.04706 | L8: 303.57219 | M8: 390.35836
A9: Malad Reach Gain | B9: 121.28949 | C9: 83.42878 | D9: 79.451788 | E9: 71.099264 | F9: 91.516008 | G9: 116.80029 | H9: 82.226331 | I9: 66.450793 | J9: 122.46712 | K9: 129.04878 | L9: 84.599167 | M9: 74.252366 | N9: 58.060484 | O9: 73.185193 | P9: 41.639288 | Q9: 26.325903 | R9: 62.723212 | S9: 80.866653 | T9: 40.41953 | U9: 50.354866 | V9: 111.86618 | W9: 124.48363 | X9: 81.767431 | Y9: 61.579892 | Z9: 75.483508 | AA9: 96.749583 | AB9: 111.80628 | AC9: 26.633444 | AD9: 72.871599 | AE9: 136.29978 | AF9: 43.000538 | AG9: 46.741129 | AH9: 114.66599 | AI9: 133.54887 | AJ9: 87.099833 | AK9: 101.67741 | AL9: 132.48362 | AM9: 90.107187 | AN9: 193.61301 | AO9: 222.66689 | AP9: 515.28923 | AQ9: 347.79937 | AR9: 136.93492 | AS9: 122.48323 | AT9: 121.93271 | AU9: 144.41935 | AV9: 97.299125 | AW9: 116.61212 | AX9: 219.54832 | AY9: 172.39259 | AZ9: 227.61336 | BA9: 402.43256 | BB9: 351.19274 | BC9: 190.43383 | BD9: 122.64586 | BE9: 119.83879 | BF9: 137.66607
A10: Corinne, UT | B10: 1316 | C10: 1288 | D10: 2418 | E10: 3874 | F10: 5312 | G10: 5469 | H10: 2460 | I10: 1367 | J10: 1391 | K10: 1964 | L10: 2217 | M10: 1738
A11: Paradise - Little Bear | B11: 39.2 | C11: 34.6 | D11: 82.8 | E11: 367.4 | F11: 494 | G11: 202.9 | H11: 40.4 | I11: 32.3 | J11: 37.1 | K11: 48.7 | L11: 52.9 | M11: 61.7
A12: Cutler | B12: 1123 | C12: 1024 | D12: 2174 | E12: 3129 | F12: 5205 | G12: 3016 | H12: 126.7 | I12: 93 | J12: 243.4 | K12: 775.8 | L12: 979.8 | M12: 1213
A13: Little Bear - South Fork | B13: 17.920702 | C13: 19.03746 | D13: 51.460652 | E13: 82.711095 | F13: 120.50409 | G13: 69.678986 | H13: 26.251613 | I13: 23.845161 | J13: 21.925257 | K13: 16.347818 | L13: 17.266205 | M13: 15.710741
A23: Little Bear - East Fork | B23: 15.055067 | C23: 3.5849851 | D23: 35.805591 | E23: 74.477181 | F23: 81.109032 | G23: 43.207083 | H23: 20.680591 | I23: 16.489503 | J23: 17.524833 | K23: 18.005255 | L23: 19.556625 | M23: 17.666976

Sheet RiversHeadFlow-2005
B1: t1 | C1: t2 | D1: t3 | E1: t4 | F1: t5 | G1: t6 | H1: t7 | I1: t8 | J1: t9 | K1: t10 | L1: t11 | M1: t12
A2: Bear | B2: 310.46909 | C2: 299.25893 | D2: 509.0457 | E2: 1039.2556 | F2: 1245.4543 | G2: 898.425 | H2: 730.87903 | I2: 753.97312 | J2: 443.1625 | K2: 417.97043 | L2: 434.0875 | M2: 423.5
A3: Blacksmithfork | B3: 25.014798 | C3: 25.507232 | D3: 40.640712 | E3: 45.030486 | F3: 25.577513 | G3: 25.806611 | H3: 36.755376 | I3: 32.495981 | J3: 32.676722 | K3: 32.012957 | L3: 32.871667 | M3: 29.721438
A4: Malad | B4: 32.637473 | C4: 58.740818 | D4: 96.435699 | E4: 53.720639 | F4: 19.938978 | G4: 29.229903 | H4: 16.052016 | I4: 13.783266 | J4: 15.731681 | K4: 24.294328 | L4: 32.585972 | M4: 50.267043
A5: Little Bear - East Fork | B5: 5.8113881 | C5: 10.627779 | D5: 28.058404 | E5: 102.7581 | F5: 80.670968 | G5: 49.453333 | H5: 34.632258 | I5: 28.987097 | J5: 26.883333 | K5: 23.427544 | L5: 23.136393 | M5: 23.071866
A6: Cub River | B6: 20.2 | C6: 17.6 | D6: 28.3 | E6: 125.7 | F6: 467.1 | G6: 399.8 | H6: 88.4 | I6: 44.4 | J6: 30.9 | K6: 26.2 | L6: 24.1 | M6: 20.3
A7: Logan River | B7: 0 | C7: 0 | D7: 0 | E7: 0 | F7: 0 | G7: 0 | H7: 0 | I7: 0 | J7: 0 | K7: 0 | L7: 0 | M7: 0
A8: SouthCache Gain To Cutler | B8: 463.36332 | C8: 675.81381 | D8: 790.30402 | E8: 850.06365 | F8: 563.94782 | G8: 555.2169 | H8: 0 | I8: 0 | J8: 223.94075 | K8: 268.01337 | L8: 328.09822 | M8: 594.66296
A9: Malad Reach Gain | B9: 75.483508 | C9: 96.749583 | D9: 111.80628 | E9: 26.633444 | F9: 72.871599 | G9: 136.29978 | H9: 43.000538 | I9: 46.741129 | J9: 114.66599 | K9: 133.54887 | L9: 87.099833 | M9: 101.67741
A10: Corinne, UT | B10: 1240 | C10: 1016 | D10: 2232 | E10: 3114 | F10: 5862 | G10: 3241 | H10: 243.8 | I10: 171.1 | J10: 297.1 | K10: 775.8 | L10: 870.9 | M10: 1189
A11: Paradise - Little Bear | B11: 39.2 | C11: 34.6 | D11: 82.8 | E11: 367.4 | F11: 494 | G11: 202.9 | H11: 40.4 | I11: 32.3 | J11: 37.1 | K11: 48.7 | L11: 52.9 | M11: 61.7
A12: Cutler | B12: 1123 | C12: 1024 | D12: 2174 | E12: 3129 | F12: 5205 | G12: 3016 | H12: 126.7 | I12: 93 | J12: 243.4 | K12: 775.8 | L12: 979.8 | M12: 1213
A13: Little Bear - South Fork | B13: 20.938263 | C13: 14.938263 | D13: 56.197867 | E13: 151.02467 | F13: 239.5823 | G13: 138.05244 | H13: 60.037261 | I13: 49.735132 | J13: 26.770348 | K13: 38.024643 | L13: 46.975236 | M13: 36.916481

Sheet RiversHeadFlow-2006
B1: t1 | C1: t2 | D1: t3 | E1: t4 | F1: t5 | G1: t6 | H1: t7 | I1: t8 | J1: t9 | K1: t10 | L1: t11 | M1: t12
A2: Bear | B2: 531.48925 | C2: 411.43601 | D2: 719.81989 | E2: 1733.6611 | F2: 1244.8038 | G2: 474.925 | H2: 643.86962 | I2: 772.18817 | J2: 528.36667 | K2: 504.97984 | L2: 498.28472 | M2: 466.92339
A3: Blacksmithfork | B3: 27.068871 | C3: 25.38119 | D3: 40.388629 | E3: 61.328514 | F3: 49.927137 | G3: 43.341528 | H3: 73.675013 | I3: 68.150323 | J3: 61.273056 | K3: 54.136116 | L3: 50.562875 | M3: 47.351008
A4: Malad | B4: 54.132863 | C4: 55.154033 | D4: 155.41344 | E4: 143.4371 | F4: 172.36808 | G4: 63.656083 | H4: 24.294328 | I4: 20.732634 | J4: 21.176681 | K4: 32.108911 | L4: 37.943583 | M4: 55.884435
A5: Little Bear - East Fork | B5: 15.289041 | C5: 14.590741 | D5: 27.976894 | E5: 102.28268 | F5: 77.676774 | G5: 44.322 | H5: 35.106774 | I5: 30.514839 | J5: 29.263667 | K5: 25.188279 | L5: 25.054189 | M5: 24.459965
A6: Cub River | B6: 20.2 | C6: 17.6 | D6: 28.3 | E6: 125.7 | F6: 467.1 | G6: 399.8 | H6: 88.4 | I6: 44.4 | J6: 30.9 | K6: 26.2 | L6: 24.1 | M6: 20.3
A7: Logan River | B7: 0 | C7: 0 | D7: 0 | E7: 0 | F7: 0 | G7: 0 | H7: 0 | I7: 0 | J7: 0 | K7: 0 | L7: 0 | M7: 0
A8: SouthCache Gain To Cutler | B8: 756.44028 | C8: 600.79561 | D8: 1444.4326 | E8: 1656.6765 | F8: 3922.0507 | G8: 2548.0802 | H8: 143.99813 | I8: 9.7466801 | J8: 313.79165 | K8: 182.17981 | L8: 259.59037 | M8: 572.94151
A9: Malad Reach Gain | B9: 132.48362 | C9: 90.107187 | D9: 193.61301 | E9: 222.66689 | F9: 515.28923 | G9: 347.79937 | H9: 136.93492 | I9: 122.48323 | J9: 121.93271 | K9: 144.41935 | L9: 97.299125 | M9: 116.61212
A10: Corinne, UT | B10: 1811 | C10: 1585 | D10: 2500 | E10: 4968 | F10: 3853 | G10: 1201 | H10: 122.6 | I10: 149.2 | J10: 640.1 | K10: 1111 | L10: 1297 | M10: 1414
A11: Paradise - Little Bear
A12: Cutler
A13: Little Bear - South Fork | B13: 34.637988 | C13: 28.637988 | D13: 69.664161 | E13: 155.96043 | F13: 196.81021 | G13: 108.76975 | H13: 60.307542 | I13: 50.613025 | J13: 28.623043 | K13: 39.738049 | L13: 49.163043 | M13: 32.488474

Sheet RiversHeadFlow-2011
B1: t1 | C1: t2 | D1: t3 | E1: t4 | F1: t5 | G1: t6 | H1: t7 | I1: t8 | J1: t9 | K1: t10 | L1: t11 | M1: t12
A2: Bear | B2: 576.6 | C2: 493.1 | D2: 785 | E2: 1777 | F2: 2035 | G2: 1702 | H2: 1006 | I2: 1231 | J2: 1249 | K2: 1297 | L2: 1475 | M2: 1242
A3: Blacksmithfork | B3: 84.3 | C3: 75.5 | D3: 130.1 | E3: 368.8 | F3: 758.6 | G3: 527.3 | H3: 286.3 | I3: 226.3 | J3: 193.3 | K3: 166.3 | L3: 147.4 | M3: 126.5
A4: Malad | B4: 90.4 | C4: 44.1 | D4: 187 | E4: 424.1 | F4: 631.6 | G4: 509.7 | H4: 326.3 | I4: 207.3 | J4: 304.6 | K4: 467.4 | L4: 182 | M4: 16.5
A5: Little Bear - East Fork | B5: 59.9 | C5: 49.4 | D5: 138.6 | E5: 354.2 | F5: 693.5 | G5: 576.9 | H5: 123.6 | I5: 62.2 | J5: 59.6 | K5: 65.8 | L5: 65.9 | M5: 58.2
A6: Cub River | B6: 16.8 | C6: 18.5 | D6: 31.2 | E6: 81.2 | F6: 363.9 | G6: 418 | H6: 112.1 | I6: 54.8 | J6: 36.1 | K6: 28.2 | L6: 23.3 | M6: 17.2
A7: Logan River | B7: 0 | C7: 0 | D7: 0 | E7: 0 | F7: 0 | G7: 0 | H7: 0 | I7: 0 | J7: 0 | K7: 0 | L7: 0 | M7: 0
A8: SouthCache Gain To Cutler | B8: 463.36332 | C8: 675.81381 | D8: 790.30402 | E8: 850.06365 | F8: 563.94782 | G8: 555.2169 | H8: 0 | I8: 0 | J8: 223.94075 | K8: 268.01337 | L8: 328.09822 | M8: 594.66296
A9: Malad Reach Gain | B9: 75.483508 | C9: 96.749583 | D9: 111.80628 | E9: 26.633444 | F9: 72.871599 | G9: 136.29978 | H9: 43.000538 | I9: 46.741129 | J9: 114.66599 | K9: 133.54887 | L9: 87.099833 | M9: 101.67741
A10: Corinne, UT | B10: 1316 | C10: 1288 | D10: 2418 | E10: 3874 | F10: 5312 | G10: 5469 | H10: 2460 | I10: 1367 | J10: 1391 | K10: 1964 | L10: 2217 | M10: 1738
A11: Paradise - Little Bear
A12: Cutler
A13: Little Bear - South Fork

Sheet RiversHeadFlow-2003
B1: t1 | C1: t2 | D1: t3 | E1: t4 | F1: t5 | G1: t6 | H1: t7 | I1: t8 | J1: t9 | K1: t10 | L1: t11 | M1: t12
A2: Bear | B2: 285.58602 | C2: 357.05804 | D2: 398.29167 | E2: 363.16806 | F2: 242.16263 | G2: 902.79444 | H2: 1025.5726 | I2: 896.60349 | J2: 428.0375 | K2: 215.32796 | L2: 285.52639 | M2: 295.18145
A3: Blacksmithfork | B3: 29.119691 | C3: 28.856339 | D3: 36.426855 | E3: 41.166889 | F3: 24.899328 | G3: 25.453694 | H3: 35.000551 | I3: 33.945054 | J3: 37.301611 | K3: 36.028401 | L3: 36.004222 | M3: 33.722245
A4: Malad | B4: 90.4 | C4: 44.1 | D4: 187 | E4: 424.1 | F4: 631.6 | G4: 509.7 | H4: 326.3 | I4: 207.3 | J4: 304.6 | K4: 467.4 | L4: 182 | M4: 16.5
A5: Little Bear - East Fork | B5: 4.8427166 | C5: 9.5702437 | D5: 26.748287 | E5: 95.116598 | F5: 32.545161 | G5: 12.806667 | H5: 5.4866667 | I5: 4.2741935 | J5: 3.7066667 | K5: 3.1661456 | L5: 3.6745285 | M5: 0.84011643
A6: Cub River | B6: 16.8 | C6: 18.5 | D6: 31.2 | E6: 81.2 | F6: 363.9 | G6: 418 | H6: 112.1 | I6: 54.8 | J6: 36.1 | K6: 28.2 | L6: 23.3 | M6: 17.2
A7: Logan River | B7: 0 | C7: 0 | D7: 0 | E7: 0 | F7: 0 | G7: 0 | H7: 0 | I7: 0 | J7: 0 | K7: 0 | L7: 0 | M7: 0
A8: SouthCache Gain To Cutler | B8: 723.01728 | C8: 578.80854 | D8: 794.6057 | E8: 823.38987 | F8: 742.12032 | G8: 247.97269 | H8: 0 | I8: 0 | J8: 234.17365 | K8: 185.04706 | L8: 303.57219 | M8: 390.35836
A9: Malad Reach Gain | B9: 121.28949 | C9: 83.42878 | D9: 79.451788 | E9: 71.099264 | F9: 91.516008 | G9: 116.80029 | H9: 82.226331 | I9: 66.450793 | J9: 122.46712 | K9: 129.04878 | L9: 84.599167 | M9: 74.252366
A10: Corinne, UT | B10: 1316 | C10: 1288 | D10: 2418 | E10: 3874 | F10: 5312 | G10: 5469 | H10: 2460 | I10: 1367 | J10: 1391 | K10: 1964 | L10: 2217 | M10: 1738
A11: Paradise - Little Bear | B11: 39.2 | C11: 34.6 | D11: 82.8 | E11: 367.4 | F11: 494 | G11: 202.9 | H11: 40.4 | I11: 32.3 | J11: 37.1 | K11: 48.7 | L11: 52.9 | M11: 61.7
A12: Cutler | B12: 1123 | C12: 1024 | D12: 2174 | E12: 3129 | F12: 5205 | G12: 3016 | H12: 126.7 | I12: 93 | J12: 243.4 | K12: 775.8 | L12: 979.8 | M12: 1213
A13: Little Bear - South Fork | B13: 17.920702 | C13: 19.03746 | D13: 51.460652 | E13: 82.711095 | F13: 120.50409 | G13: 69.678986 | H13: 26.251613 | I13: 23.845161 | J13: 21.925257 | K13: 16.347818 | L13: 17.266205 | M13: 15.710741

Sheet weights
D1: t1 | E1: t2 | F1: t3 | G1: t4 | H1: t5 | I1: t6 | J1: t7 | K1: t8 | L1: t9 | M1: t10 | N1: t11 | O1: t12
A2: riverine | B2: j4 | C2: j5 | D2: 1 | E2: 1 | F2: 1 | G2: 1 | H2: 1 | I2: 1 | J2: 1 | K2: 1 | L2: 1 | M2: 1 | N2: 1 | O2: 1
A3: floodplain | B3: j4 | C3: j5 | D3: 0 | E3: 0 | F3: 0 | G3: 0 | H3: 0 | I3: 0 | J3: 0 | K3: 0 | L3: 0 | M3: 0 | N3: 0 | O3: 0
A4: wetlands | B4: j4 | C4: j5 | D4: 0 | E4: 0 | F4: 0 | G4: 0 | H4: 0 | I4: 0 | J4: 0 | K4: 0 | L4: 0 | M4: 0 | N4: 0 | O4: 0
A5: riverine | B5: j6 | C5: j5 | D5: 1 | E5: 1 | F5: 1 | G5: 1 | H5: 1 | I5: 1 | J5: 1 | K5: 1 | L5: 1 | M5: 1 | N5: 1 | O5: 1
A6: floodplain | B6: j6 | C6: j5 | D6: 0 | E6: 0 | F6: 0 | G6: 0 | H6: 0 | I6: 0 | J6: 0 | K6: 0 | L6: 0 | M6: 0 | N6: 0 | O6: 0
A7: wetlands | B7: j6 | C7: j5 | D7: 0 | E7: 0 | F7: 0 | G7: 0 | H7: 0 | I7: 0 | J7: 0 | K7: 0 | L7: 0 | M7: 0 | N7: 0 | O7: 0
A8: riverine | B8: j5 | C8: j18 | D8: 1 | E8: 1 | F8: 1 | G8: 1 | H8: 1 | I8: 1 | J8: 1 | K8: 1 | L8: 1 | M8: 1 | N8: 1 | O8: 1
A9: floodplain | B9: j5 | C9: j18 | D9: 0 | E9: 0 | F9: 0 | G9: 0 | H9: 0 | I9: 0 | J9: 0 | K9: 0 | L9: 0 | M9: 0 | N9: 0 | O9: 0
A10: wetlands | B10: j5 | C10: j18 | D10: 0 | E10: 0 | F10: 0 | G10: 0 | H10: 0 | I10: 0 | J10: 0 | K10: 0 | L10: 0 | M10: 0 | N10: 0 | O10: 0
A11: riverine | B11: j21 | C11: j23 | D11: 1 | E11: 1 | F11: 1 | G11: 1 | H11: 1 | I11: 1 | J11: 1 | K11: 1 | L11: 1 | M11: 1 | N11: 1 | O11: 1
A12: floodplain | B12: j21 | C12: j23 | D12: 0 | E12: 0 | F12: 0 | G12: 0 | H12: 0 | I12: 0 | J12: 0 | K12: 0 | L12: 0 | M12: 0 | N12: 0 | O12: 0
A13: wetlands | B13: j21 | C13: j23 | D13: 0 | E13: 0 | F13: 0 | G13: 0 | H13: 0 | I13: 0 | J13: 0 | K13: 0 | L13: 0 | M13: 0 | N13: 0 | O13: 0
... A79: wetlands | B79: j45 | C79: j32 | D79: 0 | E79: 0 | F79: 0 | G79: 0 | H79: 0 | I79: 0 | J79: 0 | K79: 0 | L79: 0 | M79: 0 | N79: 0 | O79: 0

Sheet Budget
A1: 50000

Sheet InitD
A1: j37 | B1: j1 | C1: 7
A2: j1 | B2: j4 | C2: 7
A3: j4 | B3: j5 | C3: 7
A4: j6 | B4: j5 | C4: 7
A5: j5 | B5: j18 | C5: 7
A6: j18 | B6: j7 | C6: 7
A7: j7 | B7: j9 | C7: 7
A8: j9 | B8: j12 | C8: 7
A9: j12 | B9: j14 | C9: 7
A10: j14 | B10: j17 | C10: 7
A11: j17 | B11: j20 | C11: 7
A12: j19 | B12: j20 | C12: 7
... A26: j45 | B26: j32 | C26: 7

Sheet InitC
A1: j37 | B1: j1 | C1: 0 | J1: 0.5 | L1: Cmax | M1: 8.6592
A2: j1 | B2: j4 | C2: 0 | J2: 0.5 | M2: 0.470914
A3: j4 | B3: j5 | C3: 0 | J3: 2 | M3: 11.079797
A4: j6 | B4: j5 | C4: 0 | J4: 0.1 | M4: 1.049697
A5: j5 | B5: j18 | C5: 0 | J5: 0.3 | M5: 0.683126
A6: j18 | B6: j7 | C6: 0 | J6: 0.4 | M6: 4.456809
A7: j7 | B7: j9 | C7: 0 | J7: 0.15 | M7: 1.000458
A8: j9 | B8: j12 | C8: 0 | J8: 0.1 | M8: 1.541125
A9: j12 | B9: j14 | C9: 0 | J9: 0.1 | M9: 5.909368
A10: j14 | B10: j17 | C10: 0 | J10: 0.05 | M10: 0.740186
A11: j17 | B11: j20 | C11: 0 | J11: 0.2 | M11: 2.224502
A12: j19 | B12: j20 | C12: 0 | J12: 0.1 | M12: 0.477768
A13: j20 | B13: j21 | C13: 0 | J13: 0.1 | M13: 1.160083
... A26: j45 | B26: j32 | C26: 0 | J26: 0.1 | M26: 0.275284
C27: 0 | M27: 0.883165

Sheet UnitCost
A1: cottonwood | B1: 100

Sheet Runs
A1: s1
A2: s2
A3: s3
A4: s4
A5: s5
A6: s6
A7: s7
A8: s8
A9: s9
A10: s10
A11: s11
A12: s12
... A30: s30

Sheet DemandRuns
A1: s1 | B1: 0.1
A2: s2 | B2: 0.2
A3: s3 | B3: 0.3
A4: s4 | B4: 0.4
A5: s5 | B5: 0.5
A6: s6 | B6: 0.6
A7: s7 | B7: 0.7
A8: s8 | B8: 0.8
A9: s9 | B9: 0.9
A10: s10 | B10: 1
A11: s11 | B11: 1.1
A12: s12 | B12: 1.2
... A14: s14 | B14: 1.4

Sheet Qrun
A1: q1
A2: q2
A3: q3
A4: q4
A5: q5
A6: q6
A7: q7
A8: q8
A9: q9
A10: q10

Sheet QRunValues
A1: q1 | B1: 22.339835
A2: q2 | B2: 26.06314
A3: q3 | B3: 29.786446
A4: q4 | B4: 33.509752
A5: q5 | B5: 37.233058
A6: q6 | B6: 40.956363
A7: q7 | B7: 44.679669
A8: q8 | B8: 48.402975
A9: q9 | B9: 52.126281
A10: q10 | B10: 55.849586

Sheet WSI curves-Mm3
A1: Flow Rate at Corinne Station (ha-m)
B3: 1992 | C3: 1996 | D3: 1997 | E3: 2004 | F3: 2005 | G3: 2006 | H3: 2007 | I3: 2008 | J3: 2009 | K3: 2010 | L3: 2011
A4: January | B4: 5453.1723 | C4: 7541.1533 | D4: 20902.563 | E4: 6593.8637 | F4: 9404.6365 | G4: 13735.32 | H4: 9904.4718 | I4: 6433.0748 | J4: 7865.0065 | K4: 7386.4319 | L4: 9982.5177
A5: February | B5: 5520.7467 | C5: 9885.144 | D5: 12960.979 | E5: 7083.3256 | F5: 6960.0182 | G5: 10857.902 | H5: 10226.686 | I5: 7706.7131 | J5: 6458.5681 | K5: 6702.4427 | L5: 8821.3729
A6: March | B6: 7117.9447 | C6: 14031.111 | D6: 20204.8 | E6: 11846.808 | F6: 16928.346 | G6: 18960.961 | H6: 14312.467 | I6: 10140.322 | J6: 14539.265 | K6: 8850.9765 | L6: 18339.531
A7: April | B7: 4681.2777 | C7: 20433.799 | D7: 28191.89 | E7: 8051.6802 | F7: 22855.909 | G7: 36463.762 | H7: 10584.375 | I7: 9835.2338 | J7: 19215.405 | K7: 11339.878 | L7: 28431.655
A8: May | B8: 544.55879 | C8: 20250.306 | D8: 42222.267 | E8: 3070.9172 | F8: 44467.245 | G8: 29222.633 | H8: 3502.7622 | I8: 10777.41 | J8: 19529.79 | K8: 7445.5901 | L8: 40287.76
A9: June | B9: 569.5628 | C9: 18305.278 | D9: 36250.91 | E9: 3689.6806 | F9: 23788.054 | G9: 8815.0118 | H9: 787.55267 | I9: 8734.2748 | J9: 22239.372 | K9: 11890.357 | L9: 40143.412
A10: July | B10: 613.57669 | C10: 1932.5011 | D10: 10678.813 | E10: 326.12852 | F10: 1849.0729 | G10: 929.84552 | H10: 586.1995 | I10: 646.18954 | J10: 1894.5792 | K10: 923.01957 | L10: 18660.032
A11: August | B11: 418.65801 | C11: 992.03747 | D11: 11952.99 | E11: 354.19075 | F11: 1297.6882 | G11: 1131.5901 | H11: 573.47731 | I11: 648.46486 | J11: 1085.3254 | K11: 892.68203 | L11: 10367.119
A12: September | B12: 456.531 | C12: 3202.3228 | D12: 13637.212 | E12: 965.17407 | F12: 2180.6328 | G12: 4698.1591 | H12: 1101.9376 | I12: 1446.6601 | J12: 1909.0629 | K12: 1552.3522 | L12: 10209.56
A13: October | B13: 725.06714 | C13: 5337.1312 | D13: 18642.417 | E13: 4095.5675 | F13: 5883.9653 | G13: 8426.251 | H13: 3552.6723 | I13: 6012.8999 | J13: 7253.7051 | K13: 3926.4358 | L13: 14892.306
A14: November | B14: 4891.9279 | C14: 8014.9816 | D14: 20184.249 | E14: 5471.0323 | F14: 6392.168 | G14: 9519.6256 | H14: 4598.8281 | I14: 6594.7445 | J14: 7596.6172 | K14: 5610.4871 | L14: 16223.243
A15: December | B15: 4847.9384 | C15: 15775.519 | D15: 18088.757 | E15: 8009.1098 | F15: 9017.8329 | G15: 10724.319 | H15: 5535.1325 | I15: 6782.7149 | J15: 7353.0606 | K15: 10762.241 | L15: 9595.4694
A18: Flow Rate at Corinne Station (Mm3/month)
B20: 1992 | C20: 1996 | D20: 1997 | E20: 2004 | F20: 2005 | G20: 2006 | H20: 2007 | I20: 2008 | J20: 2009 | K20: 2010 | L20: 2011
A21: January | B21: =B4*10000/1000000 -> 54.531723 | C21: =C4*10000/1000000 -> 75.411533 | D21: =D4*10000/1000000 -> 209.02563 | E21: =E4*10000/1000000 -> 65.938637 | F21: =F4*10000/1000000 -> 94.046365 | G21: =G4*10000/1000000 -> 137.3532 | H21: =H4*10000/1000000 -> 99.044718 | I21: =I4*10000/1000000 -> 64.330748 | ... L21: =L4*10000/1000000 -> 99.825177
A22: February | B22: =B5*10000/1000000 -> 55.207467 | C22: =C5*10000/1000000 -> 98.85144 | D22: =D5*10000/1000000 -> 129.60979 | E22: =E5*10000/1000000 -> 70.833256 | F22: =F5*10000/1000000 -> 69.600182 | G22: =G5*10000/1000000 -> 108.57902 | H22: =H5*10000/1000000 -> 102.26686 | I22: =I5*10000/1000000 -> 77.067131 | ... L22: =L5*10000/1000000 -> 88.213729
A23: March | B23: =B6*10000/1000000 -> 71.179447 | C23: =C6*10000/1000000 -> 140.31111 | D23: =D6*10000/1000000 -> 202.048 | E23: =E6*10000/1000000 -> 118.46808 | F23: =F6*10000/1000000 -> 169.28346 | G23: =G6*10000/1000000 -> 189.60961 | H23: =H6*10000/1000000 -> 143.12467 | I23: =I6*10000/1000000 -> 101.40322 | ... L23: =L6*10000/1000000 -> 183.39531
A24: April | B24: =B7*10000/1000000 -> 46.812777 | C24: =C7*10000/1000000 -> 204.33799 | D24: =D7*10000/1000000 -> 281.9189 | E24: =E7*10000/1000000 -> 80.516802 | F24: =F7*10000/1000000 -> 228.55909 | G24: =G7*10000/1000000 -> 364.63762 | H24: =H7*10000/1000000 -> 105.84375 | I24: =I7*10000/1000000 -> 98.352338 | ... L24: =L7*10000/1000000 -> 284.31655
A25: May | B25: =B8*10000/1000000 -> 5.4455879 | C25: =C8*10000/1000000 -> 202.50306 | D25: =D8*10000/1000000 -> 422.22267 | E25: =E8*10000/1000000 -> 30.709172 | F25: =F8*10000/1000000 -> 444.67245 | G25: =G8*10000/1000000 -> 292.22633 | H25: =H8*10000/1000000 -> 35.027622 | I25: =I8*10000/1000000 -> 107.7741 | ... L25: =L8*10000/1000000 -> 402.8776
A26: June | B26: =B9*10000/1000000 -> 5.695628 | C26: =C9*10000/1000000 -> 183.05278 | D26: =D9*10000/1000000 -> 362.5091 | E26: =E9*10000/1000000 -> 36.896806 | F26: =F9*10000/1000000 -> 237.88054 | G26: =G9*10000/1000000 -> 88.150118 | H26: =H9*10000/1000000 -> 7.8755267 | I26: =I9*10000/1000000 -> 87.342748 | ... L26: =L9*10000/1000000 -> 401.43412
A27: July | B27: =B10*10000/1000000 -> 6.1357669 | C27: =C10*10000/1000000 -> 19.325011 | D27: =D10*10000/1000000 -> 106.78813 | E27: =E10*10000/1000000 -> 3.2612852 | F27: =F10*10000/1000000 -> 18.490729 | G27: =G10*10000/1000000 -> 9.2984552 | H27: =H10*10000/1000000 -> 5.861995 | I27: =I10*10000/1000000 -> 6.4618954 | ... L27: =L10*10000/1000000 -> 186.60032
A28: August | B28: =B11*10000/1000000 -> 4.1865801 | C28: =C11*10000/1000000 -> 9.9203747 | D28: =D11*10000/1000000 -> 119.5299 | E28: =E11*10000/1000000 -> 3.5419075 | F28: =F11*10000/1000000 -> 12.976882 | G28: =G11*10000/1000000 -> 11.315901 | H28: =H11*10000/1000000 -> 5.7347731 | I28: =I11*10000/1000000 -> 6.4846486 | ... L28: =L11*10000/1000000 -> 103.67119
A29: September | B29: =B12*10000/1000000 -> 4.56531 | C29: =C12*10000/1000000 -> 32.023228 | D29: =D12*10000/1000000 -> 136.37212 | E29: =E12*10000/1000000 -> 9.6517407 | F29: =F12*10000/1000000 -> 21.806328 | G29: =G12*10000/1000000 -> 46.981591 | H29: =H12*10000/1000000 -> 11.019376 | I29: =I12*10000/1000000 -> 14.466601 | ... L29: =L12*10000/1000000 -> 102.0956
A30: October | B30: =B13*10000/1000000 -> 7.2506714 | C30: =C13*10000/1000000 -> 53.371312 | D30: =D13*10000/1000000 -> 186.42417 | E30: =E13*10000/1000000 -> 40.955675 | F30: =F13*10000/1000000 -> 58.839653 | G30: =G13*10000/1000000 -> 84.26251 | H30: =H13*10000/1000000 -> 35.526723 | I30: =I13*10000/1000000 -> 60.128999 | ... L30: =L13*10000/1000000 -> 148.92306
A31: November | B31: =B14*10000/1000000 -> 48.919279 | C31: =C14*10000/1000000 -> 80.149816 | D31: =D14*10000/1000000 -> 201.84249 | E31: =E14*10000/1000000 -> 54.710323 | F31: =F14*10000/1000000 -> 63.92168 | G31: =G14*10000/1000000 -> 95.196256 | H31: =H14*10000/1000000 -> 45.988281 | I31: =I14*10000/1000000 -> 65.947445 | ... L31: =L14*10000/1000000 -> 162.23243
A32: December | B32: =B15*10000/1000000 -> 48.479384 | C32: =C15*10000/1000000 -> 157.75519 | D32: =D15*10000/1000000 -> 180.88757 | E32: =E15*10000/1000000 -> 80.091098 | F32: =F15*10000/1000000 -> 90.178329 | G32: =G15*10000/1000000 -> 107.24319 | H32: =H15*10000/1000000 -> 55.351325 | I32: =I15*10000/1000000 -> 67.827149 | ... L32: =L15*10000/1000000 -> 95.954694
A36: WU (Mm2)
B37: 1992 | C37: 1996 | D37: 1997 | E37: 2004 | F37: 2005 | G37: 2006 | H37: 2007 | I37: 2008 | J37: 2009 | K37: 2010 | L37: 2011
A38: January | B38: 66.945282 | C38: 73.610179 | D38: 82.499512 | E38: 71.348109 | F38: 76.619963 | G38: 79.994103 | H38: 77.201108 | I38: 70.037742 | J38: 74.251306 | K38: 73.281973 | L38: 77.28532
A39: February | B39: 78.134914 | C39: 81.427389 | D39: 84.861491 | E39: 79.897231 | F39: 81.04765 | G39: 83.323611 | H39: 82.243755 | I39: 80.13118 | J39: 80.206964 | K39: 80.096943 | L39: 81.864287
A40: March | B40: 57.715547 | C40: 59.689718 | D40: 60.457701 | E40: 59.016295 | F40: 59.859423 | G40: 60.492137 | H40: 60.001055 | I40: 58.797968 | J40: 59.40043 | K40: 58.584031 | L40: 60.17401
A41: April | B41: 14.728418 | C41: 14.559622 | D41: 15.261489 | E41: 13.588961 | F41: 13.915883 | G41: 14.724703 | H41: 15.193432 | I41: 14.903173 | J41: 13.140958 | K41: 14.238984 | L41: 15.202112
A42: May | B42: 6.2786477 | C42: 6.2565701 | D42: 6.5181641 | E42: 4.2874801 | F42: 6.4276178 | G42: 6.4106364 | H42: 6.4495972 | I42: 5.5960916 | J42: 4.1338123 | K42: 6.1606396 | L42: 6.315752
A43: June | B43: 6.4693992 | C43: 4.5143328 | D43: 6.5834021 | E43: 3.3837203 | F43: 6.476115 | G43: 5.8525285 | H43: 2.8157617 | I43: 4.3978294 | J43: 4.417382 | K43: 6.1269579 | L43: 6.6361617
A44: July | B44: 5.9266844 | C44: 4.7894073 | D44: 7.4595108 | E44: 4.1283579 | F44: 6.9694746 | G44: 7.4324006 | H44: 3.3050529 | I44: 4.9258315 | J44: 4.8303799 | K44: 5.8689375 | L44: 7.5875646
A45: August | B45: 4.0588661 | C45: 4.6303849 | D45: 7.0751085 | E45: 2.7174623 | F45: 4.5901063 | G45: 7.4761622 | H45: 2.7938137 | I45: 3.4502642 | J45: 6.1346549 | K45: 5.8690135 | L45: 7.5490838
A46: September | B46: 3.5608207 | C46: 8.7625813 | D46: 10.48625 | E46: 4.505775 | F46: 7.1216897 | G46: 10.397278 | H46: 4.1452987 | I46: 5.7422789 | J46: 8.5942939 | K46: 6.1151008 | L46: 6.9915833
A47: October | B47: 6.2566211 | C47: 12.708515 | D47: 16.433063 | E47: 11.07023 | F47: 11.660931 | G47: 16.289537 | H47: 10.918633 | I47: 11.649015 | J47: 15.322089 | K47: 13.56717 | L47: 15.138826
A48: November | B48: 80.730163 | C48: 95.998506 | D48: 101.21841 | E48: 89.951792 | F48: 94.809356 | G48: 101.21889 | H48: 88.652548 | I48: 93.926383 | J48: 97.27719 | K48: 91.799692 | L48: 101.19917
A49: December | B49: 91.208518 | C49: 100.06235 | D49: 101.21839 | E49: 95.78183 | F49: 98.00155 | G49: 101.21887 | H49: 94.159525 | I49: 96.80669 | J49: 99.176173 | K49: 97.310895 | L49: 101.22266
A52: WSI = WU (Mm2) / AW(Mm2)
B53: 1992 | C53: 1996 | D53: 1997 | E53: 2004 | F53: 2005 | G53: 2006 | H53: 2007 | I53: 2008 | J53: 2009 | K53: 2010 | L53: 2011
A54: January | B54: =B38/aw!$D$1 -> 0.56541623 | C54: =C38/aw!$D$1 -> 0.6217076 | D54: =D38/aw!$D$1 -> 0.69678642 | E54: =E38/aw!$D$1 -> 0.60260227 | F54: =F38/aw!$D$1 -> 0.64712807 | G54: =G38/aw!$D$1 -> 0.67562587 | H54: =H38/aw!$D$1 -> 0.65203639 | I54: =I38/aw!$D$1 -> 0.59153498 | ... L54: =L38/aw!$D$1 -> 0.65274763
A55: February | B55: =B39/aw!$D$1 -> 0.65992326 | C55: =C39/aw!$D$1 -> 0.68773132 | D55: =D39/aw!$D$1 -> 0.71673557 | E55: =E39/aw!$D$1 -> 0.67480769 | F55: =F39/aw!$D$1 -> 0.68452407 | G55: =G39/aw!$D$1 -> 0.70374672 | H55: =H39/aw!$D$1 -> 0.69462631 | I55: =I39/aw!$D$1 -> 0.67678362 | ... L55: =L39/aw!$D$1 -> 0.69142134
A56: March | B56: =B40/aw!$D$1 -> 0.48746239 | C56: =C40/aw!$D$1 -> 0.50413613 | D56: =D40/aw!$D$1 -> 0.51062248 | E56: =E40/aw!$D$1 -> 0.49844843 | F56: =F40/aw!$D$1 -> 0.50556945 | G56: =G40/aw!$D$1 -> 0.51091332 | H56: =H40/aw!$D$1 -> 0.50676566 | I56: =I40/aw!$D$1 -> 0.49660446 | ... L56: =L40/aw!$D$1 -> 0.50822644
A57: April | B57: =B41/aw!$D$1 -> 0.12439543 | C57: =C41/aw!$D$1 -> 0.12296978 | D57: =D41/aw!$D$1 -> 0.12889771 | E57: =E41/aw!$D$1 -> 0.11477163 | F57: =F41/aw!$D$1 -> 0.1175328 | G57: =G41/aw!$D$1 -> 0.12436405 | H57: =H41/aw!$D$1 -> 0.12832291 | I57: =I41/aw!$D$1 -> 0.1258714 | ... L57: =L41/aw!$D$1 -> 0.12839622
A58: May | B58: =B42/aw!$D$1 -> 0.053029119 | C58: =C42/aw!$D$1 -> 0.052842653 | D58: =D42/aw!$D$1 -> 0.055052062 | E58: =E42/aw!$D$1 -> 0.036211825 | F58: =F42/aw!$D$1 -> 0.054287313 | G58: =G42/aw!$D$1 -> 0.054143888 | H58: =H42/aw!$D$1 -> 0.054472949 | I58: =I42/aw!$D$1 -> 0.047264287 | ... L58: =L42/aw!$D$1 -> 0.0533425
A59: June | B59: =B43/aw!$D$1 -> 0.054640196 | C59: =C43/aw!$D$1 -> 0.038127811 | D59: =D43/aw!$D$1 -> 0.055603059 | E59: =E43/aw!$D$1 -> 0.028578719 | F59: =F43/aw!$D$1 -> 0.054696917 | G59: =G43/aw!$D$1 -> 0.04943014 | H59: =H43/aw!$D$1 -> 0.023781771 | I59: =I43/aw!$D$1 -> 0.03714383 | ... L59: =L43/aw!$D$1 -> 0.056048663
A60: July | B60: =B44/aw!$D$1 -> 0.050056456 | C60: =C44/aw!$D$1 -> 0.040451075 | D60: =D44/aw!$D$1 -> 0.063002625 | E60: =E44/aw!$D$1 -> 0.034867888 | F60: =F44/aw!$D$1 -> 0.058863806 | G60: =G44/aw!$D$1 -> 0.062773654 | H60: =H44/aw!$D$1 -> 0.027914298 | I60: =I44/aw!$D$1 -> 0.041603307 | ... L60: =L44/aw!$D$1 -> 0.064084161
A61: August | B61: =B45/aw!$D$1 -> 0.034280964 | C61: =C45/aw!$D$1 -> 0.039107981 | D61: =D45/aw!$D$1 -> 0.059755984 | E61: =E45/aw!$D$1 -> 0.02295154 | F61: =F45/aw!$D$1 -> 0.03876779 | G61: =G45/aw!$D$1 -> 0.063143262 | H61: =H45/aw!$D$1 -> 0.0235964 | I61: =I45/aw!$D$1 -> 0.029140745 | ... L61: =L45/aw!$D$1 -> 0.063759154
A62: September | B62: =B46/aw!$D$1 -> 0.030074499 | C62: =C46/aw!$D$1 -> 0.074008288 | D62: =D46/aw!$D$1 -> 0.088566304 | E62: =E46/aw!$D$1 -> 0.038055532 | F62: =F46/aw!$D$1 -> 0.060149407 | G62: =G46/aw!$D$1 -> 0.08781485 | H62: =H46/aw!$D$1 -> 0.035010969 | I62: =I46/aw!$D$1 -> 0.048498977 | ... L62: =L46/aw!$D$1 -> 0.059050535
A63: October | B63: =B47/aw!$D$1 -> 0.052843083 | C63: =C47/aw!$D$1 -> 0.10733543 | D63: =D47/aw!$D$1 -> 0.13879276 | E63: =E47/aw!$D$1 -> 0.093498568 | F63: =F47/aw!$D$1 -> 0.098487593 | G63: =G47/aw!$D$1 -> 0.13758055 | H63: =H47/aw!$D$1 -> 0.092218184 | I63: =I47/aw!$D$1 -> 0.098386952 | ... L63: =L47/aw!$D$1 -> 0.1278617
A64: November | B64: =B48/aw!$D$1 -> 0.68184259 | C64: =C48/aw!$D$1 -> 0.81079819 | D64: =D48/aw!$D$1 -> 0.85488519 | E64: =E48/aw!$D$1 -> 0.75972798 | F64: =F48/aw!$D$1 -> 0.8007547 | G64: =G48/aw!$D$1 -> 0.85488928 | H64: =H48/aw!$D$1 -> 0.74875463 | I64: =I48/aw!$D$1 -> 0.79329716 | ... L64: =L48/aw!$D$1 -> 0.85472274
A65: December | B65: =B49/aw!$D$1 -> 0.77034221 | C65: =C49/aw!$D$1 -> 0.84512117 | D65: =D49/aw!$D$1 -> 0.85488504 | E65: =E49/aw!$D$1 -> 0.80896816 | F65: =F49/aw!$D$1 -> 0.82771579 | G65: =G49/aw!$D$1 -> 0.85488914 | H65: =H49/aw!$D$1 -> 0.79526626 | I65: =I49/aw!$D$1 -> 0.81762407 | ... L65: =L49/aw!$D$1 -> 0.85492108
A74: Old WSI
B75: 1992 | C75: 1996 | D75: 1997 | E75: 2004 | F75: 2005 | G75: 2006 | H75: 2007 | I75: 2008 | J75: 2009 | K75: 2010 | L75: 2011
A76: January | B76: 0.56541623 | C76: 0.6217076 | D76: 0.69678642 | E76: 0.60260227 | F76: 0.64712807 | G76: 0.67562587 | H76: 0.65203639 | I76: 0.59153498 | J76: 0.62712252 | K76: 0.61893559 | L76: 0.65274763
A77: February | B77: 0.65992326 | C77: 0.68773132 | D77: 0.71673557 | E77: 0.67480769 | F77: 0.68452407 | G77: 0.70374672 | H77: 0.69462631 | I77: 0.67678362 | J77: 0.67742368 | K77: 0.67649445 | L77: 0.69142134
A78: March | B78: 0.48746239 | C78: 0.50413613 | D78: 0.51062248 | E78: 0.49844843 | F78: 0.50556945 | G78: 0.51091332 | H78: 0.50676566 | I78: 0.49660446 | J78: 0.50169282 | K78: 0.49479756 | L78: 0.50822644
A79: April | B79: 0.12439543 | C79: 0.12296978 | D79: 0.12889771 | E79: 0.11477163 | F79: 0.1175328 | G79: 0.12436405 | H79: 0.12832291 | I79: 0.1258714 | J79: 0.11098782 | K79: 0.12026169 | L79: 0.12839622
A80: May | B80: 0.053029119 | C80: 0.052842653 | D80: 0.055052062 | E80: 0.036211825 | F80: 0.054287313 | G80: 0.054143888 | H80: 0.054472949 | I80: 0.047264287 | J80: 0.034913955 | K80: 0.052032429 | L80: 0.0533425
A81: June | B81: 0.054640196 | C81: 0.038127811 | D81: 0.055603059 | E81: 0.028578719 | F81: 0.054696917 | G81: 0.04943014 | H81: 0.023781771 | I81: 0.03714383 | J81: 0.03730897 | K81: 0.051747955 | L81: 0.056048663
A82: July | B82: 0.050056456 | C82: 0.040451075 | D82: 0.063002625 | E82: 0.034867888 | F82: 0.058863806 | G82: 0.062773654 | H82: 0.027914298 | I82: 0.041603307 | J82: 0.040797128 | K82: 0.049568729 | L82: 0.064084161
A83: August | B83: 0.034280964 | C83: 0.039107981 | D83: 0.059755984 | E83: 0.02295154 | F83: 0.03876779 | G83: 0.063143262 | H83: 0.0235964 | I83: 0.029140745 | J83: 0.051812964 | K83: 0.049569371 | L83: 0.063759154
A84: September | B84: 0.030074499 | C84: 0.074008288 | D84: 0.088566304 | E84: 0.038055532 | F84: 0.060149407 | G84: 0.08781485 | H84: 0.035010969 | I84: 0.048498977 | J84: 0.072586941 | K84: 0.051647811 | L84: 0.059050535
A85: October | B85: 0.052843083 | C85: 0.10733543 | D85: 0.13879276 | E85: 0.093498568 | F85: 0.098487593 | G85: 0.13758055 | H85: 0.092218184 | I85: 0.098386952 | J85: 0.12940953 | K85: 0.11458758 | L85: 0.1278617
A86: November | B86: 0.68184259 | C86: 0.81079819 | D86: 0.85488519 | E86: 0.75972798 | F86: 0.8007547 | G86: 0.85488928 | H86: 0.74875463 | I86: 0.79329716 | J86: 0.82159789 | K86: 0.77533524 | L86: 0.85472274
A87: December | B87: 0.77034221 | C87: 0.84512117 | D87: 0.85488504 | E87: 0.80896816 | F87: 0.82771579 | G87: 0.85488914 | H87: 0.79526626 | I87: 0.81762407 | J87: 0.83763659 | K87: 0.82188256 | L87: 0.85492108

Sheet Stage-Flow
D5: Date | E5: Flow (ha-m/month) | F5: Flow (m3/month) | G5: Stage (m) | H5: Width (m) | I5: Bank Full (m) | J5: Stage (ft) | K5: Flow (cfs) | L5: Width (ft) | N5: Flow (Mm3/month)
C6: Cub | D6: 41137 | E6: 36.060186 | F6: 360601.86 | G6: =0.3048*J6 -> 4.16052 | H6: =0.3048*J28 -> 13.444728 | I6: =0.3048*K28 -> 4.492752 | J6: 13.65 | K6: 4.8425 | N6: =F6/1000000 -> 0.36060186 | Q6: Flow (m3) | R6: Stage (m) | S6: Width (m)
D7: 41230 | E7: 180.77379 | F7: 1807737.9 | G7: =0.3048*J7 -> 3.83667 | H7: =0.3048*J29 -> 12.3444 | I7: =0.3048*K29 -> 4.456176 | J7: 12.5875 | K7: 24.276 | N7: =F7/1000000 -> 1.8077379 | Q7: 57440674 | R7: =0.00000001*Q7+3.2147 -> 3.7891067 | S7: =0.00000000000004*Q7^2-0.000004*Q7+111.54 -> 13.754545
D8: 41401 | E8: 1088.7235 | F8: 10887235 | G8: =0.3048*J8 -> 4.006596 | H8: =0.3048*J30 -> 14.353032 | I8: =0.3048*K30 -> 4.572 | J8: 13.145 | K8: 146.204 | N8: =F8/1000000 -> 10.887235 | Q8: 33629372 | R8: =0.00000001*Q8+3.2147 -> 3.5509937 | S8: =0.00000000000004*Q8^2-0.000004*Q8+111.54 -> 22.259898
D9: 41501 | E9: 22.518534 | F9: 225185.34 | G9: =0.3048*J9 -> 4.2655067 | H9: =0.3048*J31 -> 14.426184 | I9: =0.3048*K31 -> 4.108704 | J9: 13.994444 | K9: 3.024 | N9: =F9/1000000 -> 0.22518534 | Q9: 42310066 | R9: =0.00000001*Q9+3.2147 -> 3.6378007 | S9: =0.00000000000004*Q9^2-0.000004*Q9+111.54 -> 13.905403
D10: 41594 | E10: 219.53978 | F10: 2195397.8 | G10: =0.3048*J10 -> 3.790188 | H10: =0.3048*J32 -> 11.131296 | I10: =0.3048*K32 -> 3.420112 | J10: 12.435 | K10: 29.481861 | N10: =F10/1000000 -> 2.1953978 | Q10: 62645907 | R10: =0.00000001*Q10+3.2147 -> 3.8411591 | S10: =0.00000000000004*Q10^2-0.000004*Q10+111.54 -> 17.936759
D11: 41764 | E11: 2035.8274 | F11: 20358274 | G11: =0.3048*J11 -> 7.2702197 | H11: =0.3048*J33 -> 17.907 | I11: =0.3048*K33 -> 4.77012 | J11: 23.852427 | K11: 273.39 | N11: =F11/1000000 -> 20.358274 | Q11: 28729951 | R11: =0.00000001*Q11+3.2147 -> 3.5019995 | S11: =0.00000000000004*Q11^2-0.000004*Q11+111.54 -> 29.636599
C13: Confluence | D13: 41137 | E13: 5744.0674 | F13: 57440674 | G13: =0.3048*J13 -> 3.975354 | H13: =0.3048*J34 -> 44.37888 | I13: =0.3048*K34 -> 3.8727888 | J13: 13.0425 | K13: 771.36725 | N13: =F13/1000000 -> 57.440674
D14: 41230 | E14: 3362.9372 | F14: 33629372 | G14: =0.3048*J14 -> 3.664458 | H14: =0.3048*J35 -> 32.12592 | I14: =0.3048*K35 -> 3.938016 | J14: 12.0225 | K14: 451.60675 | N14: =F14/1000000 -> 33.629372
D15: 41401 | E15: 4231.0066 | F15: 42310066 | G15: =0.3048*J15 -> 3.832098 | H15: =0.3048*J36 -> 35.32632 | I15: =0.3048*K36 -> 4.288536 | J15: 12.5725 | K15: 568.17925 | N15: =F15/1000000 -> 42.310066 | Q15: Flow (Mm3/month) | R15: Stage (m) | S15: Width (m)
D16: 41501 | E16: 6264.5907 | F16: 62645907 | G16: =0.3048*J16 -> 4.1013888 | H16: =0.3048*J37 -> 35.000184 | I16: =0.3048*K37 -> 3.770376 | J16: 13.456 | K16: 841.268 | N16: =F16/1000000 -> 62.645907 | Q16: 57.440674 | R16: =0.0138*Q16+3.2147 -> 4.0073813 | S16: =0.0411*Q16^2-3.6309*Q16+111.54 -> 38.585272
D17: 41594 | E17: 2872.9951 | F17: 28729951 | G17: =0.3048*J17 -> 3.612642 | H17: =0.3048*J38 -> 42.15384 | I17: =0.3048*K38 -> 3.90792 | J17: 11.8525 | K17: 385.81273 | N17: =F17/1000000 -> 28.729951 | Q17: 33.629372 | R17: =0.0138*Q17+3.2147 -> 3.6787853 | S17: =0.0411*Q17^2-3.6309*Q17+111.54 -> 35.916528
D18: 41764 | E18: 7180.0168 | F18: 71800168 | H18: =0.3048*J39 -> 66.226944 | I18: =0.3048*K39 -> 3.895344 | K18: 964.2 | N18: =F18/1000000 -> 71.800168 | Q18: 42.310066 | R18: =0.0138*Q18+3.2147 -> 3.7985789 | S18: =0.0411*Q18^2-3.6309*Q18+111.54 -> 31.491205
Q19: 62.645907 | R19: =0.0138*Q19+3.2147 -> 4.0792135 | S19: =0.0411*Q19^2-3.6309*Q19+111.54 -> 45.376324
C20: Morton | D20: 41500 | E20: 6364.176 | F20: 63641760 | G20: =J20*0.3048 -> 4.539996 | H20: =0.3048*J40 -> 36.950904 | I20: =0.3048*K40 -> 3.203448 | J20: 14.895 | K20: 854.64125 | N20: =F20/1000000 -> 63.64176 | Q20: 28.729951 | R20: =0.0138*Q20+3.2147 -> 3.6111733 | S20: =0.0411*Q20^2-3.6309*Q20+111.54 -> 41.148775
D21: 41594 | E21: 2402.7969 | F21: 24027969 | G21: =J21*0.3048 -> 4.0663368 | H21: =0.3048*J41 -> 34.521648 | I21: =0.3048*K41 -> 2.493264 | J21: 13.341 | K21: 322.67011 | N21: =F21/1000000 -> 24.027969
D22: 41764 | E22: 5164.8909 | F22: 51648909 | H22: =0.3048*J42 -> 63.15456 | I22: =0.3048*K42 -> 3.666744 | K22: 693.59 | N22: =F22/1000000 -> 51.648909
K24: Depth+WSL-BM
A26: Location | B26: Date | C26: Flow (ft^3/s) | D26: Processed Flow (ft^3/s) | E26: Stage (ft) | F26: StdDev (Flow-ft^3/s) | G26: Processed StdDev (Flow-ft^3/s) | H26: StdDev (Stage - ft) | I26: Max Depth (ft) | J26: Width (ft) | K26: Bankfull(ft)
C27: (avg, good) | E27: (average)
A28: Cub | B28: ='[1]Table of Transects'!B3 -> 41137 | C28: =AVERAGEIFS('[1]Table of Transects'!$E$3:$E$70,'[1]Table of Transects'!$A$3:$A$70,'Stage-Flow'!A28,'[1]Table of Transects'!$B$3:$B$70,'Stage-Flow'!B28,'[1]Table of Transects'!$J$3:$J$70,"Yes") -> #VALUE! | D28: =AVERAGEIFS('[1]Table of Transects'!$G$3:$G$53,'[1]Table of Transects'!$A$3:$A$53,'Stage-Flow'!A28,'[1]Table of Transects'!$B$3:$B$53,'Stage-Flow'!B28,'[1]Table of Transects'!$J$3:$J$53,"Yes") -> #VALUE! | E28: =AVERAGEIFS('[1]Table of Stages'!$H$3:$H$65,'[1]Table of Stages'!$A$3:$A$65,'Stage-Flow'!A28,'[1]Table of Stages'!$B$3:$B$65,'Stage-Flow'!B28) -> #VALUE! | F28: =_xlfn.STDEV.S('[1]Table of Transects'!E3:E6) -> 1.2760834 | G28: ='[1]Transect Cub 8-16'!E77 -> 0.674 | H28: =_xlfn.STDEV.S('[1]Table of Stages'!H3:H6) -> 0.088317609 | I28: 8 | J28: 44.11 | K28: =I28+10.71-3.97 -> 14.74
A29: =A28 -> Cub | B29: ='[1]Table of Transects'!B12 -> 41230 | C29: =AVERAGEIFS('[1]Table of Transects'!$E$3:$E$70,'[1]Table of Transects'!$A$3:$A$70,'Stage-Flow'!A29,'[1]Table of Transects'!$B$3:$B$70,'Stage-Flow'!B29,'[1]Table of Transects'!$J$3:$J$70,"Yes") -> #VALUE! | D29: =AVERAGEIFS('[1]Table of Transects'!$G$3:$G$53,'[1]Table of Transects'!$A$3:$A$53,'Stage-Flow'!A29,'[1]Table of Transects'!$B$3:$B$53,'Stage-Flow'!B29,'[1]Table of Transects'!$J$3:$J$53,"Yes") -> #VALUE! | E29: =AVERAGEIFS('[1]Table of Stages'!$H$3:$H$65,'[1]Table of Stages'!$A$3:$A$65,'Stage-Flow'!A29,'[1]Table of Stages'!$B$3:$B$65,'Stage-Flow'!B29) -> #VALUE! | F29: =_xlfn.STDEV.S('[1]Table of Transects'!E12:E18) -> 2.0213978 | G29: ='[1]Transect 11-17 Cub '!E52 -> 2.038 | H29: =_xlfn.STDEV.S('[1]Table of Stages'!H11:H14) -> 0.018929694 | I29: 6.8 | J29: 40.5 | K29: =I29+11.91-4.09 -> 14.62
A30: =A29 -> Cub | B30: ='[1]Table of Transects'!B24 -> 41401 | C30: =AVERAGEIFS('[1]Table of Transects'!$E$3:$E$70,'[1]Table of Transects'!$A$3:$A$70,'Stage-Flow'!A30,'[1]Table of Transects'!$B$3:$B$70,'Stage-Flow'!B30,'[1]Table of Transects'!$J$3:$J$70,"Yes") -> #VALUE! | D30: =AVERAGEIFS('[1]Table of Transects'!$G$3:$G$53,'[1]Table of Transects'!$A$3:$A$53,'Stage-Flow'!A30,'[1]Table of Transects'!$B$3:$B$53,'Stage-Flow'!B30,'[1]Table of Transects'!$J$3:$J$53,"Yes") -> #VALUE! | E30: =AVERAGEIFS('[1]Table of Stages'!$H$3:$H$65,'[1]Table of Stages'!$A$3:$A$65,'Stage-Flow'!A30,'[1]Table of Stages'!$B$3:$B$65,'Stage-Flow'!B30) -> #VALUE! | F30: =_xlfn.STDEV.S('[1]Table of Transects'!E24:E27) -> 2.9512402 | G30: ='[1]Transect 5-7-13 Cub'!E48 -> 3.624 | H30: =_xlfn.STDEV.S('[1]Table of Stages'!H19:H22) -> 0.064549722 | I30: 7.8 | J30: 47.09 | K30: =I30+11.59-4.39 -> 15
A31: Cub | B31: ='[1]Table of Transects'!B45 -> 41501 | C31: =AVERAGEIFS('[1]Table of Transects'!$E$3:$E$70,'[1]Table of Transects'!$A$3:$A$70,'Stage-Flow'!A31,'[1]Table of Transects'!$B$3:$B$70,'Stage-Flow'!B31,'[1]Table of Transects'!$J$3:$J$70,"Yes") -> #VALUE! | D31: =AVERAGEIFS('[1]Table of Transects'!$G$3:$G$53,'[1]Table of Transects'!$A$3:$A$53,'Stage-Flow'!A31,'[1]Table of Transects'!$B$3:$B$53,'Stage-Flow'!B31,'[1]Table of Transects'!$J$3:$J$53,"Yes") -> #VALUE! | E31: =AVERAGEIFS('[1]Table of Stages'!$H$3:$H$65,'[1]Table of Stages'!$A$3:$A$65,'Stage-Flow'!A31,'[1]Table of Stages'!$B$3:$B$65,'Stage-Flow'!B31) -> #VALUE! | F31: =_xlfn.STDEV.S('[1]Table of Transects'!E45:E53) -> 3.2553565 | G31: ='[1]Table of Transects'!K47 -> 3.618 | H31: =_xlfn.STDEV.S('[1]Table of Stages'!H40:H48) -> 0.089597867 | I31: 7.1 | J31: 47.33 | K31: =I31+10.68-4.3 -> 13.48
A32: Cub | B32: ='[1]Table of Transects'!B63 -> 41594 | C32: =AVERAGEIFS('[1]Table of Transects'!$E$3:$E$70,'[1]Table of Transects'!$A$3:$A$70,'Stage-Flow'!A32,'[1]Table of Transects'!$B$3:$B$70,'Stage-Flow'!B32,'[1]Table of Transects'!$J$3:$J$70,"Yes") -> #VALUE! | E32: =AVERAGEIFS('[1]Table of Stages'!$H$3:$H$65,'[1]Table of Stages'!$A$3:$A$65,'Stage-Flow'!A32,'[1]Table of Stages'!$B$3:$B$65,'Stage-Flow'!B32) -> #VALUE! | F32: ='[1]Table of Transects'!K64 -> 1.5421502 | H32: =_xlfn.STDEV.S('[1]Table of Stages'!H58:H65) -> 0.037416574 | I32: =1*3.28084 -> 3.28084 | J32: 36.52 | K32: =I32+12.19-4.25 -> 11.22084
A33: Cub | B33: 41764 | D33: 273.39 | E33: 23.852427 | I33: 10.3 | J33: 58.75 | K33: =I33+10.05-4.7 -> 15.65
A34: Confluence | B34: ='[1]Table of Transects'!B8 -> 41137 | C34: =AVERAGEIFS('[1]Table of Transects'!$E$3:$E$70,'[1]Table of Transects'!$A$3:$A$70,'Stage-Flow'!A34,'[1]Table of Transects'!$B$3:$B$70,'Stage-Flow'!B34,'[1]Table of Transects'!$J$3:$J$70,"Yes") -> #VALUE! | D34: =AVERAGEIFS('[1]Table of Transects'!$G$3:$G$53,'[1]Table of Transects'!$A$3:$A$53,'Stage-Flow'!A34,'[1]Table of Transects'!$B$3:$B$53,'Stage-Flow'!B34,'[1]Table of Transects'!$J$3:$J$53,"Yes") -> #VALUE! | E34: =AVERAGEIFS('[1]Table of Stages'!$H$3:$H$65,'[1]Table of Stages'!$A$3:$A$65,'Stage-Flow'!A34,'[1]Table of Stages'!$B$3:$B$65,'Stage-Flow'!B34) -> #VALUE! | F34: =_xlfn.STDEV.S('[1]Table of Transects'!E8:E11) -> 20.855805 | G34: ='[1]Transect Confluence 8-16'!H60 -> 21.808 | H34: =_xlfn.STDEV.S('[1]Table of Stages'!H7:H10) -> 0.064355782 | I34: 6.556 | J34: 145.6 | K34: =I34+11.22-5.07 -> 12.706
A35: =A34 -> Confluence | B35: ='[1]Table of Transects'!B19 -> 41230 | C35: =AVERAGEIFS('[1]Table of Transects'!$E$3:$E$70,'[1]Table of Transects'!$A$3:$A$70,'Stage-Flow'!A35,'[1]Table of Transects'!$B$3:$B$70,'Stage-Flow'!B35,'[1]Table of Transects'!$J$3:$J$70,"Yes") -> #VALUE! | D35: =AVERAGEIFS('[1]Table of Transects'!$G$3:$G$53,'[1]Table of Transects'!$A$3:$A$53,'Stage-Flow'!A35,'[1]Table of Transects'!$B$3:$B$53,'Stage-Flow'!B35,'[1]Table of Transects'!$J$3:$J$53,"Yes") -> #VALUE! | E35: =AVERAGEIFS('[1]Table of Stages'!$H$3:$H$65,'[1]Table of Stages'!$A$3:$A$65,'Stage-Flow'!A35,'[1]Table of Stages'!$B$3:$B$65,'Stage-Flow'!B35) -> #VALUE! | F35: =_xlfn.STDEV.S('[1]Table of Transects'!E19:E23) -> 12.270428 | G35: ='[1]Transect 11-17 Confluence'!F47 -> 15.044 | H35: =_xlfn.STDEV.S('[1]Table of Stages'!H15:H18) -> 0.056199051 | I35: 5.2 | J35: 105.4 | K35: =I35+12.02-4.3 -> 12.92
A36: =A35 -> Confluence | B36: ='[1]Table of Transects'!B28 -> 41401 | C36: =AVERAGEIFS('[1]Table of Transects'!$E$3:$E$70,'[1]Table of Transects'!$A$3:$A$70,'Stage-Flow'!A36,'[1]Table of Transects'!$B$3:$B$70,'Stage-Flow'!B36,'[1]Table of Transects'!$J$3:$J$70,"Yes") -> #VALUE! | D36: =AVERAGEIFS('[1]Table of Transects'!$G$3:$G$53,'[1]Table of Transects'!$A$3:$A$53,'Stage-Flow'!A36,'[1]Table of Transects'!$B$3:$B$53,'Stage-Flow'!B36,'[1]Table of Transects'!$J$3:$J$53,"Yes") -> #VALUE! | E36: =AVERAGEIFS('[1]Table of Stages'!$H$3:$H$65,'[1]Table of Stages'!$A$3:$A$65,'Stage-Flow'!A36,'[1]Table of Stages'!$B$3:$B$65,'Stage-Flow'!B36) -> #VALUE! | F36: =_xlfn.STDEV.S('[1]Table of Transects'!E28:E31) -> 10.415672 | G36: ='[1]Transect 5-7-13 Confluence'!F46 -> 11.33 | H36: =_xlfn.STDEV.S('[1]Table of Stages'!H23:H26) -> 0.022173558 | I36: 6.9 | J36: 115.9 | K36: =I36+11.71-4.54 -> 14.07
A37: =A36 -> Confluence | B37: ='[1]Table of Transects'!B40 -> 41501 | C37: =AVERAGEIFS('[1]Table of Transects'!$E$3:$E$70,'[1]Table of Transects'!$A$3:$A$70,'Stage-Flow'!A37,'[1]Table of Transects'!$B$3:$B$70,'Stage-Flow'!B37,'[1]Table of Transects'!$J$3:$J$70,"Yes") -> #VALUE! | D37: =AVERAGEIFS('[1]Table of Transects'!$G$3:$G$53,'[1]Table of Transects'!$A$3:$A$53,'Stage-Flow'!A37,'[1]Table of Transects'!$B$3:$B$53,'Stage-Flow'!B37,'[1]Table of Transects'!$J$3:$J$53,"Yes") -> #VALUE! | E37: =AVERAGEIFS('[1]Table of Stages'!$H$3:$H$65,'[1]Table of Stages'!$A$3:$A$65,'Stage-Flow'!A37,'[1]Table of Stages'!$B$3:$B$65,'Stage-Flow'!B37) -> #VALUE! | F37: =_xlfn.STDEV.S('[1]Table of Transects'!E40:E44) -> 21.396053 | G37: ='[1]Table of Transects'!K40 -> 25.394 | H37: =_xlfn.STDEV.S('[1]Table of Stages'!H35:H39) -> 0.021908902 | I37: 6.1 | J37: 114.83 | K37: =I37+10.81-4.54 -> 12.37
A38: Confluence | B38: ='[1]Table of Transects'!B59 -> 41594 | C38: =AVERAGEIFS('[1]Table of Transects'!$E$3:$E$70,'[1]Table of Transects'!$A$3:$A$70,'Stage-Flow'!A38,'[1]Table of Transects'!$B$3:$B$70,'Stage-Flow'!B38,'[1]Table of Transects'!$J$3:$J$70,"Yes") -> #VALUE! | E38: =AVERAGEIFS('[1]Table of Stages'!$H$3:$H$65,'[1]Table of Stages'!$A$3:$A$65,'Stage-Flow'!A38,'[1]Table of Stages'!$B$3:$B$65,'Stage-Flow'!B38) -> #VALUE! | F38: ='[1]Table of Transects'!K59 -> 7.4830437 | H38: =_xlfn.STDEV.S('[1]Table of Stages'!H54:H57) -> 0.029011492 | I38: =1.5*3.28084 -> 4.92126 | J38: 138.3 | K38: =I38+11.55-3.65 -> 12.82126
A39: Confluence | B39: 41764 | D39: 964.2 | I39: 7.52 | J39: 217.28 | K39: =I39+9.42-4.16 -> 12.78
A40: Mortin | B40: ='[1]Table of Transects'!B32 -> 41500 | C40: =AVERAGEIFS('[1]Table of Transects'!$E$3:$E$70,'[1]Table of Transects'!$A$3:$A$70,'Stage-Flow'!A40,'[1]Table of Transects'!$B$3:$B$70,'Stage-Flow'!B40,'[1]Table of Transects'!$J$3:$J$70,"Yes") -> #VALUE! | D40: =AVERAGEIFS('[1]Table of Transects'!$G$3:$G$53,'[1]Table of Transects'!$A$3:$A$53,'Stage-Flow'!A40,'[1]Table of Transects'!$B$3:$B$53,'Stage-Flow'!B40,'[1]Table of Transects'!$J$3:$J$53,"Yes") -> #VALUE! | E40: =AVERAGEIFS('[1]Table of Stages'!$H$3:$H$65,'[1]Table of Stages'!$A$3:$A$65,'Stage-Flow'!A40,'[1]Table of Stages'!$B$3:$B$65,'Stage-Flow'!B40) -> #VALUE! | F40: =_xlfn.STDEV.S('[1]Table of Transects'!E32:E39) -> 25.843239 | G40: ='[1]Table of Transects'!K32 -> 26.074 | H40: =_xlfn.STDEV.S('[1]Table of Stages'!H27:H34) -> 0.021380899 | I40: 5.4 | J40: 121.23 | K40: =I40+9.76-4.65 -> 10.51
A41: Mortin | B41: ='[1]Table of Transects'!B54 -> 41594 | C41: =AVERAGEIFS('[1]Table of Transects'!$E$3:$E$70,'[1]Table of Transects'!$A$3:$A$70,'Stage-Flow'!A41,'[1]Table of Transects'!$B$3:$B$70,'Stage-Flow'!B41,'[1]Table of Transects'!$J$3:$J$70,"Yes") -> #VALUE! | E41: =AVERAGEIFS('[1]Table of Stages'!$H$3:$H$65,'[1]Table of Stages'!$A$3:$A$65,'Stage-Flow'!A41,'[1]Table of Stages'!$B$3:$B$65,'Stage-Flow'!B41) -> #VALUE! | F41: ='[1]Table of Transects'!K55 -> 9.3905588 | H41: =_xlfn.STDEV.S('[1]Table of Stages'!H49:H53) -> 0.037980258 | I41: 1.54 | J41: 113.26 | K41: =I41+10.75-4.11 -> 8.18
A42: Mortin | B42: 41764 | D42: 693.59 | I42: 5.83 | J42: 207.2 | K42: =I42+10.91-4.71 -> 12.03
D44: Old Workbook Data: | E44: (Old Protocal)
A45: Confluence | B45: 41137 | C45: 770.6285 | D45: 771.36725 | E45: =AVERAGEIFS('[1]Table of Stages'!$H$3:$H$65,'[1]Table of Stages'!$A$3:$A$65,'Stage-Flow'!A45,'[1]Table of Stages'!$B$3:$B$65,'Stage-Flow'!B45) -> #VALUE! | F45: 20.855805 | G45: 21.808 | H45: 0.064355782
A46: Confluence | B46: 41230 | C46: 451.15525 | D46: 451.60675 | E46: =AVERAGEIFS('[1]Table of Stages'!$H$3:$H$65,'[1]Table of Stages'!$A$3:$A$65,'Stage-Flow'!A46,'[1]Table of Stages'!$B$3:$B$65,'Stage-Flow'!B46) -> #VALUE! | F46: 12.270428 | G46: 15.044 | H46: 0.056199051
A47: Confluence | B47: 41401 | C47: 565.2475 | D47: 568.17925 | E47: =AVERAGEIFS('[1]Table of Stages'!$H$3:$H$65,'[1]Table of Stages'!$A$3:$A$65,'Stage-Flow'!A47,'[1]Table of Stages'!$B$3:$B$65,'Stage-Flow'!B47) -> #VALUE! | F47: 10.415672 | G47: 11.323 | H47: 0.022173558
A48: Confluence | B48: 41501 | C48: 865.6825 | D48: 861.56075 | E48: =AVERAGEIFS('[1]Table of Stages'!$H$3:$H$65,'[1]Table of Stages'!$A$3:$A$65,'Stage-Flow'!A48,'[1]Table of Stages'!$B$3:$B$65,'Stage-Flow'!B48) -> #VALUE! | F48: 21.396053 | G48: 25.394 | H48: 0.021908902
A49: Mortin | B49: 41500 | C49: 846.1375 | D49: 843.9585 | E49: =AVERAGEIFS('[1]Table of Stages'!$H$3:$H$65,'[1]Table of Stages'!$A$3:$A$65,'Stage-Flow'!A49,'[1]Table of Stages'!$B$3:$B$65,'Stage-Flow'!B49) -> #VALUE! | F49: 25.843239 | G49: 26.074 | H49: 0.021380899

Sheet Stage-Flow-Width
P1: (ft) | Q1: Motron | R1: Confluence | S1: Cub
P2: Bench Mark | Q2: 3.35 | R2: 4.05 | S2: 4.28
P3: Datum | Q3: 20 | R3: 20 | S3: 20
P4: WSL surveyed | Q4: 14.44 | R4: 13.19 | S4: 11.16
P5: WSL to Datum | Q5: =Q2+Q3-Q4 -> 8.91 | R5: =R2+R3-R4 -> 10.86 | S5: =S2+S3-S4 -> 13.12
P6: Transducer Channel Bottom Survery | Q6: 11.52 | R6: 12.99 | S6: 13.99
P7: Channel bed at transducer to Datum | Q7: =Q2+Q3-Q6 -> 11.83 | R7: =R2+R3-R6 -> 11.06 | S7: =S2+S3-S6 -> 10.29
P8: Deepest Channel bottom to Datum | Q8: 9.452 | R8: 6.73 | S8: 7.13
P9: Max Water Depth | Q9: =Q2+Q3-Q5-Q8 -> 4.988 | R9: =R2+R3-R5-R8 -> 6.46 | S9: =S2+S3-S5-S8 -> 4.03
F11: Datum = 30 | G11: Datum = 20
D12: Date | E12: Flow (cfs) | F12: Old Stage (ft) | G12: New Stage (ft) | H12: Width (ft) | I12: Water Depth at Transducer (ft) | J12: Max Water Depth (ft) | K12: Flow (Mm3/month) | L12: Stage (m) | M12: Width (m) | N12: Max Water Depth | O12: Water Depth at Transducer (m) | P12: Width/max Depth ratio | Q12: Width/ Stage | R12: Temp [C]
C13: Cub | D13: 41137 | E13: 4.8425 | F13: 23.65 | G13: =F13-10 -> 13.65 | I13: =G13-$S$7 -> 3.36 | J13: =G13-$S$8 -> 6.52 | K13: =E13*0.0744661151309 -> 0.36060216 | L13: =G13*0.3048 -> 4.16052 | M13: =H13*0.3048 -> 0 | N13: =J13*0.3048 -> 1.987296 | O13: =I13*0.3048 -> 1.024128 | R13: 26.4
D14: 41230 | E14: 24.276 | F14: 22.5875 | G14: =F14-10 -> 12.5875 | H14: 31.1 | I14: =G14-$S$7 -> 2.2975 | J14: =G14-$S$8 -> 5.4575 | K14: =E14*0.0744661151309 -> 1.8077394 | L14: =G14*0.3048 -> 3.83667 | M14: =H14*0.3048 -> 9.47928 | N14: =J14*0.3048 -> 1.663446 | O14: =I14*0.3048 -> 0.700278 | P14: =H14/$S$9 -> 7.7171216 | Q14: =H14/G14 -> 2.4707051 | R14: 10.9
D15: 41401 | E15: 146.204 | F15: 23.145 | G15: =F15-10 -> 13.145 | H15: 38.9 | I15: =G15-$S$7 -> 2.855 | J15: =G15-$S$8 -> 6.015 | K15: =E15*0.0744661151309 -> 10.887244 | L15: =G15*0.3048 -> 4.006596 | M15: =H15*0.3048 -> 11.85672 | N15: =J15*0.3048 -> 1.833372 | O15: =I15*0.3048 -> 0.870204 | P15: =H15/$S$9 -> 9.6526055 | Q15: =H15/G15 -> 2.9593001 | R15: 7.6
D16: 41501 | E16: 2.18 | F16: 24.07 | G16: =F16-10 -> 14.07 | H16: =76.5-20.5 -> 56 | I16: =G16-$S$7 -> 3.78 | J16: =G16-$S$8 -> 6.94 | K16: =E16*0.0744661151309 -> 0.16233613 | L16: =G16*0.3048 -> 4.288536 | M16: =H16*0.3048 -> 17.0688 | N16: =J16*0.3048 -> 2.115312 | O16: =I16*0.3048 -> 1.152144 | P16: =H16/$S$9 -> 13.895782 | Q16: =H16/G16 -> 3.9800995 | R16: 29
D17: 41594 | E17: 29.481861 | F17: 22.435 | G17: =F17-10 -> 12.435 | I17: =G17-$S$7 -> 2.145 | J17: =G17-$S$8 -> 5.305 | K17: =E17*0.0744661151309 -> 2.1953997 | L17: =G17*0.3048 -> 3.790188 | M17: =H17*0.3048 -> 0 | N17: =J17*0.3048 -> 1.616964 | O17: =I17*0.3048 -> 0.653796 | R17: 4.2
D18: 41764 | E18: 273.39 | F18: 23.852427 | G18: =F18-10 -> 13.852427 | I18: =G18-$S$7 -> 3.562427 | J18: =G18-$S$8 -> 6.722427 | K18: =E18*0.0744661151309 -> 20.358291 | L18: =G18*0.3048 -> 4.2222197 | M18: =H18*0.3048 -> 0 | N18: =J18*0.3048 -> 2.0489957 | O18: =I18*0.3048 -> 1.0858277 | R18: 12.4
D19: 42237 | E19: 4.19 | F19: 22.93 | G19: =F19-10 -> 12.93 | H19: =70-20 -> 50 | I19: =G19-$S$7 -> 2.64 | J19: =G19-$S$8 -> 5.8 | K19: =E19*0.0744661151309 -> 0.31201302 | L19: =G19*0.3048 -> 3.941064 | M19: =H19*0.3048 -> 15.24 | N19: =J19*0.3048 -> 1.76784 | O19: =I19*0.3048 -> 0.804672 | P19: =H19/$S$9 -> 12.406948 | Q19: =H19/G19 -> 3.866976
C20: Confluence | D20: 41137 | H20: =20+86 -> 106 | K20: =E20*0.0744661151309 -> 0 | L20: =G20*0.3048 -> 0 | M20: =H20*0.3048 -> 32.3088 | R20: 21.4
D21: 41230 | E21: 450.60675 | F21: 22.0225 | G21: =F21-10 -> 12.0225 | H21: 105.4 | I21: =G21-$R$7 -> 0.9625 | J21: =G21-$R$8 -> 5.2925 | K21: =E21*0.0744661151309 -> 33.554934 | L21: =G21*0.3048 -> 3.664458 | M21: =H21*0.3048 -> 32.12592 | N21: =J21*0.3048 -> 1.613154 | O21: =I21*0.3048 -> 0.29337 | P21: =H21/$R$9 -> 16.315789 | Q21: =H21/G21 -> 8.7668954 | R21: 12.8
D22: 41401 | E22: 568.17925 | F22: 22.7525 | G22: =F22-10 -> 12.7525 | H22: =20+98.2 -> 118.2 | I22: =G22-$R$7 -> 1.6925 | J22: =G22-$R$8 -> 6.0225 | K22: =E22*0.0744661151309 -> 42.310101 | L22: =G22*0.3048 -> 3.886962 | M22: =H22*0.3048 -> 36.02736 | N22: =J22*0.3048 -> 1.835658 | O22: =I22*0.3048 -> 0.515874 | P22: =H22/$R$9 -> 18.297214 | Q22: =H22/G22 -> 9.2687708 | R22: 16.1
D23: 41501 | E23: 841.268 | F23: 23.46 | G23: =F23-10 -> 13.46 | H23: =154.5-34.5 -> 120 | I23: =G23-$R$7 -> 2.4 | J23: =G23-$R$8 -> 6.73 | K23: =E23*0.0744661151309 -> 62.64596 | L23: =G23*0.3048 -> 4.102608 | M23: =H23*0.3048 -> 36.576 | N23: =J23*0.3048 -> 2.051304 | O23: =I23*0.3048 -> 0.73152 | P23: =H23/$R$9 -> 18.575851 | Q23: =H23/G23 -> 8.9153046 | R23: 21.2
D24: 41594 | E24: 385.81273 | F24: 21.8525 | G24: =F24-10 -> 11.8525 | H24: 108.3 | I24: =G24-$R$7 -> 0.7925 | J24: =G24-$R$8 -> 5.1225 | K24: =E24*0.0744661151309 -> 28.729975 | L24: =G24*0.3048 -> 3.612642 | M24: =H24*0.3048 -> 33.00984 | N24: =J24*0.3048 -> 1.561338 | O24: =I24*0.3048 -> 0.241554 | P24: =H24/$R$9 -> 16.764706 | Q24: =H24/G24 -> 9.1373128 | R24: 3.7
D25: 41764 | L25: =G25*0.3048 -> 0 | P25: =H25/$R$9 -> 0 | R25: 12.3
D26: 42237 | E26: 421.5425 | F26: 22.18 | G26: =F26-10 -> 12.18 | H26: =154-49 -> 105 | I26: =G26-$R$7 -> 1.12 | J26: =G26-$R$8 -> 5.45 | K26: =E26*0.0744661151309 -> 31.390632 | L26: =G26*0.3048 -> 3.712464 | M26: =H26*0.3048 -> 32.004 | N26: =J26*0.3048 -> 1.66116 | O26: =I26*0.3048 -> 0.341376 | P26: =H26/$R$9 -> 16.25387 | Q26: =H26/G26 -> 8.6206897 | R26: 16.6
C27: Morton | D27: 41500 | E27: 856.6875 | F27: 24.885 | G27: =F27-10 -> 14.885 | H27: 123 | I27: =G27-$Q$7 -> 3.055 | J27: =G27-$Q$8 -> 5.433 | K27: =E27*0.0744661151309 -> 63.79419 | L27: =G27*0.3048 -> 4.536948 | M27: =H27*0.3048 -> 37.4904 | N27: =J27*0.3048 -> 1.6559784 | O27: =I27*0.3048 -> 0.931164 | P27: =H27/$Q$9 -> 24.659182 | Q27: =H27/G27 -> 8.2633524 | R27: 21.1
D28: 41594 | E28: 322.67011 | F28: 23.3475 | G28: =F28-10 -> 13.3475 | H28: 111 | I28: =G28-$Q$7 -> 1.5175 | J28: =G28-$Q$8 -> 3.8955 | K28: =E28*0.0744661151309 -> 24.02799 | L28: =G28*0.3048 -> 4.068318 | M28: =H28*0.3048 -> 33.8328 | N28: =J28*0.3048 -> 1.1873484 | O28: =I28*0.3048 -> 0.462534 | P28: =H28/$Q$9 -> 22.253408 | Q28: =H28/G28 -> 8.3161641 | R28: 4.7
D29: 41764 | L29: =G29*0.3048 -> 0 | R29: 13.55
D30: 42235 | E30: 508.8225 | F30: 23.91 | G30: =F30-10 -> 13.91 | H30: =163.7-42 -> 121.7 | I30: =G30-$Q$7 -> 2.08 | J30: =G30-$Q$8 -> 4.458 | K30: =E30*0.0744661151309 -> 37.890035 | L30: =G30*0.3048 -> 4.239768 | M30: =H30*0.3048 -> 37.09416 | N30: =J30*0.3048 -> 1.3587984 | O30: =I30*0.3048 -> 0.633984 | P30: =H30/$Q$9 -> 24.398557 | Q30: =H30/G30 -> 8.7491014 | R30: 18.6

Sheet RSI curves
B1: Juvenile | C1: Fry | D1: Spawn/eggs
A2: Suitability Index | B2: Depth (m) | C2: Depth (m) | D2: Depth (m)
A3: 0 | B3: 0 | C3: 0 | D3: 0
A4: 0 | B4: 0.25 | C4: 0.249 | D4: 0.09
A5: 0.25 | B5: 0.251 | C5: 0.25 | D5: 0.1
A6: 0.25 | B6: 0.75 | C6: 0.499 | D6: 0.199
A7: 0.5 | B7: 0.751 | C7: 0.5 | D7: 0.2
A8: 0.5 | B8: 1.249 | C8: 0.749 | D8: 0.399
A9: 1 | B9: 1.25 | C9: 0.75 | D9: 0.4
A10: 1 | B10: 1.5 | C10: 1 | D10: 0.5
A16: month | B16: funcNo | C16: Life Stage
A17: 1 | B17: 1 | C17: Spawn/eggs
A18: 2 | B18: 1 | C18: Spawn/eggs
A19: 3 | B19: 2 | C19: Fy
A20: 4 | B20: 2 | C20: Fy
A21: 5 | B21: 2 | C21: Fry
A22: 6 | B22: 2 | C22: Fry
A23: 7 | B23: 2 | C23: Fry
A24: 8 | B24: 2 | C24: Fry
A25: 9 | B25: 3 | C25: Juvenile | AC25: Boltzmann Model.
A26: 10 | B26: 3 | C26: Juvenile
A27: 11 | B27: 3 | C27: Juvenile | AC27: fit = (A+((B-A)/(1+exp((C-x)/D))))
A28: 12 | B28: 3 | C28: Juvenile | K28: Boltzmann Model. | AC28: inv = (C-(D*ln((B-y)/(y-A))))
AC29: res = (y-fit)
K30: fit = (A+((B-A)/(1+exp((C-x)/D))))
K31: inv = (C-(D*ln((B-y)/(y-A))))
K32: res = (y-fit)
A33: RSI | B33: J | C33: F | D33: S | J33: Model
A34: 0 | B34: 0 | C34: 0 | D34: 0 | F34: Juvenile Depth (m) | G34: Suitability Index | J34: A | K34: =[2]!xf4_ParameterValue(N34,1) -> #NAME? | N34: =[2]!xf4_FitData("",[2]!xf4_SetModel("600"),[2]!xf4_SetParameters(0,FALSE,TRUE,100,FALSE,TRUE,1,FALSE,TRUE,1,FALSE,TRUE),[2]!xf4_SetData(,$F$35:$F$113,,$G$35:$G$113)) -> #NAME? | P34: =[2]!xf4_Chart2D([2]!xf_Init()&[2]!xf_ScaleX(,,,,FALSE)&[2]!xf_ScaleY(,,,,FALSE),[2]!xf4_C2DFit(N34)&[2]!xf4_C2DFitDetails(7,0,0.05,0,0.05)&[2]!xf4_C2DFitPoints(101,,,,1,-1)) -> #NAME? | AD34: Model
A35: 1 | B35: 1.5 | C35: 1 | D35: 0.5 | F35: 0 | G35: =PieceWiseLinInt(F35, $B$34:$B$35, $A$34:$A$35, FALSE, FALSE) -> #NAME? | J35: B | K35: =[2]!xf4_ParameterValue(N34,2) -> #NAME? | Z35: Fry Depth (m) | AA35: Suitability Index | AD35: A | AE35: =[2]!xf4_ParameterValue(AG35,1) -> #NAME? | AG35: =[2]!xf4_FitData("",[2]!xf4_SetModel("600"),[2]!xf4_SetParameters(0,FALSE,TRUE,100,FALSE,TRUE,1,FALSE,TRUE,1,FALSE,TRUE),[2]!xf4_SetData(,$Z$36:$Z$112,,$AA$36:$AA$112)) -> #NAME? | AS35: Model
F36: 0.05 | G36: =PieceWiseLinInt(F36, $B$34:$B$35, $A$34:$A$35, FALSE, FALSE) -> #NAME? | J36: C | K36: =[2]!xf4_ParameterValue(N34,3) -> #NAME? | Z36: 0 | AA36: =PieceWiseLinInt(Z36, $C$34:$C$35, $A$34:$A$35, FALSE, FALSE) -> #NAME? | AD36: B | AE36: =[2]!xf4_ParameterValue(AG35,2) -> #NAME? | AO36: Spawn Depth (m) | AP36: Suitability Index | AS36: A | AT36: =[2]!xf4_ParameterValue(AW36,1) -> #NAME? | AW36: =[2]!xf4_FitData("",[2]!xf4_SetModel("600"),[2]!xf4_SetParameters(0,FALSE,TRUE,1000,FALSE,TRUE,10,FALSE,FALSE,1,FALSE,TRUE),[2]!xf4_SetData(,$AO$37:$AO$76,,$AP$37:$AP$76)) -> #NAME?
F37: 0.1 | G37: =PieceWiseLinInt(F37, $B$34:$B$35, $A$34:$A$35, FALSE, FALSE) -> #NAME? | J37: D | K37: =[2]!xf4_ParameterValue(N34,4) -> #NAME? | Z37: 0.05 | AA37: =PieceWiseLinInt(Z37, $C$34:$C$35, $A$34:$A$35, FALSE, FALSE) -> #NAME? | AD37: C | AE37: =[2]!xf4_ParameterValue(AG35,3) -> #NAME? | AO37: 0 | AP37: =PieceWiseLinInt(AO37, $D$34:$D$35, $A$34:$A$35, FALSE, FALSE) -> #NAME? | AS37: B | AT37: =[2]!xf4_ParameterValue(AW36,2) -> #NAME?
F38: 0.15 | G38: =PieceWiseLinInt(F38, $B$34:$B$35, $A$34:$A$35, FALSE, FALSE) -> #NAME? | Z38: 0.1 | AA38: =PieceWiseLinInt(Z38, $C$34:$C$35, $A$34:$A$35, FALSE, FALSE) -> #NAME? | AD38: D | AE38: =[2]!xf4_ParameterValue(AG35,4) -> #NAME? | AG38: =[2]!xf4_Chart2D([2]!xf_Init()&[2]!xf_ScaleX(,,,,FALSE)&[2]!xf_ScaleY(,,,,FALSE),[2]!xf4_C2DFit(AG35)) -> #NAME? | AO38: 0.05 | AP38: =PieceWiseLinInt(AO38, $D$34:$D$35, $A$34:$A$35, FALSE, FALSE) -> #NAME? | AS38: C | AT38: =[2]!xf4_ParameterValue(AW36,3) -> #NAME? | AW38: =[2]!xf4_Chart2D([2]!xf_Init()&[2]!xf_ScaleX(,,,,FALSE)&[2]!xf_ScaleY(,,,,FALSE),[2]!xf4_C2DFit(AW36)) -> #NAME?
F39: 0.2 | G39: =PieceWiseLinInt(F39, $B$34:$B$35, $A$34:$A$35, FALSE, FALSE) -> #NAME? | Z39: 0.15 | AA39: =PieceWiseLinInt(Z39, $C$34:$C$35, $A$34:$A$35, FALSE, FALSE) -> #NAME? | AO39: 0.1 | AP39: =PieceWiseLinInt(AO39, $D$34:$D$35, $A$34:$A$35, FALSE, FALSE) -> #NAME? | AS39: D | AT39: =[2]!xf4_ParameterValue(AW36,4) -> #NAME?
F40: 0.25 | G40: =PieceWiseLinInt(F40, $B$34:$B$35, $A$34:$A$35, FALSE, FALSE) -> #NAME? | Z40: 0.2 | AA40: =PieceWiseLinInt(Z40, $C$34:$C$35, $A$34:$A$35, FALSE, FALSE) -> #NAME? | AO40: 0.15 | AP40: =PieceWiseLinInt(AO40, $D$34:$D$35, $A$34:$A$35, FALSE, FALSE) -> #NAME?
F41: 0.3 | G41: =PieceWiseLinInt(F41, $B$34:$B$35, $A$34:$A$35, FALSE, FALSE) -> #NAME? | J41: Depth | K41: 10000 | Z41: 0.25 | AA41: =PieceWiseLinInt(Z41, $C$34:$C$35, $A$34:$A$35, FALSE, FALSE) -> #NAME? | AO41: 0.2 | AP41: =PieceWiseLinInt(AO41, $D$34:$D$35, $A$34:$A$35, FALSE, FALSE) -> #NAME?
F42: 0.35 | G42: =PieceWiseLinInt(F42, $B$34:$B$35, $A$34:$A$35, FALSE, FALSE) -> #NAME? | J42: RSI | K42: =(K34+((K35-K34)/(1+EXP((K36-K41)/K37)))) -> #NAME? | Z42: 0.3 | AA42: =PieceWiseLinInt(Z42, $C$34:$C$35, $A$34:$A$35, FALSE, FALSE) -> #NAME? | AD42: Depth | AE42: 10 | AO42: 0.25 | AP42: =PieceWiseLinInt(AO42, $D$34:$D$35, $A$34:$A$35, FALSE, FALSE) -> #NAME?
F43: 0.4 | G43: =PieceWiseLinInt(F43, $B$34:$B$35, $A$34:$A$35, FALSE, FALSE) -> #NAME? | Z43: 0.35 | AA43: =PieceWiseLinInt(Z43, $C$34:$C$35, $A$34:$A$35, FALSE, FALSE) -> #NAME? | AD43: RSI | AE43: =(AE35+((AE36-AE35)/(1+EXP((AE37-AE42)/AE38)))) -> #NAME? | AO43: 0.3 | AP43: =PieceWiseLinInt(AO43, $D$34:$D$35, $A$34:$A$35, FALSE, FALSE) -> #NAME? | AS43: Depth | AT43: 0
F44: 0.45 | G44: =PieceWiseLinInt(F44, $B$34:$B$35, $A$34:$A$35, FALSE, FALSE) -> #NAME? | Z44: 0.4 | AA44: =PieceWiseLinInt(Z44, $C$34:$C$35, $A$34:$A$35, FALSE, FALSE) -> #NAME? | AO44: 0.35 | AP44: =PieceWiseLinInt(AO44, $D$34:$D$35, $A$34:$A$35, FALSE, FALSE) -> #NAME? | AS44: RSI | AT44: =(AT36+((AT37-AT36)/(1+EXP((AT38-AT43)/AT39)))) -> #NAME?
F45: 0.5 | G45: =PieceWiseLinInt(F45, $B$34:$B$35, $A$34:$A$35, FALSE, FALSE) -> #NAME? | Z45: 0.45 | AA45: =PieceWiseLinInt(Z45, $C$34:$C$35, $A$34:$A$35, FALSE, FALSE) -> #NAME? | AO45: 0.4 | AP45: =PieceWiseLinInt(AO45, $D$34:$D$35, $A$34:$A$35, FALSE, FALSE) -> #NAME?
F46: 0.55 | G46: =PieceWiseLinInt(F46, $B$34:$B$35, $A$34:$A$35, FALSE, FALSE) -> #NAME? | J46: Copy | Z46: 0.5 | AA46: =PieceWiseLinInt(Z46, $C$34:$C$35, $A$34:$A$35, FALSE, FALSE) -> #NAME? | AO46: 0.45 | AP46: =PieceWiseLinInt(AO46, $D$34:$D$35, $A$34:$A$35, FALSE, FALSE) -> #NAME?
F47: 0.6 | G47: =PieceWiseLinInt(F47, $B$34:$B$35, $A$34:$A$35, FALSE, FALSE) -> #NAME? | J47: A | K47: -0.040639407 | Z47: 0.55 | AA47: =PieceWiseLinInt(Z47, $C$34:$C$35, $A$34:$A$35, FALSE, FALSE) -> #NAME? | AO47: 0.5 | AP47: =PieceWiseLinInt(AO47, $D$34:$D$35, $A$34:$A$35, FALSE, FALSE) -> #NAME?
F48: 0.65 | G48: =PieceWiseLinInt(F48, $B$34:$B$35, $A$34:$A$35, FALSE, FALSE) -> #NAME? | J48: B | K48: 1.0073214 | Z48: 0.6 | AA48: =PieceWiseLinInt(Z48, $C$34:$C$35, $A$34:$A$35, FALSE, FALSE) -> #NAME? | AO48: 0.55 | AP48: =PieceWiseLinInt(AO48, $D$34:$D$35, $A$34:$A$35, FALSE, FALSE) -> #NAME?
F49: 0.7 | G49: =PieceWiseLinInt(F49, $B$34:$B$35, $A$34:$A$35, FALSE, FALSE) -> #NAME? | J49: C | K49: 0.71969176 | Z49: 0.65 | AA49: =PieceWiseLinInt(Z49, $C$34:$C$35, $A$34:$A$35, FALSE, FALSE) -> #NAME? | AD49: Copy | AO49: 0.6 | AP49: =PieceWiseLinInt(AO49, $D$34:$D$35, $A$34:$A$35, FALSE, FALSE) -> #NAME?
F50: 0.75 | G50: =PieceWiseLinInt(F50, $B$34:$B$35, $A$34:$A$35, FALSE, FALSE) -> #NAME? | J50: D | K50: 0.31060214 | Z50: 0.7 | AA50: =PieceWiseLinInt(Z50, $C$34:$C$35, $A$34:$A$35, FALSE, FALSE) -> #NAME? | AD50: A | AE50: -0.050319228 | AO50: 0.65 | AP50: =PieceWiseLinInt(AO50, $D$34:$D$35, $A$34:$A$35, FALSE, FALSE) -> #NAME? | AS50: Copy
F51: 0.8 | G51: =PieceWiseLinInt(F51, $B$34:$B$35, $A$34:$A$35, FALSE, FALSE) -> #NAME? | Z51: 0.75 | AA51: =PieceWiseLinInt(Z51, $C$34:$C$35, $A$34:$A$35, FALSE, FALSE) -> #NAME? | AD51: B | AE51: 1.010037 | AO51: 0.7 | AP51: =PieceWiseLinInt(AO51, $D$34:$D$35, $A$34:$A$35, FALSE, FALSE) -> #NAME? | AS51: A | AT51: -0.064253143
F52: 0.85 | G52: =PieceWiseLinInt(F52, $B$34:$B$35, $A$34:$A$35, FALSE, FALSE) -> #NAME? | Z52: 0.8 | AA52: =PieceWiseLinInt(Z52, $C$34:$C$35, $A$34:$A$35, FALSE, FALSE) -> #NAME? | AD52: C | AE52: 0.47632015 | AO52: 0.75 | AP52: =PieceWiseLinInt(AO52, $D$34:$D$35, $A$34:$A$35, FALSE, FALSE) -> #NAME? | AS52: B | AT52: 1.0052001
F53: 0.9 | G53: =PieceWiseLinInt(F53, $B$34:$B$35, $A$34:$A$35, FALSE, FALSE) -> #NAME? | Z53: 0.85 | AA53: =PieceWiseLinInt(Z53, $C$34:$C$35, $A$34:$A$35, FALSE, FALSE) -> #NAME? | AD53: D | AE53: 0.20991268 | AO53: 0.8 | AP53: =PieceWiseLinInt(AO53, $D$34:$D$35, $A$34:$A$35, FALSE, FALSE) -> #NAME? | AS53: C | AT53: 0.23336288
F54: 0.95 | G54: =PieceWiseLinInt(F54, $B$34:$B$35, $A$34:$A$35, FALSE, FALSE) -> #NAME? | J54: Depth | K54: 10000 | Z54: 0.9 | AA54: =PieceWiseLinInt(Z54, $C$34:$C$35, $A$34:$A$35, FALSE, FALSE) -> #NAME? | AO54: 0.85 | AP54: =PieceWiseLinInt(AO54, $D$34:$D$35, $A$34:$A$35, FALSE, FALSE) -> #NAME? | AS54: D | AT54: 0.10489703
F55: 1 | G55: =PieceWiseLinInt(F55, $B$34:$B$35, $A$34:$A$35, FALSE, FALSE) -> #NAME? | J55: RSI | K55: =(K47+((K48-K47)/(1+EXP((K49-K54)/K50)))) -> 1.0073214 | Z55: 0.95 | AA55: =PieceWiseLinInt(Z55, $C$34:$C$35, $A$34:$A$35, FALSE, FALSE) -> #NAME? | AO55: 0.9 | AP55: =PieceWiseLinInt(AO55, $D$34:$D$35, $A$34:$A$35, FALSE, FALSE) -> #NAME?
F56: 1.05 | G56: =PieceWiseLinInt(F56, $B$34:$B$35, $A$34:$A$35, FALSE, FALSE) -> #NAME? | Z56: 1 | AA56: =PieceWiseLinInt(Z56, $C$34:$C$35, $A$34:$A$35, FALSE, FALSE) -> #NAME? | AO56: 0.95 | AP56: =PieceWiseLinInt(AO56, $D$34:$D$35, $A$34:$A$35, FALSE, FALSE) -> #NAME?
F57: 1.1 | G57: =PieceWiseLinInt(F57, $B$34:$B$35, $A$34:$A$35, FALSE, FALSE) -> #NAME? | Z57: 1.05 | AA57: =PieceWiseLinInt(Z57, $C$34:$C$35, $A$34:$A$35, FALSE, FALSE) -> #NAME? | AD57: Depth | AE57: 10 | AO57: 1 | AP57: =PieceWiseLinInt(AO57, $D$34:$D$35, $A$34:$A$35, FALSE, FALSE) -> #NAME?
F58: 1.15 | G58: =PieceWiseLinInt(F58, $B$34:$B$35, $A$34:$A$35, FALSE, FALSE) -> #NAME? | Z58: 1.1 | AA58: =PieceWiseLinInt(Z58, $C$34:$C$35, $A$34:$A$35, FALSE, FALSE) -> #NAME? | AD58: RSI | AE58: =(AE50+((AE51-AE50)/(1+EXP((AE52-AE57)/AE53)))) -> 1.010037 | AO58: 1.05 | AP58: =PieceWiseLinInt(AO58, $D$34:$D$35, $A$34:$A$35, FALSE, FALSE) -> #NAME? | AS58: Depth | AT58: 0
F59: 1.2 | G59: =PieceWiseLinInt(F59, $B$34:$B$35, $A$34:$A$35, FALSE, FALSE) -> #NAME? | Z59: 1.15 | AA59: =PieceWiseLinInt(Z59, $C$34:$C$35, $A$34:$A$35, FALSE, FALSE) -> #NAME? | AO59: 1.1 | AP59: =PieceWiseLinInt(AO59, $D$34:$D$35, $A$34:$A$35, FALSE, FALSE) -> #NAME? | AS59: RSI | AT59: =(AT51+((AT52-AT51)/(1+EXP((AT53-AT58)/AT54)))) -> 0.040077953
F60: 1.25 | G60: =PieceWiseLinInt(F60, $B$34:$B$35, $A$34:$A$35, FALSE, FALSE) -> #NAME? | Z60: 1.2 | AA60: =PieceWiseLinInt(Z60, $C$34:$C$35, $A$34:$A$35, FALSE, FALSE) -> #NAME? | AO60: 1.15 | AP60: =PieceWiseLinInt(AO60, $D$34:$D$35, $A$34:$A$35, FALSE, FALSE) -> #NAME?
F61: 1.3 | G61: =PieceWiseLinInt(F61, $B$34:$B$35, $A$34:$A$35, FALSE, FALSE) -> #NAME? | Z61: 1.25 | AA61: =PieceWiseLinInt(Z61, $C$34:$C$35, $A$34:$A$35, FALSE, FALSE) -> #NAME? | AO61: 1.2 | AP61: =PieceWiseLinInt(AO61, $D$34:$D$35, $A$34:$A$35, FALSE, FALSE) -> #NAME?
F62: 1.35 | G62: =PieceWiseLinInt(F62, $B$34:$B$35, $A$34:$A$35, FALSE, FALSE) -> #NAME? | Z62: 1.3 | AA62: =PieceWiseLinInt(Z62, $C$34:$C$35, $A$34:$A$35, FALSE, FALSE) -> #NAME? | AO62: 1.25 | AP62: =PieceWiseLinInt(AO62, $D$34:$D$35, $A$34:$A$35, FALSE, FALSE) -> #NAME?
F63: 1.4 | G63: =PieceWiseLinInt(F63, $B$34:$B$35, $A$34:$A$35, FALSE, FALSE) -> #NAME? | Z63: 1.35 | AA63: =PieceWiseLinInt(Z63, $C$34:$C$35, $A$34:$A$35, FALSE, FALSE) -> #NAME? | AO63: 1.3 | AP63: =PieceWiseLinInt(AO63, $D$34:$D$35, $A$34:$A$35, FALSE, FALSE) -> #NAME?
F64: 1.45 | G64: =PieceWiseLinInt(F64, $B$34:$B$35, $A$34:$A$35, FALSE, FALSE) -> #NAME? | Z64: 1.4 | AA64: =PieceWiseLinInt(Z64, $C$34:$C$35, $A$34:$A$35, FALSE, FALSE) -> #NAME? | AO64: 1.35 | AP64: =PieceWiseLinInt(AO64, $D$34:$D$35, $A$34:$A$35, FALSE, FALSE) -> #NAME?
F65: 1.5 | G65: =PieceWiseLinInt(F65, $B$34:$B$35, $A$34:$A$35, FALSE, FALSE) -> #NAME? | Z65: 1.45 | AA65: =PieceWiseLinInt(Z65, $C$34:$C$35, $A$34:$A$35, FALSE, FALSE) -> #NAME? | AO65: 1.4 | AP65: =PieceWiseLinInt(AO65, $D$34:$D$35, $A$34:$A$35, FALSE, FALSE) -> #NAME?
F66: 1.55 | G66: =PieceWiseLinInt(F66, $B$34:$B$35, $A$34:$A$35, FALSE, FALSE) -> #NAME? | Z66: 1.5 | AA66: =PieceWiseLinInt(Z66, $C$34:$C$35, $A$34:$A$35, FALSE, FALSE) -> #NAME? | AO66: 1.45 | AP66: =PieceWiseLinInt(AO66, $D$34:$D$35, $A$34:$A$35, FALSE, FALSE) -> #NAME?
F67: 1.6 | G67: =PieceWiseLinInt(F67, $B$34:$B$35, $A$34:$A$35, FALSE, FALSE) -> #NAME? | Z67: 2.5 | AA67: =PieceWiseLinInt(Z67, $C$34:$C$35, $A$34:$A$35, FALSE, FALSE) -> #NAME? | AO67: 1.5 | AP67: =PieceWiseLinInt(AO67, $D$34:$D$35, $A$34:$A$35, FALSE, FALSE) -> #NAME?
F68: 1.65 | G68: =PieceWiseLinInt(F68, $B$34:$B$35, $A$34:$A$35, FALSE, FALSE) -> #NAME? | Z68: 3.5 | AA68: =PieceWiseLinInt(Z68, $C$34:$C$35, $A$34:$A$35, FALSE, FALSE) -> #NAME? | AO68: 2.5 | AP68: =PieceWiseLinInt(AO68, $D$34:$D$35, $A$34:$A$35, FALSE, FALSE) -> #NAME?
F69: 1.7 | G69: =PieceWiseLinInt(F69, $B$34:$B$35, $A$34:$A$35, FALSE, FALSE) -> #NAME? | Z69: 4.5 | AA69: =PieceWiseLinInt(Z69, $C$34:$C$35, $A$34:$A$35, FALSE, FALSE) -> #NAME? | AO69: 3.5 | AP69: =PieceWiseLinInt(AO69, $D$34:$D$35, $A$34:$A$35, FALSE, FALSE) -> #NAME?
F70: 1.75 | G70: =PieceWiseLinInt(F70, $B$34:$B$35, $A$34:$A$35, FALSE, FALSE) -> #NAME? | Z70: 5.5 | AA70: =PieceWiseLinInt(Z70, $C$34:$C$35, $A$34:$A$35, FALSE, FALSE) -> #NAME? | AO70: 4.5 | AP70: =PieceWiseLinInt(AO70, $D$34:$D$35, $A$34:$A$35, FALSE, FALSE) -> #NAME?
F71: 1.8 | G71: =PieceWiseLinInt(F71, $B$34:$B$35, $A$34:$A$35, FALSE, FALSE) -> #NAME? | Z71: 6.5 | AA71: =PieceWiseLinInt(Z71, $C$34:$C$35, $A$34:$A$35, FALSE, FALSE) -> #NAME? | AO71: 5.5 | AP71: =PieceWiseLinInt(AO71, $D$34:$D$35, $A$34:$A$35, FALSE, FALSE) -> #NAME?
... F76: 3 | G76: =PieceWiseLinInt(F76, $B$34:$B$35, $A$34:$A$35, FALSE, FALSE) -> #NAME? | Z76: 11.5 | AA76: =PieceWiseLinInt(Z76, $C$34:$C$35, $A$34:$A$35, FALSE, FALSE) -> #NAME? | AO76: 10.5 | AP76: =PieceWiseLinInt(AO76, $D$34:$D$35, $A$34:$A$35, FALSE, FALSE) -> #NAME?
F77: 4 | G77: =PieceWiseLinInt(F77, $B$34:$B$35, $A$34:$A$35, FALSE, FALSE) -> #NAME? | Z77: 12.5 | AA77: =PieceWiseLinInt(Z77, $C$34:$C$35, $A$34:$A$35, FALSE, FALSE) -> #NAME?
F78: 5 | G78: =PieceWiseLinInt(F78, $B$34:$B$35, $A$34:$A$35, FALSE, FALSE) -> #NAME? | Z78: 13.5 | AA78: =PieceWiseLinInt(Z78, $C$34:$C$35, $A$34:$A$35, FALSE, FALSE) -> #NAME?
F79: 6 | G79: =PieceWiseLinInt(F79, $B$34:$B$35, $A$34:$A$35, FALSE, FALSE) -> #NAME? | Z79: 14.5 | AA79: =PieceWiseLinInt(Z79, $C$34:$C$35, $A$34:$A$35, FALSE, FALSE) -> #NAME?
F80: 7 | G80: =PieceWiseLinInt(F80, $B$34:$B$35, $A$34:$A$35, FALSE, FALSE) -> #NAME? | Z80: 15.5 | AA80: =PieceWiseLinInt(Z80, $C$34:$C$35, $A$34:$A$35, FALSE, FALSE) -> #NAME?
F81: 8 | G81: =PieceWiseLinInt(F81, $B$34:$B$35, $A$34:$A$35, FALSE, FALSE) -> #NAME? | Z81: 16.5 | AA81: =PieceWiseLinInt(Z81, $C$34:$C$35, $A$34:$A$35, FALSE, FALSE) -> #NAME?
F82: 9 | G82: =PieceWiseLinInt(F82, $B$34:$B$35, $A$34:$A$35, FALSE, FALSE) -> #NAME? | Z82: 17.5 | AA82: =PieceWiseLinInt(Z82, $C$34:$C$35, $A$34:$A$35, FALSE, FALSE) -> #NAME?
F83: 10 | G83: =PieceWiseLinInt(F83, $B$34:$B$35, $A$34:$A$35, FALSE, FALSE) -> #NAME? | Z83: 18.5 | AA83: =PieceWiseLinInt(Z83, $C$34:$C$35, $A$34:$A$35, FALSE, FALSE) -> #NAME?
F84: 11 | G84: =PieceWiseLinInt(F84, $B$34:$B$35, $A$34:$A$35, FALSE, FALSE) -> #NAME? | Z84: 19.5 | AA84: =PieceWiseLinInt(Z84, $C$34:$C$35, $A$34:$A$35, FALSE, FALSE) -> #NAME?
F85: 12 | G85: =PieceWiseLinInt(F85, $B$34:$B$35, $A$34:$A$35, FALSE, FALSE) -> #NAME?
F86: 13 | G86: =PieceWiseLinInt(F86, $B$34:$B$35, $A$34:$A$35, FALSE, FALSE) -> #NAME?
F87: 14 | G87: =PieceWiseLinInt(F87, $B$34:$B$35, $A$34:$A$35, FALSE, FALSE) -> #NAME?
F88: 15 | G88: =PieceWiseLinInt(F88, $B$34:$B$35, $A$34:$A$35, FALSE, FALSE) -> #NAME?
F89: 16 | G89: =PieceWiseLinInt(F89, $B$34:$B$35, $A$34:$A$35, FALSE, FALSE) -> #NAME?
F90: 17 | G90: =PieceWiseLinInt(F90, $B$34:$B$35, $A$34:$A$35, FALSE, FALSE) -> #NAME?
F91: 18 | G91: =PieceWiseLinInt(F91, $B$34:$B$35, $A$34:$A$35, FALSE, FALSE) -> #NAME?
F92: 19 | G92: =PieceWiseLinInt(F92, $B$34:$B$35, $A$34:$A$35, FALSE, FALSE) -> #NAME?
F93: 20 | G93: =PieceWiseLinInt(F93, $B$34:$B$35, $A$34:$A$35, FALSE, FALSE) -> #NAME?
F94: 21 | G94: =PieceWiseLinInt(F94, $B$34:$B$35, $A$34:$A$35, FALSE, FALSE) -> #NAME?
F95: 22 | G95: =PieceWiseLinInt(F95, $B$34:$B$35, $A$34:$A$35, FALSE, FALSE) -> #NAME?
F96: 23 | G96: =PieceWiseLinInt(F96, $B$34:$B$35, $A$34:$A$35, FALSE, FALSE) -> #NAME?
... F113: 40 | G113: =PieceWiseLinInt(F113, $B$34:$B$35, $A$34:$A$35, FALSE, FALSE) -> #NAME?

Sheet RSI curves-Stage
B1: Juvenile | C1: Fry | D1: Spawn/eggs
A2: Suitability Index | B2: Depth (m) | C2: Depth (m) | D2: Depth (m)
A3: 0 | B3: 0 | C3: 0 | D3: 0
A4: 0 | B4: 0.25 | C4: 0.249 | D4: 0.09
A5: 0.25 | B5: 0.251 | C5: 0.25 | D5: 0.1
A6: 0.25 | B6: 0.75 | C6: 0.499 | D6: 0.199
A7: 0.5 | B7: 0.751 | C7: 0.5 | D7: 0.2
A8: 0.5 | B8: 1.249 | C8: 0.749 | D8: 0.399
A9: 1 | B9: 1.25 | C9: 0.75 | D9: 0.4
A10: 1 | B10: 1.5 | C10: 1 | D10: 0.5
A16: month | B16: funcNo | C16: Life Stage
A17: 1 | B17: 1 | C17: Spawn/eggs
A18: 2 | B18: 1 | C18: Spawn/eggs
A19: 3 | B19: 2 | C19: Fy
A20: 4 | B20: 2 | C20: Fy
A21: 5 | B21: 2 | C21: Fry
A22: 6 | B22: 2 | C22: Fry
A23: 7 | B23: 2 | C23: Fry
A24: 8 | B24: 2 | C24: Fry
A25: 9 | B25: 3 | C25: Juvenile | AC25: Boltzmann Model.
A26: 10 | B26: 3 | C26: Juvenile
A27: 11 | B27: 3 | C27: Juvenile | AC27: fit = (A+((B-A)/(1+exp((C-x)/D))))
A28: 12 | B28: 3 | C28: Juvenile | K28: Boltzmann Model. | AC28: inv = (C-(D*ln((B-y)/(y-A))))
AC29: res = (y-fit)
K30: fit = (A+((B-A)/(1+exp((C-x)/D))))
K31: inv = (C-(D*ln((B-y)/(y-A))))
K32: res = (y-fit)
A33: RSI | B33: Juvenile | C33: Fry | D33: Spawn/eggs | J33: Model
A34: 0 | B34: 0 | C34: 0 | D34: 0 | F34: Juvenile Depth (m) | G34: Suitability Index | J34: A | K34: =[2]!xf4_ParameterValue(J67,1) -> #NAME? | N34: =[2]!xf4_FitData("",[2]!xf4_SetModel("600"),[2]!xf4_SetParameters(0,FALSE,TRUE,100,FALSE,TRUE,1,FALSE,TRUE,1,FALSE,TRUE),[2]!xf4_SetData(,$F$35:$F$113,,$G$35:$G$113)) -> #NAME? | P34: =[2]!xf4_Chart2D([2]!xf_Init()&[2]!xf_ScaleX(,,,,FALSE)&[2]!xf_ScaleY(,,,,FALSE),[2]!xf4_C2DFit(N34)&[2]!xf4_C2DFitDetails(7,0,0.05,0,0.05)&[2]!xf4_C2DFitPoints(101,,,,1,-1)) -> #NAME? | AD34: Model
A35: 1 | B35: 1.5 | C35: 1 | D35: 0.5 | F35: ='[3]RSI curves'!F35+6.5 -> 6.5 | G35: =PieceWiseLinInt(F35, $B$34:$B$35, $A$34:$A$35, FALSE, FALSE) -> #NAME? | H35: 1 | J35: B | K35: =[2]!xf4_ParameterValue(J67,2) -> #NAME? | Z35: Fry Depth (m) | AA35: Suitability Index | AD35: A | AE35: =[2]!xf4_ParameterValue(AG35,1) -> #NAME? | AG35: =[2]!xf4_FitData("",[2]!xf4_SetModel("600"),[2]!xf4_SetParameters(0,FALSE,TRUE,100,FALSE,TRUE,1,FALSE,TRUE,1,FALSE,TRUE),[2]!xf4_SetData(,$Z$36:$Z$84,,$AB$36:$AB$84)) -> #NAME? | AS35: Model
F36: ='[3]RSI curves'!F36+6.5 -> 6.55 | G36: =PieceWiseLinInt(F36, $B$34:$B$35, $A$34:$A$35, FALSE, FALSE) -> #NAME? | H36: 0.033333333 | J36: C | K36: =[2]!xf4_ParameterValue(J67,3) -> #NAME? | Z36: ='[3]RSI curves'!Z36+6.5 -> 6.5 | AA36: =PieceWiseLinInt(Z36, $C$34:$C$35, $A$34:$A$35, FALSE, FALSE) -> #NAME? | AB36: 0 | AD36: B | AE36: =[2]!xf4_ParameterValue(AG35,2) -> #NAME? | AO36: Spawn Depth (m) | AP36: Suitability Index | AS36: A | AT36: =[2]!xf4_ParameterValue(AW36,1) -> #NAME? | AW36: =[2]!xf4_FitData("",[2]!xf4_SetModel("600"),[2]!xf4_SetParameters(0,FALSE,TRUE,100,FALSE,TRUE,1,FALSE,FALSE,1,FALSE,TRUE),[2]!xf4_SetData(,$AO$37:$AO$76,,$AQ$37:$AQ$76)) -> #NAME?
F37: ='[3]RSI curves'!F37+6.5 -> 6.6 | G37: =PieceWiseLinInt(F37, $B$34:$B$35, $A$34:$A$35, FALSE, FALSE) -> #NAME? | H37: 0.066666667 | J37: D | K37: =[2]!xf4_ParameterValue(J67,4) -> #NAME? | Z37: ='[3]RSI curves'!Z37+6.5 -> 6.55 | AA37: =PieceWiseLinInt(Z37, $C$34:$C$35, $A$34:$A$35, FALSE, FALSE) -> #NAME? | AB37: 0.05 | AD37: C | AE37: =[2]!xf4_ParameterValue(AG35,3) -> #NAME? | AO37: ='[3]RSI curves'!AO37+6.5 -> 6.5 | AP37: =PieceWiseLinInt(AO37, $D$34:$D$35, $A$34:$A$35, FALSE, FALSE) -> #NAME? | AQ37: 0 | AS37: B | AT37: =[2]!xf4_ParameterValue(AW36,2) -> #NAME?
F38: ='[3]RSI curves'!F38+6.5 -> 6.65 | G38: =PieceWiseLinInt(F38, $B$34:$B$35, $A$34:$A$35, FALSE, FALSE) -> #NAME? | H38: 0.1 | Z38: ='[3]RSI curves'!Z38+6.5 -> 6.6 | AA38: =PieceWiseLinInt(Z38, $C$34:$C$35, $A$34:$A$35, FALSE, FALSE) -> #NAME? | AB38: 0.1 | AD38: D | AE38: =[2]!xf4_ParameterValue(AG35,4) -> #NAME? | AG38: =[2]!xf4_Chart2D([2]!xf_Init()&[2]!xf_ScaleX(,,,,FALSE)&[2]!xf_ScaleY(,,,,FALSE),[2]!xf4_C2DFit(AG35)) -> #NAME? | AO38: ='[3]RSI curves'!AO38+6.5 -> 6.55 | AP38: =PieceWiseLinInt(AO38, $D$34:$D$35, $A$34:$A$35, FALSE, FALSE) -> #NAME? | AQ38: 0.1 | AS38: C | AT38: =[2]!xf4_ParameterValue(AW36,3) -> #NAME? | AW38: =[2]!xf4_Chart2D([2]!xf_Init()&[2]!xf_ScaleX(,,,,FALSE)&[2]!xf_ScaleY(,,,,FALSE),[2]!xf4_C2DFit(AW36)) -> #NAME?
F39: ='[3]RSI curves'!F39+6.5 -> 6.7 | G39: =PieceWiseLinInt(F39, $B$34:$B$35, $A$34:$A$35, FALSE, FALSE) -> #NAME? | H39: 0.13333333 | Z39: ='[3]RSI curves'!Z39+6.5 -> 6.65 | AA39: =PieceWiseLinInt(Z39, $C$34:$C$35, $A$34:$A$35, FALSE, FALSE) -> #NAME? | AB39: 0.15 | AO39: ='[3]RSI curves'!AO39+6.5 -> 6.6 | AP39: =PieceWiseLinInt(AO39, $D$34:$D$35, $A$34:$A$35, FALSE, FALSE) -> #NAME? | AQ39: 0.2 | AS39: D | AT39: =[2]!xf4_ParameterValue(AW36,4) -> #NAME?
F40: ='[3]RSI curves'!F40+6.5 -> 6.75 | G40: =PieceWiseLinInt(F40, $B$34:$B$35, $A$34:$A$35, FALSE, FALSE) -> #NAME? | H40: 0.16666667 | Z40: ='[3]RSI curves'!Z40+6.5 -> 6.7 | AA40: =PieceWiseLinInt(Z40, $C$34:$C$35, $A$34:$A$35, FALSE, FALSE) -> #NAME? | AB40: 0.2 | AO40: ='[3]RSI curves'!AO40+6.5 -> 6.65 | AP40: =PieceWiseLinInt(AO40, $D$34:$D$35, $A$34:$A$35, FALSE, FALSE) -> #NAME? | AQ40: 0.3
F41: ='[3]RSI curves'!F41+6.5 -> 6.8 | G41: =PieceWiseLinInt(F41, $B$34:$B$35, $A$34:$A$35, FALSE, FALSE) -> #NAME? | H41: 0.2 | J41: Depth | K41: 6.5 | Z41: ='[3]RSI curves'!Z41+6.5 -> 6.75 | AA41: =PieceWiseLinInt(Z41, $C$34:$C$35, $A$34:$A$35, FALSE, FALSE) -> #NAME? | AB41: 0.25 | AO41: ='[3]RSI curves'!AO41+6.5 -> 6.7 | AP41: =PieceWiseLinInt(AO41, $D$34:$D$35, $A$34:$A$35, FALSE, FALSE) -> #NAME? | AQ41: 0.4
F42: ='[3]RSI curves'!F42+6.5 -> 6.85 | G42: =PieceWiseLinInt(F42, $B$34:$B$35, $A$34:$A$35, FALSE, FALSE) -> #NAME? | H42: 0.23333333 | J42: RSI | K42: =(K34+((K35-K34)/(1+EXP((K36-K41)/K37)))) -> #NAME? | Z42: ='[3]RSI curves'!Z42+6.5 -> 6.8 | AA42: =PieceWiseLinInt(Z42, $C$34:$C$35, $A$34:$A$35, FALSE, FALSE) -> #NAME? | AB42: 0.3 | AD42: Depth | AE42: 0 | AO42: ='[3]RSI curves'!AO42+6.5 -> 6.75 | AP42: =PieceWiseLinInt(AO42, $D$34:$D$35, $A$34:$A$35, FALSE, FALSE) -> #NAME? | AQ42: 0.5
F43: ='[3]RSI curves'!F43+6.5 -> 6.9 | G43: =PieceWiseLinInt(F43, $B$34:$B$35, $A$34:$A$35, FALSE, FALSE) -> #NAME? | H43: 0.26666667 | Z43: ='[3]RSI curves'!Z43+6.5 -> 6.85 | AA43: =PieceWiseLinInt(Z43, $C$34:$C$35, $A$34:$A$35, FALSE, FALSE) -> #NAME? | AB43: 0.35 | AD43: RSI | AE43: =(AE35+((AE36-AE35)/(1+EXP((AE37-AE42)/AE38)))) -> #NAME? | AO43: ='[3]RSI curves'!AO43+6.5 -> 6.8 | AP43: =PieceWiseLinInt(AO43, $D$34:$D$35, $A$34:$A$35, FALSE, FALSE) -> #NAME? | AQ43: 0.6 | AS43: Depth | AT43: -10
F44: ='[3]RSI curves'!F44+6.5 -> 6.95 | G44: =PieceWiseLinInt(F44, $B$34:$B$35, $A$34:$A$35, FALSE, FALSE) -> #NAME? | H44: 0.3 | Z44: ='[3]RSI curves'!Z44+6.5 -> 6.9 | AA44: =PieceWiseLinInt(Z44, $C$34:$C$35, $A$34:$A$35, FALSE, FALSE) -> #NAME? | AB44: 0.4 | AO44: ='[3]RSI curves'!AO44+6.5 -> 6.85 | AP44: =PieceWiseLinInt(AO44, $D$34:$D$35, $A$34:$A$35, FALSE, FALSE) -> #NAME? | AQ44: 0.7 | AS44: RSI | AT44: =(AT36+((AT37-AT36)/(1+EXP((AT38-AT43)/AT39)))) -> #NAME?
F45: ='[3]RSI curves'!F45+6.5 -> 7 | G45: =PieceWiseLinInt(F45, $B$34:$B$35, $A$34:$A$35, FALSE, FALSE) -> #NAME? | H45: 0.33333333 | Z45: ='[3]RSI curves'!Z45+6.5 -> 6.95 | AA45: =PieceWiseLinInt(Z45, $C$34:$C$35, $A$34:$A$35, FALSE, FALSE) -> #NAME? | AB45: 0.45 | AO45: ='[3]RSI curves'!AO45+6.5 -> 6.9 | AP45: =PieceWiseLinInt(AO45, $D$34:$D$35, $A$34:$A$35, FALSE, FALSE) -> #NAME? | AQ45: 0.8
F46: ='[3]RSI curves'!F46+6.5 -> 7.05 | G46: =PieceWiseLinInt(F46, $B$34:$B$35, $A$34:$A$35, FALSE, FALSE) -> #NAME? | H46: 0.36666667 | J46: Copy | Z46: ='[3]RSI curves'!Z46+6.5 -> 7 | AA46: =PieceWiseLinInt(Z46, $C$34:$C$35, $A$34:$A$35, FALSE, FALSE) -> #NAME? | AB46: 0.5 | AO46: ='[3]RSI curves'!AO46+6.5 -> 6.95 | AP46: =PieceWiseLinInt(AO46, $D$34:$D$35, $A$34:$A$35, FALSE, FALSE) -> #NAME? | AQ46: 0.9
F47: ='[3]RSI curves'!F47+6.5 -> 7.1 | G47: =PieceWiseLinInt(F47, $B$34:$B$35, $A$34:$A$35, FALSE, FALSE) -> #NAME? | H47: 0.4 | J47: A | K47: 0.23057142 | Z47: ='[3]RSI curves'!Z47+6.5 -> 7.05 | AA47: =PieceWiseLinInt(Z47, $C$34:$C$35, $A$34:$A$35, FALSE, FALSE) -> #NAME? | AB47: 0.55 | AO47: ='[3]RSI curves'!AO47+6.5 -> 7 | AP47: =PieceWiseLinInt(AO47, $D$34:$D$35, $A$34:$A$35, FALSE, FALSE) -> #NAME? | AQ47: 1
F48: ='[3]RSI curves'!F48+6.5 -> 7.15 | G48: =PieceWiseLinInt(F48, $B$34:$B$35, $A$34:$A$35, FALSE, FALSE) -> #NAME? | H48: 0.43333333 | J48: B | K48: 1.0031481 | Z48: ='[3]RSI curves'!Z48+6.5 -> 7.1 | AA48: =PieceWiseLinInt(Z48, $C$34:$C$35, $A$34:$A$35, FALSE, FALSE) -> #NAME? | AB48: 0.6 | AO48: ='[3]RSI curves'!AO48+6.5 -> 7.05 | AP48: =PieceWiseLinInt(AO48, $D$34:$D$35, $A$34:$A$35, FALSE, FALSE) -> #NAME? | AQ48: 1
F49: ='[3]RSI curves'!F49+6.5 -> 7.2 | G49: =PieceWiseLinInt(F49, $B$34:$B$35, $A$34:$A$35, FALSE, FALSE) -> #NAME? | H49: 0.46666667 | J49: C | K49: 7.4282764 | Z49: ='[3]RSI curves'!Z49+6.5 -> 7.15 | AA49: =PieceWiseLinInt(Z49, $C$34:$C$35, $A$34:$A$35, FALSE, FALSE) -> #NAME? | AB49: 0.65 | AD49: Copy | AO49: ='[3]RSI curves'!AO49+6.5 -> 7.1 | AP49: =PieceWiseLinInt(AO49, $D$34:$D$35, $A$34:$A$35, FALSE, FALSE) -> #NAME? | AQ49: 1
